Workbook
Name cat1_opt_eval: #REF!
Name cat1_opt_score: #REF!
Name cat1_pref_eval: #REF!
Name cat1_pref_score: #REF!
Name cat1_req_eval: #REF!
Name cat1_req_score: #REF!
Name cat10_opt_eval: #REF!
Name cat10_opt_score: #REF!
Name cat10_pref_eval: #REF!
Name cat10_pref_score: #REF!
Name cat10_req_eval: #REF!
Name cat10_req_score: #REF!
Name cat2_opt_eval: #REF!
Name cat2_opt_score: #REF!
Name cat2_pref_eval: #REF!
Name cat2_pref_score: #REF!
Name cat2_req_eval: #REF!
Name cat2_req_score: #REF!
Name cat3_opt_eval: #REF!
Name cat3_opt_score: #REF!
Name cat3_pref_eval: #REF!
Name cat3_pref_score: #REF!
Name cat3_req_eval: #REF!
Name cat3_req_score: #REF!
Name cat4_opt_eval: #REF!
Name cat4_opt_score: #REF!
Name cat4_pref_eval: #REF!
Name cat4_pref_score: #REF!
Name cat4_req_eval: #REF!
Name cat4_req_score: #REF!
Name cat5_opt_eval: #REF!
Name cat5_opt_score: #REF!
Name cat5_pref_eval: #REF!
Name cat5_pref_score: #REF!
Name cat5_req_eval: #REF!
Name cat5_req_score: #REF!
Name cat6_opt_eval: #REF!
Name cat6_opt_score: #REF!
Name cat6_pref_eval: #REF!
Name cat6_pref_score: #REF!
Name cat6_req_eval: #REF!
Name cat6_req_score: #REF!
Name cat7_opt_eval: #REF!
Name cat7_opt_score: #REF!
Name cat7_pref_eval: #REF!
Name cat7_pref_score: #REF!
Name cat7_req_eval: #REF!
Name cat7_req_score: #REF!
Name cat8_opt_eval: #REF!
Name cat8_opt_score: #REF!
Name cat8_pref_eval: #REF!
Name cat8_pref_score: #REF!
Name cat8_req_eval: #REF!
Name cat8_req_score: #REF!
Name cat9_opt_eval: #REF!
Name cat9_opt_score: #REF!
Name cat9_pref_eval: #REF!
Name cat9_pref_score: #REF!
Name cat9_req_eval: #REF!
Name cat9_req_score: #REF!

Sheet Instructions
A1: Business Priorities - Readiness Alignment Tool
A3: Purpose:
A4: Define Business Case priority objectives and quantify current state alignment with those objectives. At the conclusion of the Business Case and CRA discovery the information collected quantifies business objectives and provides a comparative of current state people, process, and technology capabilities that support the achievement of the business objectives.
A6: Overview:
A7: 1. Inputs: a. Business Case Priorities Workshop.pptx b. Business Case - Current State Business Alignment Workshop.pptx 2. There are two sections in each perspective tab that records the inputs from the workshop PowerPoints; 1) Business Case objectives and priorities and 2) CRA across six business function perspectives. Each worksheet perspective tab has a Business Priority score card and a Current State scorecard. 2. The Busines Priority uses a 0 - 4 scale and the Current State uses a 0 - 3 scale. Because the number of questions/answers is different across perspectives, the scales are normalized to a base 10 scorecard for comparison. 3. The formulas in the perspective tabs automatically count the the number of questions/answers, sum the results, and convert the result into a consistent base 10 ranking. 4. The Busines Priority and Current State input are summarized and charted in the Scoring and Charts tab. 5. Additional questions and answers can easily be added. Insert a new row in the middle of the section and add the text and copy the sum() function down in columns G or F as appropriate. This will assure that the formulas pick up the new row and update - a row added at the top or bottom of the an Excel computational range is not always picked up by the formula. Once the row is inserted you can reoder the questions in the range.
A9: Version History
A10: v1 1/13/2023 - Jim Leonard - Initial template draft for review and comment.

Sheet Scoring and Charts
C1: Business Case - Readiness Alignment
D4: Business Priority | E4: Current State
D5: Ranking | E5: Value
C6: Platform | D6: =Platform!I11 | E6: =Platform!I27
C7: Security | D7: =Security!I8 | E7: =Security!I26
C8: Ways of Working | D8: ='Ways of Working'!I5 | E8: ='Ways of Working'!I17
C9: Operations | D9: =Operations!I10 | E9: =Operations!I29
C10: Financial | D10: ='Cost Management'!I7 | E10: ='Cost Management'!I17
C11: Data Management | D11: ='Data Management'!I9 | E11: ='Data Management'!I26

Sheet Platform
A1: Platform – practices for handling infrastructure and application architecture so that the eco-system maintains its integrity over time. It implements the policies, procedures, techniques, and tools that manage system change.
A2: Business Priority | B2: Don't know (0) | C2: Not Important (1) | D2: Somewhat important (2) | E2: Very Important (3) | F2: Critical (4) | G2: Score | H2: Max Value | I2: Adjusted Value
A3: Architectural alignment with overall business goals and objectives. | F3: 4 | G3: =SUM(B3:F3)
A4: Standards and guidelines for the design and implementation of cloud-based solutions. | E4: 3 | G4: =SUM(B4:F4)
A5: Rapid development and time to market of new products and services. | E5: 3 | G5: =SUM(B5:F5)
A6: Modernizing applications to take advantage of cloud services. | F6: 4 | G6: =SUM(B6:F6)
A7: Tool standardization across the enterprise. | E7: 3 | G7: =SUM(B7:F7)
A8: DevOps as an important strategic initiative. | E8: 3 | G8: =SUM(B8:F8)
A9: A self-service model using a Service Catalog. | D9: 2 | G9: =SUM(B9:F9)
A10: Business data analytics as a strategic enabler. | E10: 3 | G10: =SUM(B10:F10)
A11: Business Priority Score: | G11: =SUM(G3:G10) | H11: =COUNTIF(A3:A10,"*")*4 | I11: =G11/H11*10
A15: Current State | B15: Does not exist (0) | C15: Exists, but not formalized (1) | D15: Formalized, but needs development (2) | E15: Formalized and performing (3) | F15: Score | H15: Max Value | I15: Max Value
A16: We have a cross-functional architecture oversight group to review landing zones, account structures, and architecture changes. | C16: 1 | F16: =SUM(B16:E16)
A17: There is a standard cloud account creation process. | D17: 2 | F17: =SUM(B17:E17)
A18: We have defined processes to manage source code, third party artifacts, images and libraries. | C18: 1 | F18: =SUM(B18:E18)
A19: Internal staff are experienced with DevSecOps concepts and implementation techniques. | B19: 0 | F19: =SUM(B19:E19)
A20: There are defined CI/CD pipelines. | B20: 0 | F20: =SUM(B20:E20)
A21: There are automated build processes for standard infrastructure components. | B21: 0 | F21: =SUM(B21:E21)
A22: We use automated application testing tools. | B22: 0 | F22: =SUM(B22:E22)
A23: We use metrics to evaluate pipeline efficiency (Frequency, Change Failure Rate, Mean Time to Restore, Lead Time for Changes). | B23: 0 | F23: =SUM(B23:E23)
A24: We leverage automation tools to ensure resource deployments are scripted and orchestrated. | B24: 0 | F24: =SUM(B24:E24)
A25: A Service Catalog and on demand self-service has been adopted. | B25: 0 | F25: =SUM(B25:E25)
A26: Data management and business analytics processes are in place. | B26: 0 | F26: =SUM(B26:E26)
A27: Current State Value: | F27: =SUM(F16:F26) | H27: =COUNTIF(A17:A26,"*")*3 | I27: =(F27/H27)*10

Sheet Security
A1: Security – processes to ensure that security and compliance requirements are consistently applied to cloud environments, especially as requirements mature.
A2: Business Priority | B2: Don't know (0) | C2: Not Important (1) | D2: Somewhat important (2) | E2: Very Important (3) | F2: Critical (4) | G2: Score | H2: Max Value | I2: Adjusted Value
A3: Preventing exploits by continuously monitoring and applying security recommendations across machines, networks, and services. | F3: 4 | G3: =SUM(B3:F3)
A4: Preventing loss or leaks of data, including Personally Identifiable information (PII) or other forms of high priority data. | F4: 4 | G4: =SUM(B4:F4)
A5: Stopping unauthorized traffic or other forms of intrusion that could compromise the network or other IT assets. | F5: 4 | G5: =SUM(B5:F5)
A6: Conducting regular review of access rights and recurring access recertification configuration for all users in administrator roles. | E6: 3 | G6: =SUM(B6:F6)
A7: Enabling just-in-time access, and role change alerting capabilities to provide a comprehensive set of governance controls to help secure company's resources | E7: 3 | G7: =SUM(B7:F7)
A8: Business Priority Score: | G8: =SUM(G3:G7) | H8: =COUNTIF(A3:A7,"*")*4 | I8: =G8/H8*10
A12: Current State | B12: Does not exist (0) | C12: Exists, but not formalized (1) | D12: Formalized, but needs development (2) | E12: Formalized and performing (3) | F12: Score | H12: Max Value | I12: Max Value
A13: We have processes in place to ensure production resources have the right security and audit safeguards. | C13: 1 | F13: =SUM(B13:E13)
A14: We have implemented a data classification and access policy model, to ensure that only the right individuals have access to high business impact data. | C14: 1 | F14: =SUM(B14:E14)
A15: Our data classification aligns with security measures in place to protect sensitive information. | C15: 1 | F15: =SUM(B15:E15)
A16: Data is always encrypted at rest. | D16: 2 | F16: =SUM(B16:E16)
A17: Data is always encrypted in transit. | D17: 2 | F17: =SUM(B17:E17)
A18: We use tools to look for patterns in the data that might indicate malicious activity. | C18: 1 | F18: =SUM(B18:E18)
A19: Network intrusion detection is setup to ensure only required ports and routes are open. | C19: 1 | F19: =SUM(B19:E19)
A20: Security for the machines, networks and services are continuously monitored, and we use actionable security recommendations to remediate issues before they can be exploited. | D20: 2 | F20: =SUM(B20:E20)
A21: Our identity tools are constantly scanning the environment for malicious actors. | C21: 1 | F21: =SUM(B21:E21)
A22: We effectively use RBAC to manage access. | C22: 1 | F22: =SUM(B22:E22)
A23: Our Identity Baseline process is setup to ensure least privilege access. | C23: 1 | F23: =SUM(B23:E23)
A24: We use a single centralized identity provider for all apps. | D24: 2 | F24: =SUM(B24:E24)
A25: We periodically audit our identity policies and privileged accounts. | D25: 2 | F25: =SUM(B25:E25)
A26: Current State Value: | F26: =SUM(F13:F25) | H26: =COUNTIF(A13:A25,"*")*3 | I26: =(F26/H26)*10

Sheet Ways of Working
A1: Ways of Working – the degree to which your people, roles, skills, and policies support cloud adoption.
A2: Business Priority | B2: Don't know (0) | C2: Not Important (1) | D2: Somewhat important (2) | E2: Very Important (3) | F2: Critical (4) | G2: Score | H2: Max Value | I2: Adjusted Value
A3: Having executive leadership actively support large change initiatives and help remove barriers. | F3: 4 | G3: =SUM(B3:F3)
A4: Establishing a cross-functional organization structure that supports collaborative strategic roadmap development. | E4: 3 | G4: =SUM(B4:F4)
A5: Business Priority Score: | G5: =SUM(G3:G4) | H5: =COUNTIF(A3:A4,"*")*4 | I5: =G5/H5*10
A9: Current State | B9: Does not exist (0) | C9: Exists, but not formalized (1) | D9: Formalized, but needs development (2) | E9: Formalized and performing (3) | F9: Score | H9: Max Value | I9: Max Value
A10: We have a dedicated Cloud Strategy team that consists of influencers from Finance, impacted Line of Business units, and Technical Architects. | B10: 0 | F10: =SUM(B10:E10)
A11: We have an established structure with representation from Business, Finance, and IT to advocate, support and influence across the company. | B11: 0 | F11: =SUM(B11:E11)
A12: We have a dedicated Cloud Governance team that consists of subject matter experts from Security, IT Ops and Business Decision Makers to assess business risks and tolerance levels. | B12: 0 | F12: =SUM(B12:E12)
A13: We have a dedicated Cloud Migration team that consists of subject matter experts that have strong awareness of current technical estate. | B13: 0 | F13: =SUM(B13:E13)
A14: We have top down support and push to adopt the cloud. | E14: 3 | F14: =SUM(B14:E14)
A15: We have adequate training for our developers to ensure they are building safe apps that prevent Common Vulnerabilities & Exposures (CVEs). | B15: 0 | F15: =SUM(B15:E15)
A16: We have professional development plans to enable team members to maintain and grow their skills. | B16: 0 | F16: =SUM(B16:E16)
A17: Current State Value: | F17: =SUM(F10:F16) | H17: =COUNTIF(A10:A16,"*")*3 | I17: =(F17/H17)*10

Sheet Operations
A1: Operations - methods to establish policies related to the operational management of an environment, application, or workload. It ensures that resources are consistently configured to be discoverable by IT, included in recovery solutions, and on-boarded into repeatable processes.
A2: Business Priority | B2: Don't know (0) | C2: Not Important (1) | D2: Somewhat important (2) | E2: Very Important (3) | F2: Critical (4) | G2: Score | H2: Max Value | I2: Adjusted Value
A3: Knowing and understanding available resource and define resources deployment. | E3: 3 | G3: =SUM(B3:F3)
A4: Deploying, managing and monitoring all resources by business unit, solution, workload, or application. | E4: 3 | G4: =SUM(B4:F4)
A5: Ensuring stability, performance, uptime across applications, workloads, and solutions that support the business. | F5: 4 | G5: =SUM(B5:F5)
A6: Speed to remediation of performance or uptime for mission critical applications, workloads, or solutions | F6: 4 | G6: =SUM(B6:F6)
A7: Having a holistic view to manage users across the enterprise with a single identity and sign-on. | E7: 3 | G7: =SUM(B7:F7)
A8: Having processes in place to restore applications with no business impact and data loss. | F8: 4 | G8: =SUM(B8:F8)
A9: Speed of recovery from a disaster or business continuity event. | F9: 4 | G9: =SUM(B9:F9)
A10: Business Priority Score: | G10: =SUM(G3:G9) | H10: =COUNTIF(A3:A9,"*")*4 | I10: =G10/H10*10
A14: Current State | B14: Does not exist (0) | C14: Exists, but not formalized (1) | D14: Formalized, but needs development (2) | E14: Formalized and performing (3) | F14: Score | H14: Max Value | I14: Max Value
A15: All resources related to a single application or single type are managed collectively. | C15: 1 | F15: =SUM(B15:E15)
A16: We have a formal process to control and approve changes. | E16: 3 | F16: =SUM(B16:E16)
A17: We backup our data and verify the integrity of the restore process. | C17: 1 | F17: =SUM(B17:E17)
A18: System and software changes undergo functional and performance testing prior to Production release. | B18: 0 | F18: =SUM(B18:E18)
A19: We continually monitor resource and systems performance. | B19: 0 | F19: =SUM(B19:E19)
A20: Our subscription and tagging strategies align with cloud accounting models, deployment needs, and resource consistency policies. | D20: 2 | F20: =SUM(B20:E20)
A21: We have processes in place to identify configuration drift. | B21: 0 | F21: =SUM(B21:E21)
A22: We have a formal process for managing the hardening of OS images. | C22: 1 | F22: =SUM(B22:E22)
A23: We leverage automation tools to ensure resource deployments are scripted and orchestrated. | B23: 0 | F23: =SUM(B23:E23)
A24: We have a formal process for patch application and vulnerability detection. | D24: 2 | F24: =SUM(B24:E24)
A25: We have a clear process to understand Role definitions and Role assignments to manage access to resources. | D25: 2 | F25: =SUM(B25:E25)
A26: We have worked with the business to document business risk & acceptable recovery times (RTO/RPO). | B26: 0 | F26: =SUM(B26:E26)
A27: We have formal processes in place to restore applications. | B27: 0 | F27: =SUM(B27:E27)
A28: We have documented Disaster Recovery (DR) plans and periodically test our capabilities. | B28: 0 | F28: =SUM(B28:E28)
A29: Current State Value: | F29: =SUM(F15:F28) | H29: =COUNTIF(A15:A28,"*")*3 | I29: =(F29/H29)*10

Sheet Cost Management
A1: Cost Management - Process to effectively plan and control costs involved in adopting cloud technologies. Tasks are normally performed by finance, management, and app development teams.
A2: Business Priority | B2: Don't know (0) | C2: Not Important (1) | D2: Somewhat important (2) | E2: Very Important (3) | F2: Critical (4) | G2: Score | H2: Max Value | I2: Adjusted Value
A3: Creating comprehensive plans to (a) identify business outcomes enabled by the cloud and (b) identify expected usage/cost patterns from resources supporting those business outcomes. | E3: 3 | G3: =SUM(B3:F3)
A4: Helping find underused resources to remove wastage and maximize cost saving opportunities. | E4: 3 | G4: =SUM(B4:F4)
A5: Organizing resources to maximize insights into cost attribution (and business impact) to have accountability for efficient spending. | E5: 3 | G5: =SUM(B5:F5)
A6: Leveraging tagging feature to categorize resources for managing and billing to reduce unnecessary costs in subscriptions. | F6: 4 | G6: =SUM(B6:F6)
A7: Business Priority Score: | G7: =SUM(G3:G6) | H7: =COUNTIF(A3:A6,"*")*4 | I7: =G7/H7*10
A11: Current State | B11: Does not exist (0) | C11: Exists, but not formalized (1) | D11: Formalized, but needs development (2) | E11: Formalized and performing (3) | F11: Score | H11: Max Value | I11: Max Value
A12: We understand the accounting change from Capital expense (CapEx) to Operating Expense (OpEx) and have a funding process for projects. | C12: 1 | F12: =SUM(B12:E12)
A13: We have a well-developed cost model, and we can effectively manage plan vs. actual spend. | C13: 1 | F13: =SUM(B13:E13)
A14: We have a clear understanding of our current spend trajectory and how to manage spikes. | B14: 0 | F14: =SUM(B14:E14)
A15: We have a documented and agreed to policy for cost allocation, shared costs across the organization and costs specific to a project. | D15: 2 | F15: =SUM(B15:E15)
A16: When architecting solutions, we conduct cost tradeoff analysis of each option and it factors into our decision | D16: 2 | F16: =SUM(B16:E16)
A17: Current State Value: | F17: =SUM(F12:F16) | H17: =COUNTIF(A12:A16,"*")*3 | I17: =(F17/H17)*10

Sheet Data Management
A1: Data Management - Policies and processes for data life cycle management, access and visibility, and compliance.
A2: Business Priority | B2: Don't know (0) | C2: Not Important (1) | D2: Somewhat important (2) | E2: Very Important (3) | F2: Critical (4) | G2: Score | H2: Max Value | I2: Adjusted Value
A3: Data as an asset and competitive advantage. | E3: 3 | G3: =SUM(B3:F3)
A4: Clear data ownership across the organization. | E4: 3 | G4: =SUM(B4:F4)
A5: Concern with cybersecurity and data breaches. | F5: 4 | G5: =SUM(B5:F5)
A6: Driving innovation and new products with data. | E6: 3 | G6: =SUM(B6:F6)
A7: Adoption of Machine Learning and AI. | D7: 2 | G7: =SUM(B7:F7)
A8: A well articulated and holistic data strategy (Pain points of data fragmentation, lack of reusability, manual data quality checks, lack of data products). | E8: 3 | G8: =SUM(B8:F8)
A9: Business Priority Score: | G9: =SUM(G3:G8) | H9: =COUNTIF(A3:A8,"*")*4 | I9: =G9/H9*10
A13: Current State | B13: Does not exist (0) | C13: Exists, but not formalized (1) | D13: Formalized, but needs development (2) | E13: Formalized and performing (3) | F13: Score | H13: Max Value | I13: Max Value
A14: We have a data management plan. | C14: 1 | F14: =SUM(B14:E14)
A15: A data privacy policy exists. | C15: 1 | F15: =SUM(B15:E15)
A16: Data compliance requirements are defined. | C16: 1 | F16: =SUM(B16:E16)
A17: Data life cycle policies are in place for data retention, archiving, expiration/disposal/destruction. | C17: 1 | F17: =SUM(B17:E17)
A18: Data is classified and tagged (criticality and severity) PII, PCI/DSS, Intellectual Property. | C18: 1 | F18: =SUM(B18:E18)
A19: Data owners, roles, and responsibilities are identified. | C19: 1 | F19: =SUM(B19:E19)
A20: Application workloads are aligned to data classifications. | D20: 2 | F20: =SUM(B20:E20)
A21: Data life cycle is automated and storage types leveraged (hot – warm – cold) to save costs. | B21: 0 | F21: =SUM(B21:E21)
A22: We have a backup/snapshot retention policy, | C22: 1 | F22: =SUM(B22:E22)
A23: Organization accounts are structured to segment and isolate data (PII, financial). | C23: 1 | F23: =SUM(B23:E23)
A24: User groups and roles are used to control data access. | D24: 2 | F24: =SUM(B24:E24)
A25: Data boundaries and DLP policies are in place. | D25: 2 | F25: =SUM(B25:E25)
A26: Current State Value: | F26: =SUM(F14:F25) | H26: =COUNTIF(A14:A25,"*")*3 | I26: =(F26/H26)*10

Sheet Gap Register
A1: Cloud Governance Gap Register — Gaps to Close Before or During Part 2
A2: Gap ID | B2: Domain | C2: Gap Description | D2: Business Risk if Not Closed | E2: Recommended Action | F2: Priority | G2: Part 2 Dependency?
A3: G001 | B3: Identity & Access Management | C3: No RBAC model defined for cloud subscriptions | D3: Uncontrolled access to cloud resources; audit failure | E3: Design Azure RBAC / AWS IAM policy framework in Part 2 landing zone | F3: Critical | G3: Yes
A4: G002 | B4: Cost Management | C4: No FinOps process — cloud costs will not be allocated by BU | D4: Cloud cost overrun with no accountability; finance unable to attribute spend | E4: Implement tagging strategy and cost allocation model in landing zone | F4: High | G4: Yes
A5: G003 | B5: Change Management | C5: CAB lead time 10+ business days — blocks Phase 1 discovery | D5: Phase 1 delayed if firewall change not submitted on Day 1 | E5: Submit CAB pre-engagement; target dedicated cloud change category | F5: Critical | G5: No (Phase 1 action)
A6: G004 | B6: Monitoring & Observability | C6: No cloud-native monitoring capability — Dynatrace on-prem only | D6: Cloud workloads will not be monitored post-migration | E6: Deploy Azure Monitor / AWS CloudWatch / GCP Cloud Operations in Part 2 | F6: High | G6: Yes

Sheet Summary Dashboard
A1: Cloud Governance Maturity — Executive Summary Dashboard
A2: Governance Domain | B2: Current Maturity (1-5) | C2: Target Maturity (1-5) | D2: Status
A3: Identity & Access Management | B3: [Score from assessment tab] | C3: [Target score] | D3: [ ] Review maturity tabs and enter scores
A4: Security & Compliance | B4: [Score from assessment tab] | C4: [Target score] | D4: [ ] Review maturity tabs and enter scores
A5: Change Management | B5: [Score from assessment tab] | C5: [Target score] | D5: [ ] Review maturity tabs and enter scores
A6: Monitoring & Observability | B6: [Score from assessment tab] | C6: [Target score] | D6: [ ] Review maturity tabs and enter scores
A7: Cost Management (FinOps) | B7: [Score from assessment tab] | C7: [Target score] | D7: [ ] Review maturity tabs and enter scores
A8: Operational Readiness | B8: [Score from assessment tab] | C8: [Target score] | D8: [ ] Review maturity tabs and enter scores
A10: Overall Assessment Note:
A11: [Enter overall governance readiness narrative for this customer. Reference the Gap Register for remediation roadmap.]

Sheet CAF-WAF-GAF Alignment
A1: Framework Alignment — CAF / AWS WAF / Google Cloud Architecture Framework
A2: Governance Domain | B2: CAF Stage / Pillar | C2: AWS WAF Pillar | D2: GCAF Pillar | E2: CRA Output
A3: Identity & Access Management | B3: CAF: Ready — Identity Management | C3: Security (IAM) | D3: Security, Privacy, Compliance | E3: Governance Maturity score + Gap Register → informs landing zone IAM design
A4: Security & Compliance | B4: CAF: Ready — Security Baseline | C4: Security | D4: Security, Privacy, Compliance | E4: Compliance requirements captured → cloud region constraints in TCO
A5: Change Management | B5: CAF: Plan — Platform Automation | C5: Operational Excellence | D5: Operational Excellence | E5: CAB lead time documented → Phase 1 risk register item
A6: Monitoring & Observability | B6: CAF: Manage — Management Baseline | C6: Operational Excellence | D6: Operational Excellence | E6: Monitoring gap → Part 2 landing zone tooling requirement
A7: Cost Management (FinOps) | B7: CAF: Govern — Cost Management | C7: Cost Optimisation | D7: Cost Optimisation | E7: FinOps maturity → TCO Layer (g) partner credits visibility
A8: Operational Readiness | B8: CAF: Manage | C8: Reliability | D8: Reliability | E8: RTO/RPO requirements → Business Criticality scores in readiness template
