Workbook
Name altcostAdv: [1]Costs!$AH$48:$AT$57
Name altcostAdv: PriceTbls!$AJ$48:$AV$57
Name altcostAdv: Costs!$AJ$51:$AV$60
Name altcostAps: [1]Costs!$AH$4:$AT$13
Name altcostAps: PriceTbls!$AJ$4:$AV$13
Name altcostAps: Costs!$AJ$4:$AV$13
Name altcostData: [1]Costs!$AH$18:$AT$27
Name altcostData: PriceTbls!$AJ$18:$AV$27
Name altcostData: Costs!$AJ$18:$AV$27
Name altcostErp: [1]Costs!$AH$111:$AT$122
Name altcostErp: PriceTbls!$AJ$111:$AV$122
Name altcostErp: Costs!$AJ$114:$AV$125
Name altcostProd: [1]Costs!$AH$63:$AT$72
Name altcostProd: PriceTbls!$AJ$63:$AV$72
Name altcostProd: Costs!$AJ$66:$AV$75
Name altcostPvtCld: [1]Costs!$AH$77:$AT$88
Name altcostPvtCld: PriceTbls!$AJ$77:$AV$88
Name altcostPvtCld: Costs!$AJ$80:$AV$91
Name altcostSdaia: [1]Costs!$AH$94:$AT$105
Name altcostSdaia: PriceTbls!$AJ$94:$AW$105
Name altcostSdaia: Costs!$AJ$97:$AW$108
Name altcostSec: [1]Costs!$AH$33:$AT$42
Name altcostSec: PriceTbls!$AJ$33:$AV$42
Name altcostSec: Costs!$AJ$36:$AV$45
Name Contingency: [1]Calculator!$I$17
Name Contingency: Calculator!$I$17
Name Contingency_amount: [1]Calculator!$F$19
Name Contingency_amount: Calculator!$F$19
Name costAdv: [1]Costs!$C$48:$O$57
Name costAdv: PriceTbls!$C$50:$O$59
Name costAdv: Costs!$C$51:$O$60
Name costAps: [1]Costs!$C$4:$O$15
Name costAps: Costs!$C$4:$O$15
Name costData: TbCostData[[US]:[VN]]
Name costData: [1]!TbCostData[[US]:[VN]]
Name costData: TbCostData25[[US]:[VN]]
Name costData: TbCostData[[US]:[VN]]
Name costErp: [1]Costs!$C$111:$O$122
Name costErp: PriceTbls!$C$113:$O$124
Name costErp: Costs!$C$114:$O$125
Name costHealth: PriceTbls!$C$128:$P$141
Name costHealth: Costs!$C$129:$P$142
Name costProd: [1]Costs!$C$63:$O$72
Name costProd: PriceTbls!$C$65:$O$74
Name costProd: Costs!$C$66:$O$75
Name costPvtCld: [1]Costs!$C$77:$O$88
Name costPvtCld: PriceTbls!$C$79:$O$90
Name costPvtCld: Costs!$C$80:$O$91
Name costSdaia: [1]Costs!$C$94:$O$105
Name costSdaia: PriceTbls!$C$96:$P$107
Name costSdaia: Costs!$C$97:$P$108
Name costSec: TbCostSec[[US]:[VN]]
Name costSec: [1]!TbCostSec[[US]:[VN]]
Name costSec: PriceTbls!$C$35:$O$44
Name costSec: TbCostSec[[US]:[VN]]
Name countAdv: [1]!TbCountAdv[[US]:[VN]]
Name countAdv: TbCountAdv27[[US]:[VN]]
Name countAdv: TbCountAdv[[US]:[VN]]
Name countAps: TbCountAps[[US]:[VN]]
Name countAps: [1]!TbCountAps[[US]:[VN]]

Sheet Version History
B4: Version No. | C4: Release Date | D4: Updated by | E4: Changes
B5: 1 | C5: 3.15.2024 | D5: Brijesh | E5: Base version
B6: 2 | C6: 5.12.2024 | D6: Brijesh | E6: 1. Summary sheet modified: a. Approval Matrix updated b. Contingency costs updated
B7: 3 | C7: 5.25.2024 | D7: Brijesh | E7: 1. Healthcare PS added 2. Exchange rate adjusted
B8: 4 | C8: 6.17.2024 | D8: Brijesh | E8: 1. Approval Matrix Updated 2. Channel Partner sub-classified
B9: 5 | C9: 7.2.2024 | D9: Brijesh | E9: 1. Expiry date issue (EMEA) is fixed 2. Approval matrix for RIG (Anything outside US) has been updated
B10: 6 | C10: 10.14.2024 | D10: Brijesh | E10: 1. EGY Pricing Fixed 2. Approval matrix for Pvt Cloud Updated
B11: 7 | C11: 1.31.2025 | D11: Brijesh | E11: 1. Costs and utilization assumptions revised 2. Data levels further defined for Eng and Arch
B12: 8 | C12: 2.15.2025 | D12: Brijesh | E12: 1. Discounted Price/hr (after strategic discounts or overall discount) is provided in column Q

Sheet Summary
AA1: =AA2&TEXT(AB2,"mm-dd-yy")&" at " & TEXT(AB2,"hh-mm") -> Snapshot on 05-08-26 at 10-13
B2: Financial and Approval Summary | D2: ="ver " & Calculator!E1 -> ver Updated: 2/15/2025 | AA2: Snapshot on | AB2: =NOW() -> 46150.426
B3: SalesForce ID | D3: e.g. 44404522 | F3: =IF(expiry_code=1,"The rate card has expired. Please download the latest version from Solution hub","") | AB3: =NOW() -> 46150.426
B4: Financial Force Project (if any) | D4: e.g. PR-010641
B5: Region | C5: =Calculator!F4 -> UK
B6: Customer
B7: Opportunity Name
C8: Enter details (Names) Below | D8: Date approved on
B9: Cost Model Estimates by
B10: Regional Director Approved
B11: Delivery Approved by
B12: GTM Regional Leader
B13: Finance/ Pricing
B14: Offering
B15: Delivery Type
B16: Project Start Date
B17: Project End Date
B18: Units of Service
B19: Currency
B22: Revenue | C22: =Calculator!I11/(1-Calculator!I9) -> 218571
B23: Approved Negotiated Discount | C23: =-Calculator!I11/(1-Calculator!I9)*Calculator!I9 -> -118879.22
B24: Minimum Approved Revenue | C24: =C22+C23 -> 99691.785
B25: Resource Costs | C25: =IF(Calculator!F8="Yes",75%/85%,1)*Calculator!F14 -> 94942.841 | D25: =Calculator!I12 & " " & Calculator!J12 & " efforts" -> 160 Days efforts
B26: 3rd Party Costs/Other BU costs | C26: =Calculator!F16 -> 0
B27: Materials and Expenses | C27: =Calculator!F11 -> 0
B28: Channel Partner Costs | C28: =Calculator!F17 -> 0
B29: Contingency | C29: =Contingency_amount -> 4747.142
B30: Contingency % | C30: =IFERROR(Contingency_amount/C24,"") -> 0.047618187 | D30: of the Revenue!
B31: Total Costs | C31: =SUBTOTAL(9,C25:C29) -> 99689.983
B32: Project Profit | C32: =C24-C31 -> 1.8019795
B33: Project Gross Margin | C33: =IFERROR(C32/C24,"") -> 1.8075507e-05 | D33: =IF(C33<40%,"Approval needed: Please fill in the appovers in summary above once approved", "Approved margins") -> Approval needed: Please fill in the appovers in summary above once approved
B37: Approval Matrices
B68: Include pricing@rackspace.com or pricingintl@rackspace.com (for other than AMER) on cc for any deal <35% margins
B84: Approvers | F84: Approval Level
B85: Delivery Lead | F85: None - Signs off that the technical approach is able to be delivered subject to the documented assumptions. Specifically: • Milestones and mobilization of delivery resources (if sign on from customer is delayed, then revenue milestones will be adjusted – if no option to mitigate) • Technical Delivery and Project Management delivery • Level of requirements / details within SOW • Highlight of any risks or concerns • Resources required outside of PS (e.g. GTS, contractors, etc.)
B86: Regional Director | F86: 35% MIN. Project Gross Margin (Fixed Price, T&M) 10% MIN. Contingency (Fixed Price) $200K MAX. Revenue on Fixed Price, $300 T&M
B87: Regional Leader | C87: Mahesh Desai (UK, Nordics, NL and Middle East) Juergen Stauber (DACH) | F87: 30% MIN Project Gross Margin (Fixed Price, T&M) 10% MIN Contingency (Fixed Price) $200K MAX revenue on Fixed Price, $300k T&M
B88: Finance | C88: Karthik Gurumurthy/John Vernikos/Sriram Mathew Cozens (backup) | F88: 20% MIN Project Gross Margin (Fixed Price, T&M) 5% MIN Contingency (Fixed Price) $5m Max Revenue
B89: RIG Managing Director & Finance | C89: John Vernikos Dorothea Bruggler Chax Poduri (backup) | F89: 0% MIN Project Gross Margin (Fixed Price, T&M) 0% MIN Contingency (Fixed price) No limit Max Revenue

Sheet Reference
W1: Mapping for SOW | Z1: Unique list at Z2 | AC1: Role Example | BZ1: lock | CA1: Date Lock/Expiry
C2: tb_practices | E2: TbCountries | G2: tb_roles | J2: USD exchange rates | W2: Role | X2: SOW Roles | Z2: {=_xlfn.UNIQUE(tb_role_map[Role])} -> Arch | AC2: Senior Advisory Consultant | CA2: Date updated | CB2: =VALUE(TRIM(MID(Calculator!E1,9,10))) -> #VALUE!
C3: Practice Area | E3: Region Sourced from | G3: Role | H3: Job Profile | J3: currency | K3: fx | W3: Arch | X3: Security Architect | Z3: Advisory Consultant | CA3: Previous update | CB3: 45322 | CD3: mm | CE3: dd | CF3: yyyy
C4: Platform and Apps | E4: US | G4: Jr. Eng | H4: Engineer I | J4: USD | K4: 1 | W4: Arch | X4: Solutions Architect | Z4: Sr. Advisory Consultant | CA4: Today is | CB4: =TODAY() -> 46150 | CD4: =MONTH(CB4) -> 5 | CE4: =DAY(CB4) -> 8 | CF4: =YEAR(CB4) -> 2026
C5: Data | E5: UK | G5: Eng | H5: Engineer II | J5: GBP | K5: 0.83 | W5: Arch | X5: SME (Subject Matter Expert) | Z5: Developer | CA5: Expiry date | CB5: =150+CB2 -> #VALUE! | CD5: =MONTH(CB5) -> #VALUE! | CE5: =DAY(CB5) -> #VALUE! | CF5: =YEAR(CB5) -> #VALUE!
C6: Security | E6: DE | G6: Sr. Eng | H6: Engineer III/IV/V | J6: EUR | K6: 0.95 | W6: Advisory Consultant | X6: Consultant | Z6: EM/PJM | CA6: Is expired | CB6: =CB10 -> 0 | CD6: =IF(DATE(CF4,CD4,CE4)>DATE(CF5,CD5,CE5),1,0) -> #VALUE!
C7: Advisory | E7: PL | G7: Arch | H7: Architect, Sr. and Staff Consulting Architect | J7: AUD | K7: 1.54 | W7: Advisory Consultant | X7: Advisory Consultant | Z7: Eng | CA7: There is error | CB7: =IFERROR(IF(DATE(CF4,CD4,CE4)>DATE(CF5,CD5,CE5),0,1),"Error in date") -> Error in date
C8: Productivity | E8: NL | G8: Sr. Arch | H8: Sr. Architect | J8: CAD | K8: 1.35 | W8: Advisory Consultant | X8: Security Consultant | Z8: Jr. Eng
C9: PS Private Cloud | E9: MX | G9: TCT/Lead Arch | H9: Practice Lead & Principal Consultant | W9: Sr. Advisory Consultant | X9: Sr. Advisory Consultant | Z9: Manager
C10: SDAIA | E10: IN | G10: Manager | H10: Manager | W10: Sr. Advisory Consultant | X10: Sr. Advisory Consultant | Z10: Prog Mgr | CA10: Input from Macro | CB10: =Calculator!F1 -> 0
C11: ERP | E11: EG | G11: Sr. Mgr | H11: Sr. Manager | W11: Sr. Advisory Consultant | X11: Sr. Advisory Consultant | Z11: Project Coordinator | CA11: (you need to change the date on macro button 9… to set the expiry)
C12: Healthcare PS | E12: CAN | G12: EM/PJM | H12: Engagement Manager | W12: Developer | X12: Developer | Z12: Project Mgr
E13: AU | G13: Sr. EM/Sr. PJM/PGM | H13: Sr. Engagement Manager | W13: EM/PJM | X13: Engagement Manager (EM) | Z13: Sr. Arch
E14: AE | W14: EM/PJM | X14: Project Manager | Z14: Sr. Consultant
C15: Lock sheets | E15: SG | W15: Eng | X15: Security Engineer | Z15: Sr. Developer
C16: Reference | E16: VN | W16: Eng | X16: Cloud Engineer (CE) | Z16: Sr. EM/Sr. PJM/PGM
C17: Data | E17: SA | W17: Eng | X17: Software Development Engineer (SDE) | Z17: Sr. Eng
C18: price at custom | W18: Eng | X18: Firmware Engineer (FWE) | Z18: Sr. Mgr
C19: All but security | W19: Eng | X19: Business Analyst (BA) | Z19: Sr. Proj Mgr
C20: Price Tables | G20: Roles | H20: mapped to | W20: Eng | X20: Data Engineer (DE) | Z20: TCT/Lead Arch
C21: Summary | G21: Subject Matter Expert (SME) & Security Consultant | H21: Arch | W21: Eng | X21: DBA
G22: Project Manager | H22: EM/PJM | W22: Jr. Eng | X22: Junior Engineer
G23: Engineer II, Software Development Engineer (SDE) & Business Analyst (BA) | H23: Eng | W23: Manager | X23: Managing Consultant
B24: Region | C24: Level | D24: Approvers | G24: Engineer III, IV | H24: Sr. Eng | W24: Manager | X24: Program Manager
B25: US | C25: Regional Director Approved | G25: Engineer I | H25: Jr. Eng | W25: Manager | X25: Project Manager
B26: US | C26: Delivery Approved by | G26: Advisory Consultant | H26: Arch | W26: Prog Mgr | X26: Program Manager
B27: US | C27: GTM Regional Leader | G27: Sr. Advisory Consultant | H27: Sr. Arch | W27: Project Coordinator | X27: Project Coordinator
B28: EMEA | C28: Regional Director Approved | G28: Program Manager | H28: Sr. EM/Sr. PJM/PGM | W28: Project Mgr | X28: Project Manager
B29: EMEA | C29: Delivery Approved by | G29: Security Engineer/HW Eng/Firmware Eng/Managing Consultant | H29: Sr. Eng | W29: Sr. Arch | X29: Senior Advisory Consultant
B30: EMEA | C30: GTM Regional Leader | G30: Practice Lead & Principal Consultant | H30: TCT/Lead Arch | W30: Sr. Arch | X30: Advisory Consultant
B31: APJ | C31: Regional Director Approved | W31: Sr. Arch | X31: Senior Solutions Architect
B32: APJ | C32: Delivery Approved by | W32: Sr. Arch | X32: Senior Data Scientist (SDS)
B33: APJ | C33: GTM Regional Leader | W33: Sr. Arch | X33: Senior Solutions Architect (SSA)
W34: Sr. Consultant | X34: Senior Consultant
W35: Sr. Developer | X35: Senior Developer
W36: Sr. EM/Sr. PJM/PGM | X36: Program Manager
D37: 2 | E37: 3 | F37: 4 | G37: 5 | H37: 6 | I37: 7 | J37: 8 | K37: 9 | W37: Sr. EM/Sr. PJM/PGM | X37: Senior Engagement Manager
C38: 1 | D38: Data | E38: Security | F38: Advisory | G38: Productivity | H38: PS Pvt Cloud | I38: PS SADIA | J38: erp | K38: Healthcare PS | W38: Sr. EM/Sr. PJM/PGM | X38: Senior Project Manager
C39: Platform and Apps | D39: data_roles | E39: sec_roles | F39: adv_roles | G39: prod_roles | H39: pvc_roles | I39: sadia_roles | J39: erp_roles | W39: Sr. Eng | X39: Senior Cloud Engineer (CE)
C40: pa_roles | D40: Associate Eng | E40: Jr. Eng | F40: Advisory Consultant | G40: Specialty Architect | H40: Jr. Engineer | I40: Jr. Engineer | J40: Jr. Engineer | K40: WSS Eng | W40: Sr. Eng | X40: Senior DBA
C41: Jr. Eng | D41: Eng | E41: Eng | F41: Sr. Advisory Consultant | G41: Sr. Specialty Engineer | H41: Engineer | I41: Engineer | J41: Engineer | K41: WSS Sr. Eng | W41: Sr. Eng | X41: Senior Software Development Engineer (SDE)
C42: Eng | D42: Sr. Eng | E42: Sr. Eng | G42: Specialty Engineer | H42: Sr. Engineer | I42: Sr. Engineer | J42: Sr. Engineer | K42: Cogito Eng | W42: Sr. Eng | X42: Hardware Engineer (HWE)
C43: Sr. Eng | D43: Staff Eng | E43: Arch | G43: Program Manager | H43: Architect | I43: Architect | J43: Architect | K43: Cogito Sr. Eng | W43: Sr. Eng | X43: Data Scientist (DS)
C44: Arch | D44: Lead Eng | E44: Sr. Arch | G44: Engagement Manager (EM) | H44: Sr. Architect | I44: Sr. Architect | J44: Sr. Architect | K44: ODB Eng | W44: Sr. Eng | X44: Senior Data Engineer (DE)
C45: Sr. Arch | D45: Arch | E45: TCT/Lead Arch | H45: Consultant | I45: Consultant | J45: Consultant | K45: ODB Sr. Eng | W45: Sr. Mgr | X45: Senior Practice Lead
C46: TCT/Lead Arch | D46: Sr. Arch | E46: Manager | H46: Sr. Consultant | I46: Sr. Consultant | J46: Sr. Consultant | K46: Sppt Jr. Eng | W46: Sr. Mgr | X46: Senior Subject Matter Expert (SME)
C47: Manager | D47: Lead Arch | E47: Sr. Mgr | H47: Developer | I47: Developer | J47: Developer | K47: Sppt Eng | W47: Sr. Mgr | X47: Senior Principal Consultant
C48: Sr. Mgr | D48: Manager | E48: EM/PJM | H48: Project Coordinator | I48: Project Coordinator | J48: Project Coordinator | K48: Sppt Sr. Eng | W48: Sr. Mgr | X48: Senior Managing Consultant
C49: EM/PJM | D49: Sr. Mgr | E49: Sr. EM/Sr. PJM/PGM | H49: Project Mgr | I49: Project Mgr | J49: Project Mgr | K49: Tech Coordinator | W49: Sr. Mgr | X49: Senior Program Manager
C50: Sr. EM/Sr. PJM/PGM | D50: EM | H50: Sr. Proj Mgr | I50: Sr. Proj Mgr | J50: Sr. Proj Mgr | K50: CSM | W50: Sr. Mgr | X50: Senior Project Manager
D51: Sr. EM | H51: Prog Mgr | I51: Prog Mgr | J51: Prog Mgr | K51: Sr. Arch | W51: Sr. Proj Mgr | X51: Senior Project Manager
K52: Proj Mgr | W52: TCT/Lead Arch | X52: Practice Lead
K53: Sr. Proj Mgr | W53: TCT/Lead Arch | X53: Principal Consultant
A100: Week Reference
A101: wk 1
A102: wk 2
A103: wk 3
A104: wk 4
A105: wk 5
A106: wk 6
A107: wk 7
A108: wk 8
A109: wk 9
A110: wk 10
A111: wk 11
... A152: wk 52

Sheet price at custom
C1: *AE=UAE,PL=Poland,DE=Germany, VN=Veitnam,AU=Australia,SG=Singapore, EG=Egypt,CAN=Canada | AQ1: Check
B3: Platform and Apps | E3: At Margins | F3: 0.4 | Q3: Platform and Apps | T3: At Margins | U3: 0.5
B5: Price | C5: AE | D5: US | E5: UK | F5: AU | G5: MX | H5: PL | I5: SG | J5: VN | K5: IN | L5: EG | M5: NL | N5: DE | O5: CAN | Q5: Price | R5: AE | S5: US | T5: UK | U5: AU | V5: MX | W5: PL | X5: SG | Y5: VN | Z5: IN | AA5: EG | AB5: NL | AC5: DE | AD5: CAN
B6: Eng | C6: =ROUND(Costs!C4/(1-$F$3),0) -> 0 | D6: =ROUND(Costs!D4/(1-$F$3),0) -> 115 | E6: =ROUND(Costs!E4/(1-$F$3),0) -> 108 | F6: =ROUND(Costs!F4/(1-$F$3),0) -> 110 | G6: =ROUND(Costs!G4/(1-$F$3),0) -> 0 | H6: =ROUND(Costs!H4/(1-$F$3),0) -> 0 | I6: =ROUND(Costs!I4/(1-$F$3),0) -> 27 | J6: =ROUND(Costs!J4/(1-$F$3),0) -> 0 | ... O6: =ROUND(Costs!O4/(1-$F$3),0) -> 0 | Q6: Eng | R6: =ROUND(Costs!C4/(1-$U$3),0) -> 0 | S6: =ROUND(Costs!D4/(1-$U$3),0) -> 139 | T6: =ROUND(Costs!E4/(1-$U$3),0) -> 129 | U6: =ROUND(Costs!F4/(1-$U$3),0) -> 132 | V6: =ROUND(Costs!G4/(1-$U$3),0) -> 0 | W6: =ROUND(Costs!H4/(1-$U$3),0) -> 0 | X6: =ROUND(Costs!I4/(1-$U$3),0) -> 32 | Y6: =ROUND(Costs!J4/(1-$U$3),0) -> 0 | ... AD6: =ROUND(Costs!O4/(1-$U$3),0) -> 0
B7: Sr. Eng | C7: =ROUND(Costs!C5/(1-$F$3),0) -> 193 | D7: =ROUND(Costs!D5/(1-$F$3),0) -> 167 | E7: =ROUND(Costs!E5/(1-$F$3),0) -> 156 | F7: =ROUND(Costs!F5/(1-$F$3),0) -> 118 | G7: =ROUND(Costs!G5/(1-$F$3),0) -> 144 | H7: =ROUND(Costs!H5/(1-$F$3),0) -> 53 | I7: =ROUND(Costs!I5/(1-$F$3),0) -> 35 | J7: =ROUND(Costs!J5/(1-$F$3),0) -> 43 | ... O7: =ROUND(Costs!O5/(1-$F$3),0) -> 0 | Q7: Sr. Eng | R7: =ROUND(Costs!C5/(1-$U$3),0) -> 232 | S7: =ROUND(Costs!D5/(1-$U$3),0) -> 200 | T7: =ROUND(Costs!E5/(1-$U$3),0) -> 187 | U7: =ROUND(Costs!F5/(1-$U$3),0) -> 142 | V7: =ROUND(Costs!G5/(1-$U$3),0) -> 172 | W7: =ROUND(Costs!H5/(1-$U$3),0) -> 63 | X7: =ROUND(Costs!I5/(1-$U$3),0) -> 42 | Y7: =ROUND(Costs!J5/(1-$U$3),0) -> 52 | ... AD7: =ROUND(Costs!O5/(1-$U$3),0) -> 0
B8: Arch | C8: =ROUND(Costs!C6/(1-$F$3),0) -> 271 | D8: =ROUND(Costs!D6/(1-$F$3),0) -> 199 | E8: =ROUND(Costs!E6/(1-$F$3),0) -> 178 | F8: =ROUND(Costs!F6/(1-$F$3),0) -> 153 | G8: =ROUND(Costs!G6/(1-$F$3),0) -> 193 | H8: =ROUND(Costs!H6/(1-$F$3),0) -> 85 | I8: =ROUND(Costs!I6/(1-$F$3),0) -> 60 | J8: =ROUND(Costs!J6/(1-$F$3),0) -> 58 | ... O8: =ROUND(Costs!O6/(1-$F$3),0) -> 0 | Q8: Arch | R8: =ROUND(Costs!C6/(1-$U$3),0) -> 325 | S8: =ROUND(Costs!D6/(1-$U$3),0) -> 238 | T8: =ROUND(Costs!E6/(1-$U$3),0) -> 214 | U8: =ROUND(Costs!F6/(1-$U$3),0) -> 183 | V8: =ROUND(Costs!G6/(1-$U$3),0) -> 232 | W8: =ROUND(Costs!H6/(1-$U$3),0) -> 102 | X8: =ROUND(Costs!I6/(1-$U$3),0) -> 72 | Y8: =ROUND(Costs!J6/(1-$U$3),0) -> 70 | ... AD8: =ROUND(Costs!O6/(1-$U$3),0) -> 0
B9: Sr. Arch | C9: =ROUND(Costs!C7/(1-$F$3),0) -> 297 | D9: =ROUND(Costs!D7/(1-$F$3),0) -> 236 | E9: =ROUND(Costs!E7/(1-$F$3),0) -> 224 | F9: =ROUND(Costs!F7/(1-$F$3),0) -> 178 | G9: =ROUND(Costs!G7/(1-$F$3),0) -> 177 | H9: =ROUND(Costs!H7/(1-$F$3),0) -> 96 | I9: =ROUND(Costs!I7/(1-$F$3),0) -> 70 | J9: =ROUND(Costs!J7/(1-$F$3),0) -> 62 | ... O9: =ROUND(Costs!O7/(1-$F$3),0) -> 0 | Q9: Sr. Arch | R9: =ROUND(Costs!C7/(1-$U$3),0) -> 356 | S9: =ROUND(Costs!D7/(1-$U$3),0) -> 283 | T9: =ROUND(Costs!E7/(1-$U$3),0) -> 269 | U9: =ROUND(Costs!F7/(1-$U$3),0) -> 214 | V9: =ROUND(Costs!G7/(1-$U$3),0) -> 212 | W9: =ROUND(Costs!H7/(1-$U$3),0) -> 115 | X9: =ROUND(Costs!I7/(1-$U$3),0) -> 84 | Y9: =ROUND(Costs!J7/(1-$U$3),0) -> 75 | ... AD9: =ROUND(Costs!O7/(1-$U$3),0) -> 0
B10: TCT | C10: =ROUND(Costs!C8/(1-$F$3),0) -> 310 | D10: =ROUND(Costs!D8/(1-$F$3),0) -> 259 | E10: =ROUND(Costs!E8/(1-$F$3),0) -> 0 | F10: =ROUND(Costs!F8/(1-$F$3),0) -> 0 | G10: =ROUND(Costs!G8/(1-$F$3),0) -> 231 | H10: =ROUND(Costs!H8/(1-$F$3),0) -> 105 | I10: =ROUND(Costs!I8/(1-$F$3),0) -> 72 | J10: =ROUND(Costs!J8/(1-$F$3),0) -> 0 | ... O10: =ROUND(Costs!O8/(1-$F$3),0) -> 0 | Q10: TCT | R10: =ROUND(Costs!C8/(1-$U$3),0) -> 372 | S10: =ROUND(Costs!D8/(1-$U$3),0) -> 311 | T10: =ROUND(Costs!E8/(1-$U$3),0) -> 0 | U10: =ROUND(Costs!F8/(1-$U$3),0) -> 0 | V10: =ROUND(Costs!G8/(1-$U$3),0) -> 277 | W10: =ROUND(Costs!H8/(1-$U$3),0) -> 126 | X10: =ROUND(Costs!I8/(1-$U$3),0) -> 86 | Y10: =ROUND(Costs!J8/(1-$U$3),0) -> 0 | ... AD10: =ROUND(Costs!O8/(1-$U$3),0) -> 0
B11: Manager | C11: =ROUND(Costs!C9/(1-$F$3),0) -> 0 | D11: =ROUND(Costs!D9/(1-$F$3),0) -> 266 | E11: =ROUND(Costs!E9/(1-$F$3),0) -> 0 | F11: =ROUND(Costs!F9/(1-$F$3),0) -> 0 | G11: =ROUND(Costs!G9/(1-$F$3),0) -> 386 | H11: =ROUND(Costs!H9/(1-$F$3),0) -> 0 | I11: =ROUND(Costs!I9/(1-$F$3),0) -> 0 | J11: =ROUND(Costs!J9/(1-$F$3),0) -> 0 | ... O11: =ROUND(Costs!O9/(1-$F$3),0) -> 0 | Q11: Manager | R11: =ROUND(Costs!C9/(1-$U$3),0) -> 0 | S11: =ROUND(Costs!D9/(1-$U$3),0) -> 319 | T11: =ROUND(Costs!E9/(1-$U$3),0) -> 0 | U11: =ROUND(Costs!F9/(1-$U$3),0) -> 0 | V11: =ROUND(Costs!G9/(1-$U$3),0) -> 463 | W11: =ROUND(Costs!H9/(1-$U$3),0) -> 0 | X11: =ROUND(Costs!I9/(1-$U$3),0) -> 0 | Y11: =ROUND(Costs!J9/(1-$U$3),0) -> 0 | ... AD11: =ROUND(Costs!O9/(1-$U$3),0) -> 0
B12: Sr. Mgr | C12: =ROUND(Costs!C10/(1-$F$3),0) -> 374 | D12: =ROUND(Costs!D10/(1-$F$3),0) -> 247 | E12: =ROUND(Costs!E10/(1-$F$3),0) -> 262 | F12: =ROUND(Costs!F10/(1-$F$3),0) -> 0 | G12: =ROUND(Costs!G10/(1-$F$3),0) -> 306 | H12: =ROUND(Costs!H10/(1-$F$3),0) -> 0 | I12: =ROUND(Costs!I10/(1-$F$3),0) -> 32 | J12: =ROUND(Costs!J10/(1-$F$3),0) -> 51 | ... O12: =ROUND(Costs!O10/(1-$F$3),0) -> 0 | Q12: Sr. Mgr | R12: =ROUND(Costs!C10/(1-$U$3),0) -> 449 | S12: =ROUND(Costs!D10/(1-$U$3),0) -> 297 | T12: =ROUND(Costs!E10/(1-$U$3),0) -> 315 | U12: =ROUND(Costs!F10/(1-$U$3),0) -> 0 | V12: =ROUND(Costs!G10/(1-$U$3),0) -> 368 | W12: =ROUND(Costs!H10/(1-$U$3),0) -> 0 | X12: =ROUND(Costs!I10/(1-$U$3),0) -> 38 | Y12: =ROUND(Costs!J10/(1-$U$3),0) -> 61 | ... AD12: =ROUND(Costs!O10/(1-$U$3),0) -> 0
B13: EM | C13: =ROUND(Costs!C11/(1-$F$3),0) -> 615 | D13: =ROUND(Costs!D11/(1-$F$3),0) -> 354 | E13: =ROUND(Costs!E11/(1-$F$3),0) -> 0 | F13: =ROUND(Costs!F11/(1-$F$3),0) -> 0 | G13: =ROUND(Costs!G11/(1-$F$3),0) -> 337 | H13: =ROUND(Costs!H11/(1-$F$3),0) -> 0 | I13: =ROUND(Costs!I11/(1-$F$3),0) -> 49 | J13: =ROUND(Costs!J11/(1-$F$3),0) -> 0 | ... O13: =ROUND(Costs!O11/(1-$F$3),0) -> 0 | Q13: EM | R13: =ROUND(Costs!C11/(1-$U$3),0) -> 738 | S13: =ROUND(Costs!D11/(1-$U$3),0) -> 425 | T13: =ROUND(Costs!E11/(1-$U$3),0) -> 0 | U13: =ROUND(Costs!F11/(1-$U$3),0) -> 0 | V13: =ROUND(Costs!G11/(1-$U$3),0) -> 404 | W13: =ROUND(Costs!H11/(1-$U$3),0) -> 0 | X13: =ROUND(Costs!I11/(1-$U$3),0) -> 58 | Y13: =ROUND(Costs!J11/(1-$U$3),0) -> 0 | ... AD13: =ROUND(Costs!O11/(1-$U$3),0) -> 0
B14: Jr. Eng | C14: =ROUND(Costs!C12/(1-$F$3),0) -> 0 | D14: =ROUND(Costs!D12/(1-$F$3),0) -> 120 | E14: =ROUND(Costs!E12/(1-$F$3),0) -> 181 | F14: =ROUND(Costs!F12/(1-$F$3),0) -> 0 | G14: =ROUND(Costs!G12/(1-$F$3),0) -> 0 | H14: =ROUND(Costs!H12/(1-$F$3),0) -> 96 | I14: =ROUND(Costs!I12/(1-$F$3),0) -> 34 | J14: =ROUND(Costs!J12/(1-$F$3),0) -> 26 | ... O14: =ROUND(Costs!O12/(1-$F$3),0) -> 0 | Q14: Jr. Eng | R14: =ROUND(Costs!C12/(1-$U$3),0) -> 0 | S14: =ROUND(Costs!D12/(1-$U$3),0) -> 144 | T14: =ROUND(Costs!E12/(1-$U$3),0) -> 217 | U14: =ROUND(Costs!F12/(1-$U$3),0) -> 0 | V14: =ROUND(Costs!G12/(1-$U$3),0) -> 0 | W14: =ROUND(Costs!H12/(1-$U$3),0) -> 115 | X14: =ROUND(Costs!I12/(1-$U$3),0) -> 41 | Y14: =ROUND(Costs!J12/(1-$U$3),0) -> 31 | ... AD14: =ROUND(Costs!O12/(1-$U$3),0) -> 0
B18: Data | E18: At Margins | F18: 0.4 | Q18: Data | T18: At Margins | U18: 0.5
B20: Price | C20: AE | D20: US | E20: UK | F20: AU | G20: MX | H20: PL | I20: SG | J20: VN | K20: IN | L20: EG | M20: NL | N20: DE | O20: CAN | Q20: Price | R20: AE | S20: US | T20: UK | U20: AU | V20: MX | W20: PL | X20: SG | Y20: VN | Z20: IN | AA20: EG | AB20: NL | AC20: DE | AD20: CAN
B21: Eng | C21: =ROUND(Costs!C18/(1-$F$18),0) -> 147 | D21: =ROUND(Costs!D18/(1-$F$18),0) -> 0 | E21: =ROUND(Costs!E18/(1-$F$18),0) -> 0 | F21: =ROUND(Costs!F18/(1-$F$18),0) -> 0 | G21: =ROUND(Costs!G18/(1-$F$18),0) -> 0 | H21: =ROUND(Costs!H18/(1-$F$18),0) -> 0 | I21: =ROUND(Costs!I18/(1-$F$18),0) -> 21 | J21: =ROUND(Costs!J18/(1-$F$18),0) -> 36 | ... O21: =ROUND(Costs!O18/(1-$F$18),0) -> 20 | Q21: Eng | R21: =ROUND(Costs!C18/(1-$U$18),0) -> 176 | S21: =ROUND(Costs!D18/(1-$U$18),0) -> 0 | T21: =ROUND(Costs!E18/(1-$U$18),0) -> 0 | U21: =ROUND(Costs!F18/(1-$U$18),0) -> 0 | V21: =ROUND(Costs!G18/(1-$U$18),0) -> 0 | W21: =ROUND(Costs!H18/(1-$U$18),0) -> 0 | X21: =ROUND(Costs!I18/(1-$U$18),0) -> 25 | Y21: =ROUND(Costs!J18/(1-$U$18),0) -> 43 | ... AD21: =ROUND(Costs!O18/(1-$U$18),0) -> 23
B22: Sr. Eng | C22: =ROUND(Costs!C19/(1-$F$18),0) -> 230 | D22: =ROUND(Costs!D19/(1-$F$18),0) -> 0 | E22: =ROUND(Costs!E19/(1-$F$18),0) -> 0 | F22: =ROUND(Costs!F19/(1-$F$18),0) -> 0 | G22: =ROUND(Costs!G19/(1-$F$18),0) -> 172 | H22: =ROUND(Costs!H19/(1-$F$18),0) -> 0 | I22: =ROUND(Costs!I19/(1-$F$18),0) -> 42 | J22: =ROUND(Costs!J19/(1-$F$18),0) -> 50 | ... O22: =ROUND(Costs!O19/(1-$F$18),0) -> 37 | Q22: Sr. Eng | R22: =ROUND(Costs!C19/(1-$U$18),0) -> 277 | S22: =ROUND(Costs!D19/(1-$U$18),0) -> 0 | T22: =ROUND(Costs!E19/(1-$U$18),0) -> 0 | U22: =ROUND(Costs!F19/(1-$U$18),0) -> 0 | V22: =ROUND(Costs!G19/(1-$U$18),0) -> 207 | W22: =ROUND(Costs!H19/(1-$U$18),0) -> 0 | X22: =ROUND(Costs!I19/(1-$U$18),0) -> 51 | Y22: =ROUND(Costs!J19/(1-$U$18),0) -> 60 | ... AD22: =ROUND(Costs!O19/(1-$U$18),0) -> 45
B23: Arch | C23: =ROUND(Costs!C20/(1-$F$18),0) -> 277 | D23: =ROUND(Costs!D20/(1-$F$18),0) -> 0 | E23: =ROUND(Costs!E20/(1-$F$18),0) -> 0 | F23: =ROUND(Costs!F20/(1-$F$18),0) -> 0 | G23: =ROUND(Costs!G20/(1-$F$18),0) -> 0 | H23: =ROUND(Costs!H20/(1-$F$18),0) -> 0 | I23: =ROUND(Costs!I20/(1-$F$18),0) -> 60 | J23: =ROUND(Costs!J20/(1-$F$18),0) -> 51 | ... O23: =ROUND(Costs!O20/(1-$F$18),0) -> 65 | Q23: Arch | R23: =ROUND(Costs!C20/(1-$U$18),0) -> 333 | S23: =ROUND(Costs!D20/(1-$U$18),0) -> 0 | T23: =ROUND(Costs!E20/(1-$U$18),0) -> 0 | U23: =ROUND(Costs!F20/(1-$U$18),0) -> 0 | V23: =ROUND(Costs!G20/(1-$U$18),0) -> 0 | W23: =ROUND(Costs!H20/(1-$U$18),0) -> 0 | X23: =ROUND(Costs!I20/(1-$U$18),0) -> 72 | Y23: =ROUND(Costs!J20/(1-$U$18),0) -> 61 | ... AD23: =ROUND(Costs!O20/(1-$U$18),0) -> 78
B24: Sr. Arch | C24: =ROUND(Costs!C21/(1-$F$18),0) -> 354 | D24: =ROUND(Costs!D21/(1-$F$18),0) -> 0 | E24: =ROUND(Costs!E21/(1-$F$18),0) -> 0 | F24: =ROUND(Costs!F21/(1-$F$18),0) -> 0 | G24: =ROUND(Costs!G21/(1-$F$18),0) -> 0 | H24: =ROUND(Costs!H21/(1-$F$18),0) -> 0 | I24: =ROUND(Costs!I21/(1-$F$18),0) -> 66 | J24: =ROUND(Costs!J21/(1-$F$18),0) -> 0 | ... O24: =ROUND(Costs!O21/(1-$F$18),0) -> 0 | Q24: Sr. Arch | R24: =ROUND(Costs!C21/(1-$U$18),0) -> 425 | S24: =ROUND(Costs!D21/(1-$U$18),0) -> 0 | T24: =ROUND(Costs!E21/(1-$U$18),0) -> 0 | U24: =ROUND(Costs!F21/(1-$U$18),0) -> 0 | V24: =ROUND(Costs!G21/(1-$U$18),0) -> 0 | W24: =ROUND(Costs!H21/(1-$U$18),0) -> 0 | X24: =ROUND(Costs!I21/(1-$U$18),0) -> 79 | Y24: =ROUND(Costs!J21/(1-$U$18),0) -> 0 | ... AD24: =ROUND(Costs!O21/(1-$U$18),0) -> 0
B25: TCT | C25: =ROUND(Costs!C22/(1-$F$18),0) -> 528 | D25: =ROUND(Costs!D22/(1-$F$18),0) -> 0 | E25: =ROUND(Costs!E22/(1-$F$18),0) -> 0 | F25: =ROUND(Costs!F22/(1-$F$18),0) -> 0 | G25: =ROUND(Costs!G22/(1-$F$18),0) -> 0 | H25: =ROUND(Costs!H22/(1-$F$18),0) -> 0 | I25: =ROUND(Costs!I22/(1-$F$18),0) -> 90 | J25: =ROUND(Costs!J22/(1-$F$18),0) -> 0 | ... O25: =ROUND(Costs!O22/(1-$F$18),0) -> 0 | Q25: TCT | R25: =ROUND(Costs!C22/(1-$U$18),0) -> 634 | S25: =ROUND(Costs!D22/(1-$U$18),0) -> 0 | T25: =ROUND(Costs!E22/(1-$U$18),0) -> 0 | U25: =ROUND(Costs!F22/(1-$U$18),0) -> 0 | V25: =ROUND(Costs!G22/(1-$U$18),0) -> 0 | W25: =ROUND(Costs!H22/(1-$U$18),0) -> 0 | X25: =ROUND(Costs!I22/(1-$U$18),0) -> 108 | Y25: =ROUND(Costs!J22/(1-$U$18),0) -> 0 | ... AD25: =ROUND(Costs!O22/(1-$U$18),0) -> 0
B26: Manager | C26: =ROUND(Costs!C23/(1-$F$18),0) -> 290 | D26: =ROUND(Costs!D23/(1-$F$18),0) -> 0 | E26: =ROUND(Costs!E23/(1-$F$18),0) -> 0 | F26: =ROUND(Costs!F23/(1-$F$18),0) -> 0 | G26: =ROUND(Costs!G23/(1-$F$18),0) -> 0 | H26: =ROUND(Costs!H23/(1-$F$18),0) -> 0 | I26: =ROUND(Costs!I23/(1-$F$18),0) -> 99 | J26: =ROUND(Costs!J23/(1-$F$18),0) -> 74 | ... O26: =ROUND(Costs!O23/(1-$F$18),0) -> 69 | Q26: Manager | R26: =ROUND(Costs!C23/(1-$U$18),0) -> 348 | S26: =ROUND(Costs!D23/(1-$U$18),0) -> 0 | T26: =ROUND(Costs!E23/(1-$U$18),0) -> 0 | U26: =ROUND(Costs!F23/(1-$U$18),0) -> 0 | V26: =ROUND(Costs!G23/(1-$U$18),0) -> 0 | W26: =ROUND(Costs!H23/(1-$U$18),0) -> 0 | X26: =ROUND(Costs!I23/(1-$U$18),0) -> 119 | Y26: =ROUND(Costs!J23/(1-$U$18),0) -> 88 | ... AD26: =ROUND(Costs!O23/(1-$U$18),0) -> 83
B27: Sr. Mgr | C27: =ROUND(Costs!C24/(1-$F$18),0) -> 370 | D27: =ROUND(Costs!D24/(1-$F$18),0) -> 0 | E27: =ROUND(Costs!E24/(1-$F$18),0) -> 0 | F27: =ROUND(Costs!F24/(1-$F$18),0) -> 0 | G27: =ROUND(Costs!G24/(1-$F$18),0) -> 0 | H27: =ROUND(Costs!H24/(1-$F$18),0) -> 0 | I27: =ROUND(Costs!I24/(1-$F$18),0) -> 79 | J27: =ROUND(Costs!J24/(1-$F$18),0) -> 0 | ... O27: =ROUND(Costs!O24/(1-$F$18),0) -> 0 | Q27: Sr. Mgr | R27: =ROUND(Costs!C24/(1-$U$18),0) -> 444 | S27: =ROUND(Costs!D24/(1-$U$18),0) -> 0 | T27: =ROUND(Costs!E24/(1-$U$18),0) -> 0 | U27: =ROUND(Costs!F24/(1-$U$18),0) -> 0 | V27: =ROUND(Costs!G24/(1-$U$18),0) -> 0 | W27: =ROUND(Costs!H24/(1-$U$18),0) -> 0 | X27: =ROUND(Costs!I24/(1-$U$18),0) -> 95 | Y27: =ROUND(Costs!J24/(1-$U$18),0) -> 0 | ... AD27: =ROUND(Costs!O24/(1-$U$18),0) -> 0
B28: EM | C28: =ROUND(Costs!C25/(1-$F$18),0) -> 361 | D28: =ROUND(Costs!D25/(1-$F$18),0) -> 0 | E28: =ROUND(Costs!E25/(1-$F$18),0) -> 0 | F28: =ROUND(Costs!F25/(1-$F$18),0) -> 0 | G28: =ROUND(Costs!G25/(1-$F$18),0) -> 0 | H28: =ROUND(Costs!H25/(1-$F$18),0) -> 0 | I28: =ROUND(Costs!I25/(1-$F$18),0) -> 0 | J28: =ROUND(Costs!J25/(1-$F$18),0) -> 0 | ... O28: =ROUND(Costs!O25/(1-$F$18),0) -> 0 | Q28: EM | R28: =ROUND(Costs!C25/(1-$U$18),0) -> 433 | S28: =ROUND(Costs!D25/(1-$U$18),0) -> 0 | T28: =ROUND(Costs!E25/(1-$U$18),0) -> 0 | U28: =ROUND(Costs!F25/(1-$U$18),0) -> 0 | V28: =ROUND(Costs!G25/(1-$U$18),0) -> 0 | W28: =ROUND(Costs!H25/(1-$U$18),0) -> 0 | X28: =ROUND(Costs!I25/(1-$U$18),0) -> 0 | Y28: =ROUND(Costs!J25/(1-$U$18),0) -> 0 | ... AD28: =ROUND(Costs!O25/(1-$U$18),0) -> 0
B29: Jr. Eng | C29: =ROUND(Costs!C26/(1-$F$18),0) -> 545 | D29: =ROUND(Costs!D26/(1-$F$18),0) -> 0 | E29: =ROUND(Costs!E26/(1-$F$18),0) -> 0 | F29: =ROUND(Costs!F26/(1-$F$18),0) -> 0 | G29: =ROUND(Costs!G26/(1-$F$18),0) -> 0 | H29: =ROUND(Costs!H26/(1-$F$18),0) -> 0 | I29: =ROUND(Costs!I26/(1-$F$18),0) -> 58 | J29: =ROUND(Costs!J26/(1-$F$18),0) -> 55 | ... O29: =ROUND(Costs!O26/(1-$F$18),0) -> 0 | Q29: Jr. Eng | R29: =ROUND(Costs!C26/(1-$U$18),0) -> 654 | S29: =ROUND(Costs!D26/(1-$U$18),0) -> 0 | T29: =ROUND(Costs!E26/(1-$U$18),0) -> 0 | U29: =ROUND(Costs!F26/(1-$U$18),0) -> 0 | V29: =ROUND(Costs!G26/(1-$U$18),0) -> 0 | W29: =ROUND(Costs!H26/(1-$U$18),0) -> 0 | X29: =ROUND(Costs!I26/(1-$U$18),0) -> 69 | Y29: =ROUND(Costs!J26/(1-$U$18),0) -> 66 | ... AD29: =ROUND(Costs!O26/(1-$U$18),0) -> 0
B33: Security | E33: At Margins | F33: 0.4 | Q33: Security | T33: At Margins | U33: 0.5
B35: Price | C35: AE | D35: US | E35: UK | F35: AU | G35: MX | H35: PL | I35: SG | J35: VN | K35: IN | L35: EG | M35: NL | N35: DE | O35: CAN | Q35: Price | R35: AE | S35: US | T35: UK | U35: AU | V35: MX | W35: PL | X35: SG | Y35: VN | Z35: IN | AA35: EG | AB35: NL | AC35: DE | AD35: CAN
B36: Eng | C36: =ROUND(Costs!C36/(1-$F$33),0) -> 0 | D36: =ROUND(Costs!D36/(1-$F$33),0) -> 0 | E36: =ROUND(Costs!E36/(1-$F$33),0) -> 0 | F36: =ROUND(Costs!F36/(1-$F$33),0) -> 0 | G36: =ROUND(Costs!G36/(1-$F$33),0) -> 0 | H36: =ROUND(Costs!H36/(1-$F$33),0) -> 0 | I36: =ROUND(Costs!I36/(1-$F$33),0) -> 25 | J36: =ROUND(Costs!J36/(1-$F$33),0) -> 0 | ... O36: =ROUND(Costs!O36/(1-$F$33),0) -> 0 | Q36: Eng | R36: =ROUND(Costs!C36/(1-$U$33),0) -> 0 | S36: =ROUND(Costs!D36/(1-$U$33),0) -> 0 | T36: =ROUND(Costs!E36/(1-$U$33),0) -> 0 | U36: =ROUND(Costs!F36/(1-$U$33),0) -> 0 | V36: =ROUND(Costs!G36/(1-$U$33),0) -> 0 | W36: =ROUND(Costs!H36/(1-$U$33),0) -> 0 | X36: =ROUND(Costs!I36/(1-$U$33),0) -> 30 | Y36: =ROUND(Costs!J36/(1-$U$33),0) -> 0 | ... AD36: =ROUND(Costs!O36/(1-$U$33),0) -> 0
B37: Sr. Eng | C37: =ROUND(Costs!C37/(1-$F$33),0) -> 0 | D37: =ROUND(Costs!D37/(1-$F$33),0) -> 0 | E37: =ROUND(Costs!E37/(1-$F$33),0) -> 0 | F37: =ROUND(Costs!F37/(1-$F$33),0) -> 0 | G37: =ROUND(Costs!G37/(1-$F$33),0) -> 0 | H37: =ROUND(Costs!H37/(1-$F$33),0) -> 72 | I37: =ROUND(Costs!I37/(1-$F$33),0) -> 34 | J37: =ROUND(Costs!J37/(1-$F$33),0) -> 0 | ... O37: =ROUND(Costs!O37/(1-$F$33),0) -> 0 | Q37: Sr. Eng | R37: =ROUND(Costs!C37/(1-$U$33),0) -> 0 | S37: =ROUND(Costs!D37/(1-$U$33),0) -> 0 | T37: =ROUND(Costs!E37/(1-$U$33),0) -> 0 | U37: =ROUND(Costs!F37/(1-$U$33),0) -> 0 | V37: =ROUND(Costs!G37/(1-$U$33),0) -> 0 | W37: =ROUND(Costs!H37/(1-$U$33),0) -> 86 | X37: =ROUND(Costs!I37/(1-$U$33),0) -> 40 | Y37: =ROUND(Costs!J37/(1-$U$33),0) -> 0 | ... AD37: =ROUND(Costs!O37/(1-$U$33),0) -> 0
B38: Arch | C38: =ROUND(Costs!C38/(1-$F$33),0) -> 223 | D38: =ROUND(Costs!D38/(1-$F$33),0) -> 0 | E38: =ROUND(Costs!E38/(1-$F$33),0) -> 0 | F38: =ROUND(Costs!F38/(1-$F$33),0) -> 0 | G38: =ROUND(Costs!G38/(1-$F$33),0) -> 0 | H38: =ROUND(Costs!H38/(1-$F$33),0) -> 84 | I38: =ROUND(Costs!I38/(1-$F$33),0) -> 53 | J38: =ROUND(Costs!J38/(1-$F$33),0) -> 0 | ... O38: =ROUND(Costs!O38/(1-$F$33),0) -> 0 | Q38: Arch | R38: =ROUND(Costs!C38/(1-$U$33),0) -> 268 | S38: =ROUND(Costs!D38/(1-$U$33),0) -> 0 | T38: =ROUND(Costs!E38/(1-$U$33),0) -> 0 | U38: =ROUND(Costs!F38/(1-$U$33),0) -> 0 | V38: =ROUND(Costs!G38/(1-$U$33),0) -> 0 | W38: =ROUND(Costs!H38/(1-$U$33),0) -> 101 | X38: =ROUND(Costs!I38/(1-$U$33),0) -> 64 | Y38: =ROUND(Costs!J38/(1-$U$33),0) -> 0 | ... AD38: =ROUND(Costs!O38/(1-$U$33),0) -> 0
B39: Sr. Arch | C39: =ROUND(Costs!C39/(1-$F$33),0) -> 280 | D39: =ROUND(Costs!D39/(1-$F$33),0) -> 207 | E39: =ROUND(Costs!E39/(1-$F$33),0) -> 214 | F39: =ROUND(Costs!F39/(1-$F$33),0) -> 0 | G39: =ROUND(Costs!G39/(1-$F$33),0) -> 238 | H39: =ROUND(Costs!H39/(1-$F$33),0) -> 119 | I39: =ROUND(Costs!I39/(1-$F$33),0) -> 0 | J39: =ROUND(Costs!J39/(1-$F$33),0) -> 0 | ... O39: =ROUND(Costs!O39/(1-$F$33),0) -> 0 | Q39: Sr. Arch | R39: =ROUND(Costs!C39/(1-$U$33),0) -> 336 | S39: =ROUND(Costs!D39/(1-$U$33),0) -> 248 | T39: =ROUND(Costs!E39/(1-$U$33),0) -> 257 | U39: =ROUND(Costs!F39/(1-$U$33),0) -> 0 | V39: =ROUND(Costs!G39/(1-$U$33),0) -> 286 | W39: =ROUND(Costs!H39/(1-$U$33),0) -> 143 | X39: =ROUND(Costs!I39/(1-$U$33),0) -> 0 | Y39: =ROUND(Costs!J39/(1-$U$33),0) -> 0 | ... AD39: =ROUND(Costs!O39/(1-$U$33),0) -> 0
B40: TCT | C40: =ROUND(Costs!C40/(1-$F$33),0) -> 322 | D40: =ROUND(Costs!D40/(1-$F$33),0) -> 0 | E40: =ROUND(Costs!E40/(1-$F$33),0) -> 0 | F40: =ROUND(Costs!F40/(1-$F$33),0) -> 0 | G40: =ROUND(Costs!G40/(1-$F$33),0) -> 261 | H40: =ROUND(Costs!H40/(1-$F$33),0) -> 0 | I40: =ROUND(Costs!I40/(1-$F$33),0) -> 0 | J40: =ROUND(Costs!J40/(1-$F$33),0) -> 0 | ... O40: =ROUND(Costs!O40/(1-$F$33),0) -> 0 | Q40: TCT | R40: =ROUND(Costs!C40/(1-$U$33),0) -> 387 | S40: =ROUND(Costs!D40/(1-$U$33),0) -> 0 | T40: =ROUND(Costs!E40/(1-$U$33),0) -> 0 | U40: =ROUND(Costs!F40/(1-$U$33),0) -> 0 | V40: =ROUND(Costs!G40/(1-$U$33),0) -> 313 | W40: =ROUND(Costs!H40/(1-$U$33),0) -> 0 | X40: =ROUND(Costs!I40/(1-$U$33),0) -> 0 | Y40: =ROUND(Costs!J40/(1-$U$33),0) -> 0 | ... AD40: =ROUND(Costs!O40/(1-$U$33),0) -> 0
B41: Manager | C41: =ROUND(Costs!C41/(1-$F$33),0) -> 0 | D41: =ROUND(Costs!D41/(1-$F$33),0) -> 0 | E41: =ROUND(Costs!E41/(1-$F$33),0) -> 0 | F41: =ROUND(Costs!F41/(1-$F$33),0) -> 0 | G41: =ROUND(Costs!G41/(1-$F$33),0) -> 0 | H41: =ROUND(Costs!H41/(1-$F$33),0) -> 0 | I41: =ROUND(Costs!I41/(1-$F$33),0) -> 0 | J41: =ROUND(Costs!J41/(1-$F$33),0) -> 0 | ... O41: =ROUND(Costs!O41/(1-$F$33),0) -> 0 | Q41: Manager | R41: =ROUND(Costs!C41/(1-$U$33),0) -> 0 | S41: =ROUND(Costs!D41/(1-$U$33),0) -> 0 | T41: =ROUND(Costs!E41/(1-$U$33),0) -> 0 | U41: =ROUND(Costs!F41/(1-$U$33),0) -> 0 | V41: =ROUND(Costs!G41/(1-$U$33),0) -> 0 | W41: =ROUND(Costs!H41/(1-$U$33),0) -> 0 | X41: =ROUND(Costs!I41/(1-$U$33),0) -> 0 | Y41: =ROUND(Costs!J41/(1-$U$33),0) -> 0 | ... AD41: =ROUND(Costs!O41/(1-$U$33),0) -> 0
B42: Sr. Mgr | C42: =ROUND(Costs!C42/(1-$F$33),0) -> 0 | D42: =ROUND(Costs!D42/(1-$F$33),0) -> 168 | E42: =ROUND(Costs!E42/(1-$F$33),0) -> 0 | F42: =ROUND(Costs!F42/(1-$F$33),0) -> 0 | G42: =ROUND(Costs!G42/(1-$F$33),0) -> 0 | H42: =ROUND(Costs!H42/(1-$F$33),0) -> 0 | I42: =ROUND(Costs!I42/(1-$F$33),0) -> 65 | J42: =ROUND(Costs!J42/(1-$F$33),0) -> 0 | ... O42: =ROUND(Costs!O42/(1-$F$33),0) -> 0 | Q42: Sr. Mgr | R42: =ROUND(Costs!C42/(1-$U$33),0) -> 0 | S42: =ROUND(Costs!D42/(1-$U$33),0) -> 202 | T42: =ROUND(Costs!E42/(1-$U$33),0) -> 0 | U42: =ROUND(Costs!F42/(1-$U$33),0) -> 0 | V42: =ROUND(Costs!G42/(1-$U$33),0) -> 0 | W42: =ROUND(Costs!H42/(1-$U$33),0) -> 0 | X42: =ROUND(Costs!I42/(1-$U$33),0) -> 78 | Y42: =ROUND(Costs!J42/(1-$U$33),0) -> 0 | ... AD42: =ROUND(Costs!O42/(1-$U$33),0) -> 0
B43: EM | C43: =ROUND(Costs!C43/(1-$F$33),0) -> 636 | D43: =ROUND(Costs!D43/(1-$F$33),0) -> 462 | E43: =ROUND(Costs!E43/(1-$F$33),0) -> 0 | F43: =ROUND(Costs!F43/(1-$F$33),0) -> 0 | G43: =ROUND(Costs!G43/(1-$F$33),0) -> 0 | H43: =ROUND(Costs!H43/(1-$F$33),0) -> 0 | I43: =ROUND(Costs!I43/(1-$F$33),0) -> 0 | J43: =ROUND(Costs!J43/(1-$F$33),0) -> 0 | ... O43: =ROUND(Costs!O43/(1-$F$33),0) -> 0 | Q43: EM | R43: =ROUND(Costs!C43/(1-$U$33),0) -> 763 | S43: =ROUND(Costs!D43/(1-$U$33),0) -> 555 | T43: =ROUND(Costs!E43/(1-$U$33),0) -> 0 | U43: =ROUND(Costs!F43/(1-$U$33),0) -> 0 | V43: =ROUND(Costs!G43/(1-$U$33),0) -> 0 | W43: =ROUND(Costs!H43/(1-$U$33),0) -> 0 | X43: =ROUND(Costs!I43/(1-$U$33),0) -> 0 | Y43: =ROUND(Costs!J43/(1-$U$33),0) -> 0 | ... AD43: =ROUND(Costs!O43/(1-$U$33),0) -> 0
B44: Jr. Eng | C44: =ROUND(Costs!C44/(1-$F$33),0) -> 0 | D44: =ROUND(Costs!D44/(1-$F$33),0) -> 0 | E44: =ROUND(Costs!E44/(1-$F$33),0) -> 0 | F44: =ROUND(Costs!F44/(1-$F$33),0) -> 0 | G44: =ROUND(Costs!G44/(1-$F$33),0) -> 0 | H44: =ROUND(Costs!H44/(1-$F$33),0) -> 0 | I44: =ROUND(Costs!I44/(1-$F$33),0) -> 0 | J44: =ROUND(Costs!J44/(1-$F$33),0) -> 0 | ... O44: =ROUND(Costs!O44/(1-$F$33),0) -> 0 | Q44: Jr. Eng | R44: =ROUND(Costs!C44/(1-$U$33),0) -> 0 | S44: =ROUND(Costs!D44/(1-$U$33),0) -> 0 | T44: =ROUND(Costs!E44/(1-$U$33),0) -> 0 | U44: =ROUND(Costs!F44/(1-$U$33),0) -> 0 | V44: =ROUND(Costs!G44/(1-$U$33),0) -> 0 | W44: =ROUND(Costs!H44/(1-$U$33),0) -> 0 | X44: =ROUND(Costs!I44/(1-$U$33),0) -> 0 | Y44: =ROUND(Costs!J44/(1-$U$33),0) -> 0 | ... AD44: =ROUND(Costs!O44/(1-$U$33),0) -> 0

Sheet Calculator
E1: Updated: 2/15/2025 | F1: 0 | Q1: Work Area
F2: Choose from dropdowns below | J2: =IF(expiry_code=1,"The rate card has expired. Please download the latest version from Solution hub","")
E3: Is this a T&M or a Fixed price project? | F3: Fixed Price | H3: =IF(expiry_code=1,"The rate card has expired. Please download the latest version from Solution hub","")
E4: Which market is the project being delivered | F4: UK | H4: =IF(F5="Yes"," Enter details in table below (click here)","")
E5: Is there another RXT BU/3rd party/contractor involved? | F5: No | H5: Total cost from BU/3rd Party | I5: {=SUMPRODUCT(tb_supplier[Cost (per unit/ per hr/per day rate) to Rackspace],tb_supplier[Qty (In same as cost units)],(1+tb_supplier[Add contingency]))} -> 3500
E6: Currency | F6: GBP | H6: Internal BU/3rd Party margins | I6: =IFERROR(1-I5/I7,"") -> 0.35
E7: Days or Hours | F7: Days | H7: 3rd Party/Contractor Priced at | I7: =SUM(tb_supplier[Extended Price]) -> 5384.6154
E8: Is TCV likely >1M or is it a Govt. Project | F8: No | H8: Margins under high utilization assumptions | I8: =IFERROR(1-(F14*75%/85%*(1+Contingency) +SUM(F10:F11)*(1+Contingency)+F17+IF(F5="Yes",I5,0) ) /I11,"") -> 0.11766301
E9: Channel Partner (if any) | F9: None | H9: Any strategic discounts | I9: 0.5438929
H10: Summary
E11: Non Billable travel and other expenses | H11: Total Price | I11: =IFERROR((SUM(tb_resource[Extended Price],F10)+IF(F5="Yes",I7,0))*(1-I9),"") -> 99691.785 | J11: (from configuration below)
H12: ="Total " & F7 -> Total Days | I12: =IFERROR(SUMIFS(Calculator!$H$23:$H$43,Calculator!$B$23:$B$43,">"&0),"") -> 160 | J12: =F7 -> Days
H13: Deal Margin (Gross)* | I13: =IFERROR(1-F18/I11,"") -> 1.8075507e-05 | J13: =IF(I13<40%, "Approval Needed!","") -> Approval Needed!
E14: Resource cost estimate based on hrs | F14: =SUMPRODUCT($B$23:$B$43,$H$23:$H$43) -> 94942.841 | H14: *The gross margin is based on direct costs to deliver. Other company overheads such as Sales, Marketing,
H15: Corporate, R&D, etc ranges from 20-27%. We need to be greater than that!
E16: 3rd Party Delivery Partner cost w/o contingency | F16: =IF(F5="Yes",SUMPRODUCT(tb_supplier[Cost (per unit/ per hr/per day rate) to Rackspace],tb_supplier[Qty (In same as cost units)]),0) -> 0
E17: Channel Partner Cost | F17: =I11*IF($F$9="Master",10%,IF($F$9="Sub-agent",5%,0)) -> 0 | H17: Contingency | I17: =IF(F3="T&M",I19,I18) -> 0.05
E18: Total Cost | F18: =SUM(F10:F11,F14)*(1+Contingency) + SUM(IF(F5="Yes",I5,0),F17) -> 99689.983 | H18: Contingency Factored (enter) | I18: 0.05
E19: Contingency | F19: =IF(F8="Yes",F14*75%/85%,F14)*Contingency+SUM(F10:F11,F15)*(Contingency)+SUMPRODUCT(tb_supplier[Cost (per unit/ per hr/per day rate) to Rackspace],tb_supplier[Qty (In same as cost units)],tb_supplier[Add contingency])*IF(F5="Yes",1,0) -> 4747.142 | H19: Contingency (enter if any) | I19: 0
B21: Cost | C21: Flag if role is not planned | D21: SN | E21: Practice Area | F21: Region Sourced from | G21: Role | H21: =F7 -> Days | I21: ="Price/"& IF(F7="Hours","hr","day") -> Price/day | J21: Choose between "List price" or "Strategic margin/Price" | K21: Enter custom price or custom margin value | L21: Extended Price | M21: ="Cost/"& IF(F7="Hours","hr","day") -> Cost/day | N21: Margins | O21: ="Discounted Price/"& IF(F7="Hours","hr","day") & " after strategic discount" -> Discounted Price/day after strategic discount | P21: Note (requirements, if any) | Q21: Enter Comments | R21: Count of resources available in region | S21: Suggested min. Price | T21: Possible Cost | U21: Notes on the chosen role | V21: SOW Role (please select for the resourcing)
B22: Cost | C22: Flag if role is not planned | D22: SN | E22: Practice Area | F22: Region Sourced from | G22: Role | H22: Hours | I22: Price/hr | J22: Default Price or Strategic Margin | K22: Enter Margin Value | L22: Extended Price | M22: Column1 | N22: Margins | O22: Price | P22: Note (requirements, if any) | Q22: Comments | R22: Count of resources available in region | S22: Suggested min. Price | T22: cost of unavailable | U22: Other comments | V22: Sow roles
B23: =IFERROR( INDEX( CHOOSE( MATCH(E23, practices, 0), costAps, costData, costSec, costAdv, costProd, costPvtCld, costSdaia, costErp, costHealth ), MATCH($G23,INDIRECT( "roles_"&MATCH(E23, practices, 0)), 0), MATCH($F23, countries, 0)) * INDEX(fx, MATCH($F$6, currency, 0)) * IF($F$7 = "Days", 8, 1), "" ) -> 860.93851 | C23: =IF(AND( tb_resource[[#This Row],[Practice Area]]<>0,OR(R23=0,R23="")),1,0) -> 0 | D23: 1 | E23: Platform and Apps | F23: UK | G23: Sr. EM/Sr. PJM/PGM | H23: =LOE!N40 -> 37.5 | I23: =IFERROR(ROUNDUP(IF(J23="List Price",S23*IF($F$9="Master",1.1,IF($F$9="Sub-agent",1.05,1))*IF($F$3="Fixed Price",1.1,1),IF(K23<1,B23/(1-K23),K23)),0),"") -> 1863 | J23: List Price | K23: 186 | L23: =IF(S23="","",H23*I23) -> 69862.5 | M23: =B23 -> 860.93851 | N23: =IFERROR(1-B23/I23,"") -> 0.5378752 | O23: =IFERROR(tb_resource[[#This Row],[Price/hr]]*(1-$I$9),"") -> 849.72753 | P23: =IF(Calculator!$C23=-1,"No resource in region, please work with delivery and finance to get approvals for using this rate",IF(Calculator!$C23=1,"No resource in region or planned in future. Please get special approval from Finance and HR","")) | Q23: PM | R23: =IFERROR( INDEX( CHOOSE( MATCH(E23, practices, 0), countAps, countData, countSec, countAdv, countProd, CountPvtCld, countSdaia, countErp, CountHealth ), MATCH($G23, INDIRECT( "roles_"&MATCH(E23, practices, 0)), 0), MATCH($F23, countries, 0)), "" ) -> 129.65941 | S23: =IFERROR( INDEX( CHOOSE( MATCH(E23, practices, 0), priceAps, priceData, priceSec, priceAdv, priceProd, pricePvtCld, priceSdaia, priceErp, priceHealth ), MATCH($G23,INDIRECT( "roles_"&MATCH(E23, practices, 0)), 0), MATCH($F23, countries, 0)) * INDEX(fx, MATCH($F$6, currency, 0)) * IF($F$7 = "Days", 8, 1), "" ) -> 1693.2 | T23: =ROUNDUP(IFERROR( INDEX( CHOOSE( MATCH(E23, practices, 0), altcostAps, altcostData, altcostSec, altcostAdv, altcostProd, altcostPvtCld, altcostSdaia, altcostErp ), MATCH($G23,INDIRECT( "roles_"&MATCH(E23, practices, 0)), 0), MATCH($F23, countries, 0)) * INDEX(fx, MATCH($F$6, currency, 0)) * IF($F$7 = "Days", 8, 1), 0 ), 0) -> 809 | U23: =IF(AND(OR(T23=0,T23=""),tb_resource[[#This Row],[Flag if role is not planned]]=1),"This resource is not planned for this region. Check with PS delivery",IF(tb_resource[[#This Row],[Flag if role is not planned]]=1,"This resource is not available. Use cost = " & tb_resource[[#This Row],[cost of unavailable]] & " in the Table B below and check with PS delivery team",IFERROR("role also mapped to " & INDEX(Other_roles[Roles],MATCH(Calculator!$G23,Other_roles[mapped to],0)),""))) -> role also mapped to Program Manager
B24: =IFERROR( INDEX( CHOOSE( MATCH(E24, practices, 0), costAps, costData, costSec, costAdv, costProd, costPvtCld, costSdaia, costErp, costHealth ), MATCH($G24,INDIRECT( "roles_"&MATCH(E24, practices, 0)), 0), MATCH($F24, countries, 0)) * INDEX(fx, MATCH($F$6, currency, 0)) * IF($F$7 = "Days", 8, 1), "" ) -> 703.6593 | C24: =IF(AND( tb_resource[[#This Row],[Practice Area]]<>0,OR(R24=0,R24="")),1,0) -> 0 | D24: =IF(E24="","",D23+1) -> 2 | E24: Platform and Apps | F24: NL | G24: Arch | H24: =LOE!N41 -> 40 | I24: =IFERROR(ROUNDUP(IF(J24="List Price",S24*IF($F$9="Master",1.1,IF($F$9="Sub-agent",1.05,1))*IF($F$3="Fixed Price",1.1,1),IF(K24<1,B24/(1-K24),K24)),0),"") -> 1644 | J24: List Price | K24: 0.5 | L24: =IF(S24="","",H24*I24) -> 65760 | M24: =B24 -> 703.6593 | N24: =IFERROR(1-B24/I24,"") -> 0.57198339 | O24: =IFERROR(tb_resource[[#This Row],[Price/hr]]*(1-$I$9),"") -> 749.84007 | P24: =IF(Calculator!$C24=-1,"No resource in region, please work with delivery and finance to get approvals for using this rate",IF(Calculator!$C24=1,"No resource in region or planned in future. Please get special approval from Finance and HR","")) | Q24: Lead Consulting Architect | R24: =IFERROR( INDEX( CHOOSE( MATCH(E24, practices, 0), countAps, countData, countSec, countAdv, countProd, CountPvtCld, countSdaia, countErp, CountHealth ), MATCH($G24, INDIRECT( "roles_"&MATCH(E24, practices, 0)), 0), MATCH($F24, countries, 0)), "" ) -> 133.37062 | S24: =IFERROR( INDEX( CHOOSE( MATCH(E24, practices, 0), priceAps, priceData, priceSec, priceAdv, priceProd, pricePvtCld, priceSdaia, priceErp, priceHealth ), MATCH($G24,INDIRECT( "roles_"&MATCH(E24, practices, 0)), 0), MATCH($F24, countries, 0)) * INDEX(fx, MATCH($F$6, currency, 0)) * IF($F$7 = "Days", 8, 1), "" ) -> 1494 | T24: =ROUNDUP(IFERROR( INDEX( CHOOSE( MATCH(E24, practices, 0), altcostAps, altcostData, altcostSec, altcostAdv, altcostProd, altcostPvtCld, altcostSdaia, altcostErp ), MATCH($G24,INDIRECT( "roles_"&MATCH(E24, practices, 0)), 0), MATCH($F24, countries, 0)) * INDEX(fx, MATCH($F$6, currency, 0)) * IF($F$7 = "Days", 8, 1), 0 ), 0) -> 804 | U24: =IF(AND(OR(T24=0,T24=""),tb_resource[[#This Row],[Flag if role is not planned]]=1),"This resource is not planned for this region. Check with PS delivery",IF(tb_resource[[#This Row],[Flag if role is not planned]]=1,"This resource is not available. Use cost = " & tb_resource[[#This Row],[cost of unavailable]] & " in the Table B below and check with PS delivery team",IFERROR("role also mapped to " & INDEX(Other_roles[Roles],MATCH(Calculator!$G24,Other_roles[mapped to],0)),""))) -> role also mapped to Subject Matter Expert (SME) & Security Consultant
B25: =IFERROR( INDEX( CHOOSE( MATCH(E25, practices, 0), costAps, costData, costSec, costAdv, costProd, costPvtCld, costSdaia, costErp, costHealth ), MATCH($G25,INDIRECT( "roles_"&MATCH(E25, practices, 0)), 0), MATCH($F25, countries, 0)) * INDEX(fx, MATCH($F$6, currency, 0)) * IF($F$7 = "Days", 8, 1), "" ) -> 940.26243 | C25: =IF(AND( tb_resource[[#This Row],[Practice Area]]<>0,OR(R25=0,R25="")),1,0) -> 0 | D25: =IF(E25="","",D24+1) -> 3 | E25: Platform and Apps | F25: UK | G25: Arch | H25: =LOE!N46 -> 4 | I25: =IFERROR(ROUNDUP(IF(J25="List Price",S25*IF($F$9="Master",1.1,IF($F$9="Sub-agent",1.05,1))*IF($F$3="Fixed Price",1.1,1),IF(K25<1,B25/(1-K25),K25)),0),"") -> 1826 | J25: List Price | K25: 0.5 | L25: =IF(S25="","",H25*I25) -> 7304 | M25: =B25 -> 940.26243 | N25: =IFERROR(1-B25/I25,"") -> 0.48506986 | O25: =IFERROR(tb_resource[[#This Row],[Price/hr]]*(1-$I$9),"") -> 832.85156 | P25: =IF(Calculator!$C25=-1,"No resource in region, please work with delivery and finance to get approvals for using this rate",IF(Calculator!$C25=1,"No resource in region or planned in future. Please get special approval from Finance and HR","")) | Q25: Migration Consultant | R25: =IFERROR( INDEX( CHOOSE( MATCH(E25, practices, 0), countAps, countData, countSec, countAdv, countProd, CountPvtCld, countSdaia, countErp, CountHealth ), MATCH($G25, INDIRECT( "roles_"&MATCH(E25, practices, 0)), 0), MATCH($F25, countries, 0)), "" ) -> 129.99811 | S25: =IFERROR( INDEX( CHOOSE( MATCH(E25, practices, 0), priceAps, priceData, priceSec, priceAdv, priceProd, pricePvtCld, priceSdaia, priceErp, priceHealth ), MATCH($G25,INDIRECT( "roles_"&MATCH(E25, practices, 0)), 0), MATCH($F25, countries, 0)) * INDEX(fx, MATCH($F$6, currency, 0)) * IF($F$7 = "Days", 8, 1), "" ) -> 1660 | T25: =ROUNDUP(IFERROR( INDEX( CHOOSE( MATCH(E25, practices, 0), altcostAps, altcostData, altcostSec, altcostAdv, altcostProd, altcostPvtCld, altcostSdaia, altcostErp ), MATCH($G25,INDIRECT( "roles_"&MATCH(E25, practices, 0)), 0), MATCH($F25, countries, 0)) * INDEX(fx, MATCH($F$6, currency, 0)) * IF($F$7 = "Days", 8, 1), 0 ), 0) -> 884 | U25: =IF(AND(OR(T25=0,T25=""),tb_resource[[#This Row],[Flag if role is not planned]]=1),"This resource is not planned for this region. Check with PS delivery",IF(tb_resource[[#This Row],[Flag if role is not planned]]=1,"This resource is not available. Use cost = " & tb_resource[[#This Row],[cost of unavailable]] & " in the Table B below and check with PS delivery team",IFERROR("role also mapped to " & INDEX(Other_roles[Roles],MATCH(Calculator!$G25,Other_roles[mapped to],0)),""))) -> role also mapped to Subject Matter Expert (SME) & Security Consultant
B26: =IFERROR( INDEX( CHOOSE( MATCH(E26, practices, 0), costAps, costData, costSec, costAdv, costProd, costPvtCld, costSdaia, costErp, costHealth ), MATCH($G26,INDIRECT( "roles_"&MATCH(E26, practices, 0)), 0), MATCH($F26, countries, 0)) * INDEX(fx, MATCH($F$6, currency, 0)) * IF($F$7 = "Days", 8, 1), "" ) -> 278.88 | C26: =IF(AND( tb_resource[[#This Row],[Practice Area]]<>0,OR(R26=0,R26="")),1,0) -> 0 | D26: =IF(E26="","",D25+1) -> 4 | E26: Platform and Apps | F26: IN | G26: Arch | H26: =LOE!N42 -> 22 | I26: =IFERROR(ROUNDUP(IF(J26="List Price",S26*IF($F$9="Master",1.1,IF($F$9="Sub-agent",1.05,1))*IF($F$3="Fixed Price",1.1,1),IF(K26<1,B26/(1-K26),K26)),0),"") -> 731 | J26: List Price | K26: 0.5 | L26: =IF(S26="","",H26*I26) -> 16082 | M26: =B26 -> 278.88 | N26: =IFERROR(1-B26/I26,"") -> 0.61849521 | O26: =IFERROR(tb_resource[[#This Row],[Price/hr]]*(1-$I$9),"") -> 333.41429 | P26: =IF(Calculator!$C26=-1,"No resource in region, please work with delivery and finance to get approvals for using this rate",IF(Calculator!$C26=1,"No resource in region or planned in future. Please get special approval from Finance and HR","")) | Q26: Platform Architect (AWS) | R26: =IFERROR( INDEX( CHOOSE( MATCH(E26, practices, 0), countAps, countData, countSec, countAdv, countProd, CountPvtCld, countSdaia, countErp, CountHealth ), MATCH($G26, INDIRECT( "roles_"&MATCH(E26, practices, 0)), 0), MATCH($F26, countries, 0)), "" ) -> 41.69704 | S26: =IFERROR( INDEX( CHOOSE( MATCH(E26, practices, 0), priceAps, priceData, priceSec, priceAdv, priceProd, pricePvtCld, priceSdaia, priceErp, priceHealth ), MATCH($G26,INDIRECT( "roles_"&MATCH(E26, practices, 0)), 0), MATCH($F26, countries, 0)) * INDEX(fx, MATCH($F$6, currency, 0)) * IF($F$7 = "Days", 8, 1), "" ) -> 664 | T26: =ROUNDUP(IFERROR( INDEX( CHOOSE( MATCH(E26, practices, 0), altcostAps, altcostData, altcostSec, altcostAdv, altcostProd, altcostPvtCld, altcostSdaia, altcostErp ), MATCH($G26,INDIRECT( "roles_"&MATCH(E26, practices, 0)), 0), MATCH($F26, countries, 0)) * INDEX(fx, MATCH($F$6, currency, 0)) * IF($F$7 = "Days", 8, 1), 0 ), 0) -> 244 | U26: =IF(AND(OR(T26=0,T26=""),tb_resource[[#This Row],[Flag if role is not planned]]=1),"This resource is not planned for this region. Check with PS delivery",IF(tb_resource[[#This Row],[Flag if role is not planned]]=1,"This resource is not available. Use cost = " & tb_resource[[#This Row],[cost of unavailable]] & " in the Table B below and check with PS delivery team",IFERROR("role also mapped to " & INDEX(Other_roles[Roles],MATCH(Calculator!$G26,Other_roles[mapped to],0)),""))) -> role also mapped to Subject Matter Expert (SME) & Security Consultant
B27: =IFERROR( INDEX( CHOOSE( MATCH(E27, practices, 0), costAps, costData, costSec, costAdv, costProd, costPvtCld, costSdaia, costErp, costHealth ), MATCH($G27,INDIRECT( "roles_"&MATCH(E27, practices, 0)), 0), MATCH($F27, countries, 0)) * INDEX(fx, MATCH($F$6, currency, 0)) * IF($F$7 = "Days", 8, 1), "" ) -> 278.88 | C27: =IF(AND( tb_resource[[#This Row],[Practice Area]]<>0,OR(R27=0,R27="")),1,0) -> 0 | D27: =IF(E27="","",D26+1) -> 5 | E27: Platform and Apps | F27: IN | G27: Arch | H27: =LOE!N43 -> 22 | I27: =IFERROR(ROUNDUP(IF(J27="List Price",S27*IF($F$9="Master",1.1,IF($F$9="Sub-agent",1.05,1))*IF($F$3="Fixed Price",1.1,1),IF(K27<1,B27/(1-K27),K27)),0),"") -> 731 | J27: List Price | K27: 0.5 | L27: =IF(S27="","",H27*I27) -> 16082 | M27: =B27 -> 278.88 | N27: =IFERROR(1-B27/I27,"") -> 0.61849521 | O27: =IFERROR(tb_resource[[#This Row],[Price/hr]]*(1-$I$9),"") -> 333.41429 | P27: =IF(Calculator!$C27=-1,"No resource in region, please work with delivery and finance to get approvals for using this rate",IF(Calculator!$C27=1,"No resource in region or planned in future. Please get special approval from Finance and HR","")) | Q27: Platform Architect (Azure) | R27: =IFERROR( INDEX( CHOOSE( MATCH(E27, practices, 0), countAps, countData, countSec, countAdv, countProd, CountPvtCld, countSdaia, countErp, CountHealth ), MATCH($G27, INDIRECT( "roles_"&MATCH(E27, practices, 0)), 0), MATCH($F27, countries, 0)), "" ) -> 41.69704 | S27: =IFERROR( INDEX( CHOOSE( MATCH(E27, practices, 0), priceAps, priceData, priceSec, priceAdv, priceProd, pricePvtCld, priceSdaia, priceErp, priceHealth ), MATCH($G27,INDIRECT( "roles_"&MATCH(E27, practices, 0)), 0), MATCH($F27, countries, 0)) * INDEX(fx, MATCH($F$6, currency, 0)) * IF($F$7 = "Days", 8, 1), "" ) -> 664 | T27: =ROUNDUP(IFERROR( INDEX( CHOOSE( MATCH(E27, practices, 0), altcostAps, altcostData, altcostSec, altcostAdv, altcostProd, altcostPvtCld, altcostSdaia, altcostErp ), MATCH($G27,INDIRECT( "roles_"&MATCH(E27, practices, 0)), 0), MATCH($F27, countries, 0)) * INDEX(fx, MATCH($F$6, currency, 0)) * IF($F$7 = "Days", 8, 1), 0 ), 0) -> 244 | U27: =IF(AND(OR(T27=0,T27=""),tb_resource[[#This Row],[Flag if role is not planned]]=1),"This resource is not planned for this region. Check with PS delivery",IF(tb_resource[[#This Row],[Flag if role is not planned]]=1,"This resource is not available. Use cost = " & tb_resource[[#This Row],[cost of unavailable]] & " in the Table B below and check with PS delivery team",IFERROR("role also mapped to " & INDEX(Other_roles[Roles],MATCH(Calculator!$G27,Other_roles[mapped to],0)),""))) -> role also mapped to Subject Matter Expert (SME) & Security Consultant
B28: =IFERROR( INDEX( CHOOSE( MATCH(E28, practices, 0), costAps, costData, costSec, costAdv, costProd, costPvtCld, costSdaia, costErp, costHealth ), MATCH($G28,INDIRECT( "roles_"&MATCH(E28, practices, 0)), 0), MATCH($F28, countries, 0)) * INDEX(fx, MATCH($F$6, currency, 0)) * IF($F$7 = "Days", 8, 1), "" ) -> 703.6593 | C28: =IF(AND( tb_resource[[#This Row],[Practice Area]]<>0,OR(R28=0,R28="")),1,0) -> 0 | D28: =IF(E28="","",D27+1) -> 6 | E28: Platform and Apps | F28: NL | G28: Arch | H28: =LOE!N44 -> 22 | I28: =IFERROR(ROUNDUP(IF(J28="List Price",S28*IF($F$9="Master",1.1,IF($F$9="Sub-agent",1.05,1))*IF($F$3="Fixed Price",1.1,1),IF(K28<1,B28/(1-K28),K28)),0),"") -> 1644 | J28: List Price | K28: 0.4 | L28: =IF(S28="","",H28*I28) -> 36168 | M28: =B28 -> 703.6593 | N28: =IFERROR(1-B28/I28,"") -> 0.57198339 | O28: =IFERROR(tb_resource[[#This Row],[Price/hr]]*(1-$I$9),"") -> 749.84007 | P28: =IF(Calculator!$C28=-1,"No resource in region, please work with delivery and finance to get approvals for using this rate",IF(Calculator!$C28=1,"No resource in region or planned in future. Please get special approval from Finance and HR","")) | Q28: Platform Architect (GCP) | R28: =IFERROR( INDEX( CHOOSE( MATCH(E28, practices, 0), countAps, countData, countSec, countAdv, countProd, CountPvtCld, countSdaia, countErp, CountHealth ), MATCH($G28, INDIRECT( "roles_"&MATCH(E28, practices, 0)), 0), MATCH($F28, countries, 0)), "" ) -> 133.37062 | S28: =IFERROR( INDEX( CHOOSE( MATCH(E28, practices, 0), priceAps, priceData, priceSec, priceAdv, priceProd, pricePvtCld, priceSdaia, priceErp, priceHealth ), MATCH($G28,INDIRECT( "roles_"&MATCH(E28, practices, 0)), 0), MATCH($F28, countries, 0)) * INDEX(fx, MATCH($F$6, currency, 0)) * IF($F$7 = "Days", 8, 1), "" ) -> 1494 | T28: =ROUNDUP(IFERROR( INDEX( CHOOSE( MATCH(E28, practices, 0), altcostAps, altcostData, altcostSec, altcostAdv, altcostProd, altcostPvtCld, altcostSdaia, altcostErp ), MATCH($G28,INDIRECT( "roles_"&MATCH(E28, practices, 0)), 0), MATCH($F28, countries, 0)) * INDEX(fx, MATCH($F$6, currency, 0)) * IF($F$7 = "Days", 8, 1), 0 ), 0) -> 804 | U28: =IF(AND(OR(T28=0,T28=""),tb_resource[[#This Row],[Flag if role is not planned]]=1),"This resource is not planned for this region. Check with PS delivery",IF(tb_resource[[#This Row],[Flag if role is not planned]]=1,"This resource is not available. Use cost = " & tb_resource[[#This Row],[cost of unavailable]] & " in the Table B below and check with PS delivery team",IFERROR("role also mapped to " & INDEX(Other_roles[Roles],MATCH(Calculator!$G28,Other_roles[mapped to],0)),""))) -> role also mapped to Subject Matter Expert (SME) & Security Consultant
B29: =IFERROR( INDEX( CHOOSE( MATCH(E29, practices, 0), costAps, costData, costSec, costAdv, costProd, costPvtCld, costSdaia, costErp, costHealth ), MATCH($G29,INDIRECT( "roles_"&MATCH(E29, practices, 0)), 0), MATCH($F29, countries, 0)) * INDEX(fx, MATCH($F$6, currency, 0)) * IF($F$7 = "Days", 8, 1), "" ) -> 239.92004 | C29: =IF(AND( tb_resource[[#This Row],[Practice Area]]<>0,OR(R29=0,R29="")),1,0) -> 0 | D29: =IF(E29="","",D28+1) -> 7 | E29: Platform and Apps | F29: IN | G29: Sr. Eng | H29: =LOE!N45 -> 12.5 | I29: =IFERROR(ROUNDUP(IF(J29="List Price",S29*IF($F$9="Master",1.1,IF($F$9="Sub-agent",1.05,1))*IF($F$3="Fixed Price",1.1,1),IF(K29<1,B29/(1-K29),K29)),0),"") -> 585 | J29: List Price | K29: 0.5 | L29: =IF(S29="","",H29*I29) -> 7312.5 | M29: =B29 -> 239.92004 | N29: =IFERROR(1-B29/I29,"") -> 0.58988028 | O29: =IFERROR(tb_resource[[#This Row],[Price/hr]]*(1-$I$9),"") -> 266.82265 | P29: =IF(Calculator!$C29=-1,"No resource in region, please work with delivery and finance to get approvals for using this rate",IF(Calculator!$C29=1,"No resource in region or planned in future. Please get special approval from Finance and HR","")) | Q29: Cloud Engineer | R29: =IFERROR( INDEX( CHOOSE( MATCH(E29, practices, 0), countAps, countData, countSec, countAdv, countProd, CountPvtCld, countSdaia, countErp, CountHealth ), MATCH($G29, INDIRECT( "roles_"&MATCH(E29, practices, 0)), 0), MATCH($F29, countries, 0)), "" ) -> 36.132536 | S29: =IFERROR( INDEX( CHOOSE( MATCH(E29, practices, 0), priceAps, priceData, priceSec, priceAdv, priceProd, pricePvtCld, priceSdaia, priceErp, priceHealth ), MATCH($G29,INDIRECT( "roles_"&MATCH(E29, practices, 0)), 0), MATCH($F29, countries, 0)) * INDEX(fx, MATCH($F$6, currency, 0)) * IF($F$7 = "Days", 8, 1), "" ) -> 531.2 | T29: =ROUNDUP(IFERROR( INDEX( CHOOSE( MATCH(E29, practices, 0), altcostAps, altcostData, altcostSec, altcostAdv, altcostProd, altcostPvtCld, altcostSdaia, altcostErp ), MATCH($G29,INDIRECT( "roles_"&MATCH(E29, practices, 0)), 0), MATCH($F29, countries, 0)) * INDEX(fx, MATCH($F$6, currency, 0)) * IF($F$7 = "Days", 8, 1), 0 ), 0) -> 183 | U29: =IF(AND(OR(T29=0,T29=""),tb_resource[[#This Row],[Flag if role is not planned]]=1),"This resource is not planned for this region. Check with PS delivery",IF(tb_resource[[#This Row],[Flag if role is not planned]]=1,"This resource is not available. Use cost = " & tb_resource[[#This Row],[cost of unavailable]] & " in the Table B below and check with PS delivery team",IFERROR("role also mapped to " & INDEX(Other_roles[Roles],MATCH(Calculator!$G29,Other_roles[mapped to],0)),""))) -> role also mapped to Engineer III, IV
B30: =IFERROR( INDEX( CHOOSE( MATCH(E30, practices, 0), costAps, costData, costSec, costAdv, costProd, costPvtCld, costSdaia, costErp, costHealth ), MATCH($G30,INDIRECT( "roles_"&MATCH(E30, practices, 0)), 0), MATCH($F30, countries, 0)) * INDEX(fx, MATCH($F$6, currency, 0)) * IF($F$7 = "Days", 8, 1), "" ) | C30: =IF(AND( tb_resource[[#This Row],[Practice Area]]<>0,OR(R30=0,R30="")),1,0) -> 0 | D30: =IF(E30="","",D29+1) | I30: =IFERROR(ROUNDUP(IF(J30="List Price",S30*IF($F$9="Master",1.1,IF($F$9="Sub-agent",1.05,1))*IF($F$3="Fixed Price",1.1,1),IF(K30<1,B30/(1-K30),K30)),0),"") | J30: List Price | K30: 0.5 | L30: =IF(S30="","",H30*I30) | M30: =B30 | N30: =IFERROR(1-B30/I30,"") | O30: =IFERROR(tb_resource[[#This Row],[Price/hr]]*(1-$I$9),"") | P30: =IF(Calculator!$C30=-1,"No resource in region, please work with delivery and finance to get approvals for using this rate",IF(Calculator!$C30=1,"No resource in region or planned in future. Please get special approval from Finance and HR","")) | R30: =IFERROR( INDEX( CHOOSE( MATCH(E30, practices, 0), countAps, countData, countSec, countAdv, countProd, CountPvtCld, countSdaia, countErp, CountHealth ), MATCH($G30, INDIRECT( "roles_"&MATCH(E30, practices, 0)), 0), MATCH($F30, countries, 0)), "" ) | S30: =IFERROR( INDEX( CHOOSE( MATCH(E30, practices, 0), priceAps, priceData, priceSec, priceAdv, priceProd, pricePvtCld, priceSdaia, priceErp, priceHealth ), MATCH($G30,INDIRECT( "roles_"&MATCH(E30, practices, 0)), 0), MATCH($F30, countries, 0)) * INDEX(fx, MATCH($F$6, currency, 0)) * IF($F$7 = "Days", 8, 1), "" ) | T30: =ROUNDUP(IFERROR( INDEX( CHOOSE( MATCH(E30, practices, 0), altcostAps, altcostData, altcostSec, altcostAdv, altcostProd, altcostPvtCld, altcostSdaia, altcostErp ), MATCH($G30,INDIRECT( "roles_"&MATCH(E30, practices, 0)), 0), MATCH($F30, countries, 0)) * INDEX(fx, MATCH($F$6, currency, 0)) * IF($F$7 = "Days", 8, 1), 0 ), 0) -> 0 | U30: =IF(AND(OR(T30=0,T30=""),tb_resource[[#This Row],[Flag if role is not planned]]=1),"This resource is not planned for this region. Check with PS delivery",IF(tb_resource[[#This Row],[Flag if role is not planned]]=1,"This resource is not available. Use cost = " & tb_resource[[#This Row],[cost of unavailable]] & " in the Table B below and check with PS delivery team",IFERROR("role also mapped to " & INDEX(Other_roles[Roles],MATCH(Calculator!$G30,Other_roles[mapped to],0)),"")))
B31: =IFERROR( INDEX( CHOOSE( MATCH(E31, practices, 0), costAps, costData, costSec, costAdv, costProd, costPvtCld, costSdaia, costErp, costHealth ), MATCH($G31,INDIRECT( "roles_"&MATCH(E31, practices, 0)), 0), MATCH($F31, countries, 0)) * INDEX(fx, MATCH($F$6, currency, 0)) * IF($F$7 = "Days", 8, 1), "" ) | C31: =IF(AND( tb_resource[[#This Row],[Practice Area]]<>0,OR(R31=0,R31="")),1,0) -> 0 | D31: =IF(E31="","",D30+1) | I31: =IFERROR(ROUNDUP(IF(J31="List Price",S31*IF($F$9="Master",1.1,IF($F$9="Sub-agent",1.05,1))*IF($F$3="Fixed Price",1.1,1),IF(K31<1,B31/(1-K31),K31)),0),"") | J31: List Price | K31: 0.5 | L31: =IF(S31="","",H31*I31) | M31: =B31 | N31: =IFERROR(1-B31/I31,"") | O31: =IFERROR(tb_resource[[#This Row],[Price/hr]]*(1-$I$9),"") | P31: =IF(Calculator!$C31=-1,"No resource in region, please work with delivery and finance to get approvals for using this rate",IF(Calculator!$C31=1,"No resource in region or planned in future. Please get special approval from Finance and HR","")) | R31: =IFERROR( INDEX( CHOOSE( MATCH(E31, practices, 0), countAps, countData, countSec, countAdv, countProd, CountPvtCld, countSdaia, countErp, CountHealth ), MATCH($G31, INDIRECT( "roles_"&MATCH(E31, practices, 0)), 0), MATCH($F31, countries, 0)), "" ) | S31: =IFERROR( INDEX( CHOOSE( MATCH(E31, practices, 0), priceAps, priceData, priceSec, priceAdv, priceProd, pricePvtCld, priceSdaia, priceErp, priceHealth ), MATCH($G31,INDIRECT( "roles_"&MATCH(E31, practices, 0)), 0), MATCH($F31, countries, 0)) * INDEX(fx, MATCH($F$6, currency, 0)) * IF($F$7 = "Days", 8, 1), "" ) | T31: =ROUNDUP(IFERROR( INDEX( CHOOSE( MATCH(E31, practices, 0), altcostAps, altcostData, altcostSec, altcostAdv, altcostProd, altcostPvtCld, altcostSdaia, altcostErp ), MATCH($G31,INDIRECT( "roles_"&MATCH(E31, practices, 0)), 0), MATCH($F31, countries, 0)) * INDEX(fx, MATCH($F$6, currency, 0)) * IF($F$7 = "Days", 8, 1), 0 ), 0) -> 0 | U31: =IF(AND(OR(T31=0,T31=""),tb_resource[[#This Row],[Flag if role is not planned]]=1),"This resource is not planned for this region. Check with PS delivery",IF(tb_resource[[#This Row],[Flag if role is not planned]]=1,"This resource is not available. Use cost = " & tb_resource[[#This Row],[cost of unavailable]] & " in the Table B below and check with PS delivery team",IFERROR("role also mapped to " & INDEX(Other_roles[Roles],MATCH(Calculator!$G31,Other_roles[mapped to],0)),"")))
B32: =IFERROR( INDEX( CHOOSE( MATCH(E32, practices, 0), costAps, costData, costSec, costAdv, costProd, costPvtCld, costSdaia, costErp, costHealth ), MATCH($G32,INDIRECT( "roles_"&MATCH(E32, practices, 0)), 0), MATCH($F32, countries, 0)) * INDEX(fx, MATCH($F$6, currency, 0)) * IF($F$7 = "Days", 8, 1), "" ) | C32: =IF(AND( tb_resource[[#This Row],[Practice Area]]<>0,OR(R32=0,R32="")),1,0) -> 0 | D32: =IF(E32="","",D31+1) | I32: =IFERROR(ROUNDUP(IF(J32="List Price",S32*IF($F$9="Master",1.1,IF($F$9="Sub-agent",1.05,1))*IF($F$3="Fixed Price",1.1,1),IF(K32<1,B32/(1-K32),K32)),0),"") | J32: List Price | K32: 0.5 | L32: =IF(S32="","",H32*I32) | M32: =B32 | N32: =IFERROR(1-B32/I32,"") | O32: =IFERROR(tb_resource[[#This Row],[Price/hr]]*(1-$I$9),"") | P32: =IF(Calculator!$C32=-1,"No resource in region, please work with delivery and finance to get approvals for using this rate",IF(Calculator!$C32=1,"No resource in region or planned in future. Please get special approval from Finance and HR","")) | R32: =IFERROR( INDEX( CHOOSE( MATCH(E32, practices, 0), countAps, countData, countSec, countAdv, countProd, CountPvtCld, countSdaia, countErp, CountHealth ), MATCH($G32, INDIRECT( "roles_"&MATCH(E32, practices, 0)), 0), MATCH($F32, countries, 0)), "" ) | S32: =IFERROR( INDEX( CHOOSE( MATCH(E32, practices, 0), priceAps, priceData, priceSec, priceAdv, priceProd, pricePvtCld, priceSdaia, priceErp, priceHealth ), MATCH($G32,INDIRECT( "roles_"&MATCH(E32, practices, 0)), 0), MATCH($F32, countries, 0)) * INDEX(fx, MATCH($F$6, currency, 0)) * IF($F$7 = "Days", 8, 1), "" ) | T32: =ROUNDUP(IFERROR( INDEX( CHOOSE( MATCH(E32, practices, 0), altcostAps, altcostData, altcostSec, altcostAdv, altcostProd, altcostPvtCld, altcostSdaia, altcostErp ), MATCH($G32,INDIRECT( "roles_"&MATCH(E32, practices, 0)), 0), MATCH($F32, countries, 0)) * INDEX(fx, MATCH($F$6, currency, 0)) * IF($F$7 = "Days", 8, 1), 0 ), 0) -> 0 | U32: =IF(AND(OR(T32=0,T32=""),tb_resource[[#This Row],[Flag if role is not planned]]=1),"This resource is not planned for this region. Check with PS delivery",IF(tb_resource[[#This Row],[Flag if role is not planned]]=1,"This resource is not available. Use cost = " & tb_resource[[#This Row],[cost of unavailable]] & " in the Table B below and check with PS delivery team",IFERROR("role also mapped to " & INDEX(Other_roles[Roles],MATCH(Calculator!$G32,Other_roles[mapped to],0)),"")))
B33: =IFERROR( INDEX( CHOOSE( MATCH(E33, practices, 0), costAps, costData, costSec, costAdv, costProd, costPvtCld, costSdaia, costErp, costHealth ), MATCH($G33,INDIRECT( "roles_"&MATCH(E33, practices, 0)), 0), MATCH($F33, countries, 0)) * INDEX(fx, MATCH($F$6, currency, 0)) * IF($F$7 = "Days", 8, 1), "" ) | C33: =IF(AND( tb_resource[[#This Row],[Practice Area]]<>0,OR(R33=0,R33="")),1,0) -> 0 | D33: =IF(E33="","",D32+1) | I33: =IFERROR(ROUNDUP(IF(J33="List Price",S33*IF($F$9="Master",1.1,IF($F$9="Sub-agent",1.05,1))*IF($F$3="Fixed Price",1.1,1),IF(K33<1,B33/(1-K33),K33)),0),"") | J33: List Price | K33: 0.5 | L33: =IF(S33="","",H33*I33) | M33: =B33 | N33: =IFERROR(1-B33/I33,"") | O33: =IFERROR(tb_resource[[#This Row],[Price/hr]]*(1-$I$9),"") | P33: =IF(Calculator!$C33=-1,"No resource in region, please work with delivery and finance to get approvals for using this rate",IF(Calculator!$C33=1,"No resource in region or planned in future. Please get special approval from Finance and HR","")) | R33: =IFERROR( INDEX( CHOOSE( MATCH(E33, practices, 0), countAps, countData, countSec, countAdv, countProd, CountPvtCld, countSdaia, countErp, CountHealth ), MATCH($G33, INDIRECT( "roles_"&MATCH(E33, practices, 0)), 0), MATCH($F33, countries, 0)), "" ) | S33: =IFERROR( INDEX( CHOOSE( MATCH(E33, practices, 0), priceAps, priceData, priceSec, priceAdv, priceProd, pricePvtCld, priceSdaia, priceErp, priceHealth ), MATCH($G33,INDIRECT( "roles_"&MATCH(E33, practices, 0)), 0), MATCH($F33, countries, 0)) * INDEX(fx, MATCH($F$6, currency, 0)) * IF($F$7 = "Days", 8, 1), "" ) | T33: =ROUNDUP(IFERROR( INDEX( CHOOSE( MATCH(E33, practices, 0), altcostAps, altcostData, altcostSec, altcostAdv, altcostProd, altcostPvtCld, altcostSdaia, altcostErp ), MATCH($G33,INDIRECT( "roles_"&MATCH(E33, practices, 0)), 0), MATCH($F33, countries, 0)) * INDEX(fx, MATCH($F$6, currency, 0)) * IF($F$7 = "Days", 8, 1), 0 ), 0) -> 0 | U33: =IF(AND(OR(T33=0,T33=""),tb_resource[[#This Row],[Flag if role is not planned]]=1),"This resource is not planned for this region. Check with PS delivery",IF(tb_resource[[#This Row],[Flag if role is not planned]]=1,"This resource is not available. Use cost = " & tb_resource[[#This Row],[cost of unavailable]] & " in the Table B below and check with PS delivery team",IFERROR("role also mapped to " & INDEX(Other_roles[Roles],MATCH(Calculator!$G33,Other_roles[mapped to],0)),"")))
B34: =IFERROR( INDEX( CHOOSE( MATCH(E34, practices, 0), costAps, costData, costSec, costAdv, costProd, costPvtCld, costSdaia, costErp, costHealth ), MATCH($G34,INDIRECT( "roles_"&MATCH(E34, practices, 0)), 0), MATCH($F34, countries, 0)) * INDEX(fx, MATCH($F$6, currency, 0)) * IF($F$7 = "Days", 8, 1), "" ) | C34: =IF(AND( tb_resource[[#This Row],[Practice Area]]<>0,OR(R34=0,R34="")),1,0) -> 0 | D34: =IF(E34="","",D33+1) | I34: =IFERROR(ROUNDUP(IF(J34="List Price",S34*IF($F$9="Master",1.1,IF($F$9="Sub-agent",1.05,1))*IF($F$3="Fixed Price",1.1,1),IF(K34<1,B34/(1-K34),K34)),0),"") | J34: List Price | K34: 0.5 | L34: =IF(S34="","",H34*I34) | M34: =B34 | N34: =IFERROR(1-B34/I34,"") | O34: =IFERROR(tb_resource[[#This Row],[Price/hr]]*(1-$I$9),"") | P34: =IF(Calculator!$C34=-1,"No resource in region, please work with delivery and finance to get approvals for using this rate",IF(Calculator!$C34=1,"No resource in region or planned in future. Please get special approval from Finance and HR","")) | R34: =IFERROR( INDEX( CHOOSE( MATCH(E34, practices, 0), countAps, countData, countSec, countAdv, countProd, CountPvtCld, countSdaia, countErp, CountHealth ), MATCH($G34, INDIRECT( "roles_"&MATCH(E34, practices, 0)), 0), MATCH($F34, countries, 0)), "" ) | S34: =IFERROR( INDEX( CHOOSE( MATCH(E34, practices, 0), priceAps, priceData, priceSec, priceAdv, priceProd, pricePvtCld, priceSdaia, priceErp, priceHealth ), MATCH($G34,INDIRECT( "roles_"&MATCH(E34, practices, 0)), 0), MATCH($F34, countries, 0)) * INDEX(fx, MATCH($F$6, currency, 0)) * IF($F$7 = "Days", 8, 1), "" ) | T34: =ROUNDUP(IFERROR( INDEX( CHOOSE( MATCH(E34, practices, 0), altcostAps, altcostData, altcostSec, altcostAdv, altcostProd, altcostPvtCld, altcostSdaia, altcostErp ), MATCH($G34,INDIRECT( "roles_"&MATCH(E34, practices, 0)), 0), MATCH($F34, countries, 0)) * INDEX(fx, MATCH($F$6, currency, 0)) * IF($F$7 = "Days", 8, 1), 0 ), 0) -> 0 | U34: =IF(AND(OR(T34=0,T34=""),tb_resource[[#This Row],[Flag if role is not planned]]=1),"This resource is not planned for this region. Check with PS delivery",IF(tb_resource[[#This Row],[Flag if role is not planned]]=1,"This resource is not available. Use cost = " & tb_resource[[#This Row],[cost of unavailable]] & " in the Table B below and check with PS delivery team",IFERROR("role also mapped to " & INDEX(Other_roles[Roles],MATCH(Calculator!$G34,Other_roles[mapped to],0)),"")))
B35: =IFERROR( INDEX( CHOOSE( MATCH(E35, practices, 0), costAps, costData, costSec, costAdv, costProd, costPvtCld, costSdaia, costErp, costHealth ), MATCH($G35,INDIRECT( "roles_"&MATCH(E35, practices, 0)), 0), MATCH($F35, countries, 0)) * INDEX(fx, MATCH($F$6, currency, 0)) * IF($F$7 = "Days", 8, 1), "" ) | C35: =IF(AND( tb_resource[[#This Row],[Practice Area]]<>0,OR(R35=0,R35="")),1,0) -> 0 | D35: =IF(E35="","",D34+1) | I35: =IFERROR(ROUNDUP(IF(J35="List Price",S35*IF($F$9="Master",1.1,IF($F$9="Sub-agent",1.05,1))*IF($F$3="Fixed Price",1.1,1),IF(K35<1,B35/(1-K35),K35)),0),"") | J35: List Price | K35: 0.5 | L35: =IF(S35="","",H35*I35) | M35: =B35 | N35: =IFERROR(1-B35/I35,"") | O35: =IFERROR(tb_resource[[#This Row],[Price/hr]]*(1-$I$9),"") | P35: =IF(Calculator!$C35=-1,"No resource in region, please work with delivery and finance to get approvals for using this rate",IF(Calculator!$C35=1,"No resource in region or planned in future. Please get special approval from Finance and HR","")) | R35: =IFERROR( INDEX( CHOOSE( MATCH(E35, practices, 0), countAps, countData, countSec, countAdv, countProd, CountPvtCld, countSdaia, countErp, CountHealth ), MATCH($G35, INDIRECT( "roles_"&MATCH(E35, practices, 0)), 0), MATCH($F35, countries, 0)), "" ) | S35: =IFERROR( INDEX( CHOOSE( MATCH(E35, practices, 0), priceAps, priceData, priceSec, priceAdv, priceProd, pricePvtCld, priceSdaia, priceErp, priceHealth ), MATCH($G35,INDIRECT( "roles_"&MATCH(E35, practices, 0)), 0), MATCH($F35, countries, 0)) * INDEX(fx, MATCH($F$6, currency, 0)) * IF($F$7 = "Days", 8, 1), "" ) | T35: =ROUNDUP(IFERROR( INDEX( CHOOSE( MATCH(E35, practices, 0), altcostAps, altcostData, altcostSec, altcostAdv, altcostProd, altcostPvtCld, altcostSdaia, altcostErp ), MATCH($G35,INDIRECT( "roles_"&MATCH(E35, practices, 0)), 0), MATCH($F35, countries, 0)) * INDEX(fx, MATCH($F$6, currency, 0)) * IF($F$7 = "Days", 8, 1), 0 ), 0) -> 0 | U35: =IF(AND(OR(T35=0,T35=""),tb_resource[[#This Row],[Flag if role is not planned]]=1),"This resource is not planned for this region. Check with PS delivery",IF(tb_resource[[#This Row],[Flag if role is not planned]]=1,"This resource is not available. Use cost = " & tb_resource[[#This Row],[cost of unavailable]] & " in the Table B below and check with PS delivery team",IFERROR("role also mapped to " & INDEX(Other_roles[Roles],MATCH(Calculator!$G35,Other_roles[mapped to],0)),"")))
B36: =IFERROR( INDEX( CHOOSE( MATCH(E36, practices, 0), costAps, costData, costSec, costAdv, costProd, costPvtCld, costSdaia, costErp, costHealth ), MATCH($G36,INDIRECT( "roles_"&MATCH(E36, practices, 0)), 0), MATCH($F36, countries, 0)) * INDEX(fx, MATCH($F$6, currency, 0)) * IF($F$7 = "Days", 8, 1), "" ) | C36: =IF(AND( tb_resource[[#This Row],[Practice Area]]<>0,OR(R36=0,R36="")),1,0) -> 0 | D36: =IF(E36="","",D35+1) | I36: =IFERROR(ROUNDUP(IF(J36="List Price",S36*IF($F$9="Master",1.1,IF($F$9="Sub-agent",1.05,1))*IF($F$3="Fixed Price",1.1,1),IF(K36<1,B36/(1-K36),K36)),0),"") | J36: List Price | K36: 0.5 | L36: =IF(S36="","",H36*I36) | M36: =B36 | N36: =IFERROR(1-B36/I36,"") | O36: =IFERROR(tb_resource[[#This Row],[Price/hr]]*(1-$I$9),"") | P36: =IF(Calculator!$C36=-1,"No resource in region, please work with delivery and finance to get approvals for using this rate",IF(Calculator!$C36=1,"No resource in region or planned in future. Please get special approval from Finance and HR","")) | R36: =IFERROR( INDEX( CHOOSE( MATCH(E36, practices, 0), countAps, countData, countSec, countAdv, countProd, CountPvtCld, countSdaia, countErp, CountHealth ), MATCH($G36, INDIRECT( "roles_"&MATCH(E36, practices, 0)), 0), MATCH($F36, countries, 0)), "" ) | S36: =IFERROR( INDEX( CHOOSE( MATCH(E36, practices, 0), priceAps, priceData, priceSec, priceAdv, priceProd, pricePvtCld, priceSdaia, priceErp, priceHealth ), MATCH($G36,INDIRECT( "roles_"&MATCH(E36, practices, 0)), 0), MATCH($F36, countries, 0)) * INDEX(fx, MATCH($F$6, currency, 0)) * IF($F$7 = "Days", 8, 1), "" ) | T36: =ROUNDUP(IFERROR( INDEX( CHOOSE( MATCH(E36, practices, 0), altcostAps, altcostData, altcostSec, altcostAdv, altcostProd, altcostPvtCld, altcostSdaia, altcostErp ), MATCH($G36,INDIRECT( "roles_"&MATCH(E36, practices, 0)), 0), MATCH($F36, countries, 0)) * INDEX(fx, MATCH($F$6, currency, 0)) * IF($F$7 = "Days", 8, 1), 0 ), 0) -> 0 | U36: =IF(AND(OR(T36=0,T36=""),tb_resource[[#This Row],[Flag if role is not planned]]=1),"This resource is not planned for this region. Check with PS delivery",IF(tb_resource[[#This Row],[Flag if role is not planned]]=1,"This resource is not available. Use cost = " & tb_resource[[#This Row],[cost of unavailable]] & " in the Table B below and check with PS delivery team",IFERROR("role also mapped to " & INDEX(Other_roles[Roles],MATCH(Calculator!$G36,Other_roles[mapped to],0)),"")))
B37: =IFERROR( INDEX( CHOOSE( MATCH(E37, practices, 0), costAps, costData, costSec, costAdv, costProd, costPvtCld, costSdaia, costErp, costHealth ), MATCH($G37,INDIRECT( "roles_"&MATCH(E37, practices, 0)), 0), MATCH($F37, countries, 0)) * INDEX(fx, MATCH($F$6, currency, 0)) * IF($F$7 = "Days", 8, 1), "" ) | C37: =IF(AND( tb_resource[[#This Row],[Practice Area]]<>0,OR(R37=0,R37="")),1,0) -> 0 | D37: =IF(E37="","",D36+1) | I37: =IFERROR(ROUNDUP(IF(J37="List Price",S37*IF($F$9="Master",1.1,IF($F$9="Sub-agent",1.05,1))*IF($F$3="Fixed Price",1.1,1),IF(K37<1,B37/(1-K37),K37)),0),"") | J37: List Price | K37: 0.5 | L37: =IF(S37="","",H37*I37) | M37: =B37 | N37: =IFERROR(1-B37/I37,"") | O37: =IFERROR(tb_resource[[#This Row],[Price/hr]]*(1-$I$9),"") | P37: =IF(Calculator!$C37=-1,"No resource in region, please work with delivery and finance to get approvals for using this rate",IF(Calculator!$C37=1,"No resource in region or planned in future. Please get special approval from Finance and HR","")) | R37: =IFERROR( INDEX( CHOOSE( MATCH(E37, practices, 0), countAps, countData, countSec, countAdv, countProd, CountPvtCld, countSdaia, countErp, CountHealth ), MATCH($G37, INDIRECT( "roles_"&MATCH(E37, practices, 0)), 0), MATCH($F37, countries, 0)), "" ) | S37: =IFERROR( INDEX( CHOOSE( MATCH(E37, practices, 0), priceAps, priceData, priceSec, priceAdv, priceProd, pricePvtCld, priceSdaia, priceErp, priceHealth ), MATCH($G37,INDIRECT( "roles_"&MATCH(E37, practices, 0)), 0), MATCH($F37, countries, 0)) * INDEX(fx, MATCH($F$6, currency, 0)) * IF($F$7 = "Days", 8, 1), "" ) | T37: =ROUNDUP(IFERROR( INDEX( CHOOSE( MATCH(E37, practices, 0), altcostAps, altcostData, altcostSec, altcostAdv, altcostProd, altcostPvtCld, altcostSdaia, altcostErp ), MATCH($G37,INDIRECT( "roles_"&MATCH(E37, practices, 0)), 0), MATCH($F37, countries, 0)) * INDEX(fx, MATCH($F$6, currency, 0)) * IF($F$7 = "Days", 8, 1), 0 ), 0) -> 0 | U37: =IF(AND(OR(T37=0,T37=""),tb_resource[[#This Row],[Flag if role is not planned]]=1),"This resource is not planned for this region. Check with PS delivery",IF(tb_resource[[#This Row],[Flag if role is not planned]]=1,"This resource is not available. Use cost = " & tb_resource[[#This Row],[cost of unavailable]] & " in the Table B below and check with PS delivery team",IFERROR("role also mapped to " & INDEX(Other_roles[Roles],MATCH(Calculator!$G37,Other_roles[mapped to],0)),"")))
B38: =IFERROR( INDEX( CHOOSE( MATCH(E38, practices, 0), costAps, costData, costSec, costAdv, costProd, costPvtCld, costSdaia, costErp, costHealth ), MATCH($G38,INDIRECT( "roles_"&MATCH(E38, practices, 0)), 0), MATCH($F38, countries, 0)) * INDEX(fx, MATCH($F$6, currency, 0)) * IF($F$7 = "Days", 8, 1), "" ) | C38: =IF(AND( tb_resource[[#This Row],[Practice Area]]<>0,OR(R38=0,R38="")),1,0) -> 0 | D38: =IF(E38="","",D37+1) | I38: =IFERROR(ROUNDUP(IF(J38="List Price",S38*IF($F$9="Master",1.1,IF($F$9="Sub-agent",1.05,1))*IF($F$3="Fixed Price",1.1,1),IF(K38<1,B38/(1-K38),K38)),0),"") | J38: List Price | K38: 0.5 | L38: =IF(S38="","",H38*I38) | M38: =B38 | N38: =IFERROR(1-B38/I38,"") | O38: =IFERROR(tb_resource[[#This Row],[Price/hr]]*(1-$I$9),"") | P38: =IF(Calculator!$C38=-1,"No resource in region, please work with delivery and finance to get approvals for using this rate",IF(Calculator!$C38=1,"No resource in region or planned in future. Please get special approval from Finance and HR","")) | R38: =IFERROR( INDEX( CHOOSE( MATCH(E38, practices, 0), countAps, countData, countSec, countAdv, countProd, CountPvtCld, countSdaia, countErp, CountHealth ), MATCH($G38, INDIRECT( "roles_"&MATCH(E38, practices, 0)), 0), MATCH($F38, countries, 0)), "" ) | S38: =IFERROR( INDEX( CHOOSE( MATCH(E38, practices, 0), priceAps, priceData, priceSec, priceAdv, priceProd, pricePvtCld, priceSdaia, priceErp, priceHealth ), MATCH($G38,INDIRECT( "roles_"&MATCH(E38, practices, 0)), 0), MATCH($F38, countries, 0)) * INDEX(fx, MATCH($F$6, currency, 0)) * IF($F$7 = "Days", 8, 1), "" ) | T38: =ROUNDUP(IFERROR( INDEX( CHOOSE( MATCH(E38, practices, 0), altcostAps, altcostData, altcostSec, altcostAdv, altcostProd, altcostPvtCld, altcostSdaia, altcostErp ), MATCH($G38,INDIRECT( "roles_"&MATCH(E38, practices, 0)), 0), MATCH($F38, countries, 0)) * INDEX(fx, MATCH($F$6, currency, 0)) * IF($F$7 = "Days", 8, 1), 0 ), 0) -> 0 | U38: =IF(AND(OR(T38=0,T38=""),tb_resource[[#This Row],[Flag if role is not planned]]=1),"This resource is not planned for this region. Check with PS delivery",IF(tb_resource[[#This Row],[Flag if role is not planned]]=1,"This resource is not available. Use cost = " & tb_resource[[#This Row],[cost of unavailable]] & " in the Table B below and check with PS delivery team",IFERROR("role also mapped to " & INDEX(Other_roles[Roles],MATCH(Calculator!$G38,Other_roles[mapped to],0)),"")))
B39: =IFERROR( INDEX( CHOOSE( MATCH(E39, practices, 0), costAps, costData, costSec, costAdv, costProd, costPvtCld, costSdaia, costErp, costHealth ), MATCH($G39,INDIRECT( "roles_"&MATCH(E39, practices, 0)), 0), MATCH($F39, countries, 0)) * INDEX(fx, MATCH($F$6, currency, 0)) * IF($F$7 = "Days", 8, 1), "" ) | C39: =IF(AND( tb_resource[[#This Row],[Practice Area]]<>0,OR(R39=0,R39="")),1,0) -> 0 | D39: =IF(E39="","",D38+1) | I39: =IFERROR(ROUNDUP(IF(J39="List Price",S39*IF($F$9="Master",1.1,IF($F$9="Sub-agent",1.05,1))*IF($F$3="Fixed Price",1.1,1),IF(K39<1,B39/(1-K39),K39)),0),"") | J39: List Price | K39: 0.5 | L39: =IF(S39="","",H39*I39) | M39: =B39 | N39: =IFERROR(1-B39/I39,"") | O39: =IFERROR(tb_resource[[#This Row],[Price/hr]]*(1-$I$9),"") | P39: =IF(Calculator!$C39=-1,"No resource in region, please work with delivery and finance to get approvals for using this rate",IF(Calculator!$C39=1,"No resource in region or planned in future. Please get special approval from Finance and HR","")) | R39: =IFERROR( INDEX( CHOOSE( MATCH(E39, practices, 0), countAps, countData, countSec, countAdv, countProd, CountPvtCld, countSdaia, countErp, CountHealth ), MATCH($G39, INDIRECT( "roles_"&MATCH(E39, practices, 0)), 0), MATCH($F39, countries, 0)), "" ) | S39: =IFERROR( INDEX( CHOOSE( MATCH(E39, practices, 0), priceAps, priceData, priceSec, priceAdv, priceProd, pricePvtCld, priceSdaia, priceErp, priceHealth ), MATCH($G39,INDIRECT( "roles_"&MATCH(E39, practices, 0)), 0), MATCH($F39, countries, 0)) * INDEX(fx, MATCH($F$6, currency, 0)) * IF($F$7 = "Days", 8, 1), "" ) | T39: =ROUNDUP(IFERROR( INDEX( CHOOSE( MATCH(E39, practices, 0), altcostAps, altcostData, altcostSec, altcostAdv, altcostProd, altcostPvtCld, altcostSdaia, altcostErp ), MATCH($G39,INDIRECT( "roles_"&MATCH(E39, practices, 0)), 0), MATCH($F39, countries, 0)) * INDEX(fx, MATCH($F$6, currency, 0)) * IF($F$7 = "Days", 8, 1), 0 ), 0) -> 0 | U39: =IF(AND(OR(T39=0,T39=""),tb_resource[[#This Row],[Flag if role is not planned]]=1),"This resource is not planned for this region. Check with PS delivery",IF(tb_resource[[#This Row],[Flag if role is not planned]]=1,"This resource is not available. Use cost = " & tb_resource[[#This Row],[cost of unavailable]] & " in the Table B below and check with PS delivery team",IFERROR("role also mapped to " & INDEX(Other_roles[Roles],MATCH(Calculator!$G39,Other_roles[mapped to],0)),"")))
B40: =IFERROR( INDEX( CHOOSE( MATCH(E40, practices, 0), costAps, costData, costSec, costAdv, costProd, costPvtCld, costSdaia, costErp, costHealth ), MATCH($G40,INDIRECT( "roles_"&MATCH(E40, practices, 0)), 0), MATCH($F40, countries, 0)) * INDEX(fx, MATCH($F$6, currency, 0)) * IF($F$7 = "Days", 8, 1), "" ) | C40: =IF(AND( tb_resource[[#This Row],[Practice Area]]<>0,OR(R40=0,R40="")),1,0) -> 0 | D40: =IF(E40="","",D39+1) | I40: =IFERROR(ROUNDUP(IF(J40="List Price",S40*IF($F$9="Master",1.1,IF($F$9="Sub-agent",1.05,1))*IF($F$3="Fixed Price",1.1,1),IF(K40<1,B40/(1-K40),K40)),0),"") | J40: List Price | K40: 0.5 | L40: =IF(S40="","",H40*I40) | M40: =B40 | N40: =IFERROR(1-B40/I40,"") | O40: =IFERROR(tb_resource[[#This Row],[Price/hr]]*(1-$I$9),"") | P40: =IF(Calculator!$C40=-1,"No resource in region, please work with delivery and finance to get approvals for using this rate",IF(Calculator!$C40=1,"No resource in region or planned in future. Please get special approval from Finance and HR","")) | R40: =IFERROR( INDEX( CHOOSE( MATCH(E40, practices, 0), countAps, countData, countSec, countAdv, countProd, CountPvtCld, countSdaia, countErp, CountHealth ), MATCH($G40, INDIRECT( "roles_"&MATCH(E40, practices, 0)), 0), MATCH($F40, countries, 0)), "" ) | S40: =IFERROR( INDEX( CHOOSE( MATCH(E40, practices, 0), priceAps, priceData, priceSec, priceAdv, priceProd, pricePvtCld, priceSdaia, priceErp, priceHealth ), MATCH($G40,INDIRECT( "roles_"&MATCH(E40, practices, 0)), 0), MATCH($F40, countries, 0)) * INDEX(fx, MATCH($F$6, currency, 0)) * IF($F$7 = "Days", 8, 1), "" ) | T40: =ROUNDUP(IFERROR( INDEX( CHOOSE( MATCH(E40, practices, 0), altcostAps, altcostData, altcostSec, altcostAdv, altcostProd, altcostPvtCld, altcostSdaia, altcostErp ), MATCH($G40,INDIRECT( "roles_"&MATCH(E40, practices, 0)), 0), MATCH($F40, countries, 0)) * INDEX(fx, MATCH($F$6, currency, 0)) * IF($F$7 = "Days", 8, 1), 0 ), 0) -> 0 | U40: =IF(AND(OR(T40=0,T40=""),tb_resource[[#This Row],[Flag if role is not planned]]=1),"This resource is not planned for this region. Check with PS delivery",IF(tb_resource[[#This Row],[Flag if role is not planned]]=1,"This resource is not available. Use cost = " & tb_resource[[#This Row],[cost of unavailable]] & " in the Table B below and check with PS delivery team",IFERROR("role also mapped to " & INDEX(Other_roles[Roles],MATCH(Calculator!$G40,Other_roles[mapped to],0)),"")))
B41: =IFERROR( INDEX( CHOOSE( MATCH(E41, practices, 0), costAps, costData, costSec, costAdv, costProd, costPvtCld, costSdaia, costErp, costHealth ), MATCH($G41,INDIRECT( "roles_"&MATCH(E41, practices, 0)), 0), MATCH($F41, countries, 0)) * INDEX(fx, MATCH($F$6, currency, 0)) * IF($F$7 = "Days", 8, 1), "" ) | C41: =IF(AND( tb_resource[[#This Row],[Practice Area]]<>0,OR(R41=0,R41="")),1,0) -> 0 | D41: =IF(E41="","",D40+1) | I41: =IFERROR(ROUNDUP(IF(J41="List Price",S41*IF($F$9="Master",1.1,IF($F$9="Sub-agent",1.05,1))*IF($F$3="Fixed Price",1.1,1),IF(K41<1,B41/(1-K41),K41)),0),"") | J41: List Price | K41: 0.5 | L41: =IF(S41="","",H41*I41) | M41: =B41 | N41: =IFERROR(1-B41/I41,"") | O41: =IFERROR(tb_resource[[#This Row],[Price/hr]]*(1-$I$9),"") | P41: =IF(Calculator!$C41=-1,"No resource in region, please work with delivery and finance to get approvals for using this rate",IF(Calculator!$C41=1,"No resource in region or planned in future. Please get special approval from Finance and HR","")) | R41: =IFERROR( INDEX( CHOOSE( MATCH(E41, practices, 0), countAps, countData, countSec, countAdv, countProd, CountPvtCld, countSdaia, countErp, CountHealth ), MATCH($G41, INDIRECT( "roles_"&MATCH(E41, practices, 0)), 0), MATCH($F41, countries, 0)), "" ) | S41: =IFERROR( INDEX( CHOOSE( MATCH(E41, practices, 0), priceAps, priceData, priceSec, priceAdv, priceProd, pricePvtCld, priceSdaia, priceErp, priceHealth ), MATCH($G41,INDIRECT( "roles_"&MATCH(E41, practices, 0)), 0), MATCH($F41, countries, 0)) * INDEX(fx, MATCH($F$6, currency, 0)) * IF($F$7 = "Days", 8, 1), "" ) | T41: =ROUNDUP(IFERROR( INDEX( CHOOSE( MATCH(E41, practices, 0), altcostAps, altcostData, altcostSec, altcostAdv, altcostProd, altcostPvtCld, altcostSdaia, altcostErp ), MATCH($G41,INDIRECT( "roles_"&MATCH(E41, practices, 0)), 0), MATCH($F41, countries, 0)) * INDEX(fx, MATCH($F$6, currency, 0)) * IF($F$7 = "Days", 8, 1), 0 ), 0) -> 0 | U41: =IF(AND(OR(T41=0,T41=""),tb_resource[[#This Row],[Flag if role is not planned]]=1),"This resource is not planned for this region. Check with PS delivery",IF(tb_resource[[#This Row],[Flag if role is not planned]]=1,"This resource is not available. Use cost = " & tb_resource[[#This Row],[cost of unavailable]] & " in the Table B below and check with PS delivery team",IFERROR("role also mapped to " & INDEX(Other_roles[Roles],MATCH(Calculator!$G41,Other_roles[mapped to],0)),"")))
... B43: =IFERROR( INDEX( CHOOSE( MATCH(E43, practices, 0), costAps, costData, costSec, costAdv, costProd, costPvtCld, costSdaia, costErp, costHealth ), MATCH($G43,INDIRECT( "roles_"&MATCH(E43, practices, 0)), 0), MATCH($F43, countries, 0)) * INDEX(fx, MATCH($F$6, currency, 0)) * IF($F$7 = "Days", 8, 1), "" ) | C43: =IF(AND( tb_resource[[#This Row],[Practice Area]]<>0,OR(R43=0,R43="")),1,0) -> 0 | D43: =IF(E43="","",D42+1) | I43: =IFERROR(ROUNDUP(IF(J43="List Price",S43*IF($F$9="Master",1.1,IF($F$9="Sub-agent",1.05,1))*IF($F$3="Fixed Price",1.1,1),IF(K43<1,B43/(1-K43),K43)),0),"") | J43: List Price | K43: 0.5 | L43: =IF(S43="","",H43*I43) | M43: =B43 | N43: =IFERROR(1-B43/I43,"") | O43: =IFERROR(tb_resource[[#This Row],[Price/hr]]*(1-$I$9),"") | P43: =IF(Calculator!$C43=-1,"No resource in region, please work with delivery and finance to get approvals for using this rate",IF(Calculator!$C43=1,"No resource in region or planned in future. Please get special approval from Finance and HR","")) | R43: =IFERROR( INDEX( CHOOSE( MATCH(E43, practices, 0), countAps, countData, countSec, countAdv, countProd, CountPvtCld, countSdaia, countErp, CountHealth ), MATCH($G43, INDIRECT( "roles_"&MATCH(E43, practices, 0)), 0), MATCH($F43, countries, 0)), "" ) | S43: =IFERROR( INDEX( CHOOSE( MATCH(E43, practices, 0), priceAps, priceData, priceSec, priceAdv, priceProd, pricePvtCld, priceSdaia, priceErp, priceHealth ), MATCH($G43,INDIRECT( "roles_"&MATCH(E43, practices, 0)), 0), MATCH($F43, countries, 0)) * INDEX(fx, MATCH($F$6, currency, 0)) * IF($F$7 = "Days", 8, 1), "" ) | T43: =ROUNDUP(IFERROR( INDEX( CHOOSE( MATCH(E43, practices, 0), altcostAps, altcostData, altcostSec, altcostAdv, altcostProd, altcostPvtCld, altcostSdaia, altcostErp ), MATCH($G43,INDIRECT( "roles_"&MATCH(E43, practices, 0)), 0), MATCH($F43, countries, 0)) * INDEX(fx, MATCH($F$6, currency, 0)) * IF($F$7 = "Days", 8, 1), 0 ), 0) -> 0 | U43: =IF(AND(OR(T43=0,T43=""),tb_resource[[#This Row],[Flag if role is not planned]]=1),"This resource is not planned for this region. Check with PS delivery",IF(tb_resource[[#This Row],[Flag if role is not planned]]=1,"This resource is not available. Use cost = " & tb_resource[[#This Row],[cost of unavailable]] & " in the Table B below and check with PS delivery team",IFERROR("role also mapped to " & INDEX(Other_roles[Roles],MATCH(Calculator!$G43,Other_roles[mapped to],0)),"")))
D49: Table B | E49: Make sure you choose 'Yes' as the option if you are using "3rd party contractor" in cell F5
D50: Item | E50: External or Internal Cost | F50: Type of cost (i.e. license or resources) | G50: Add details or comments | H50: Cost (per unit/ per hr/per day rate) to Rackspace | I50: Qty (In same as cost units) | J50: Enter required margin or Price | K50: Price per unit | L50: Extended Price | M50: Add contingency
D51: 1 | E51: External | H51: 3500 | I51: 1 | J51: 0.35 | K51: =tb_supplier[[#This Row],[Cost (per unit/ per hr/per day rate) to Rackspace]]*(1+tb_supplier[[#This Row],[Add contingency]])/(1-tb_supplier[[#This Row],[Enter required margin or Price]]) -> 5384.6154 | L51: =IF(tb_supplier[[#This Row],[Enter required margin or Price]]<1,tb_supplier[[#This Row],[Cost (per unit/ per hr/per day rate) to Rackspace]]*(1+tb_supplier[[#This Row],[Add contingency]])*tb_supplier[[#This Row],[Qty (In same as cost units)]]/(1-tb_supplier[[#This Row],[Enter required margin or Price]]),tb_supplier[[#This Row],[Enter required margin or Price]]) -> 5384.6154 | M51: 0
K52: =tb_supplier[[#This Row],[Cost (per unit/ per hr/per day rate) to Rackspace]]*(1+tb_supplier[[#This Row],[Add contingency]])/(1-tb_supplier[[#This Row],[Enter required margin or Price]]) -> 0 | L52: =IF(tb_supplier[[#This Row],[Enter required margin or Price]]<1,tb_supplier[[#This Row],[Cost (per unit/ per hr/per day rate) to Rackspace]]*(1+tb_supplier[[#This Row],[Add contingency]])*tb_supplier[[#This Row],[Qty (In same as cost units)]]/(1-tb_supplier[[#This Row],[Enter required margin or Price]]),tb_supplier[[#This Row],[Enter required margin or Price]]) -> 0 | M52: 0 | O52: d
K53: =tb_supplier[[#This Row],[Cost (per unit/ per hr/per day rate) to Rackspace]]*(1+tb_supplier[[#This Row],[Add contingency]])/(1-tb_supplier[[#This Row],[Enter required margin or Price]]) -> 0 | L53: =IF(tb_supplier[[#This Row],[Enter required margin or Price]]<1,tb_supplier[[#This Row],[Cost (per unit/ per hr/per day rate) to Rackspace]]*(1+tb_supplier[[#This Row],[Add contingency]])*tb_supplier[[#This Row],[Qty (In same as cost units)]]/(1-tb_supplier[[#This Row],[Enter required margin or Price]]),tb_supplier[[#This Row],[Enter required margin or Price]]) -> 0
K54: =tb_supplier[[#This Row],[Cost (per unit/ per hr/per day rate) to Rackspace]]*(1+tb_supplier[[#This Row],[Add contingency]])/(1-tb_supplier[[#This Row],[Enter required margin or Price]]) -> 0 | L54: =IF(tb_supplier[[#This Row],[Enter required margin or Price]]<1,tb_supplier[[#This Row],[Cost (per unit/ per hr/per day rate) to Rackspace]]*(1+tb_supplier[[#This Row],[Add contingency]])*tb_supplier[[#This Row],[Qty (In same as cost units)]]/(1-tb_supplier[[#This Row],[Enter required margin or Price]]),tb_supplier[[#This Row],[Enter required margin or Price]]) -> 0
K55: =tb_supplier[[#This Row],[Cost (per unit/ per hr/per day rate) to Rackspace]]*(1+tb_supplier[[#This Row],[Add contingency]])/(1-tb_supplier[[#This Row],[Enter required margin or Price]]) -> 0 | L55: =IF(tb_supplier[[#This Row],[Enter required margin or Price]]<1,tb_supplier[[#This Row],[Cost (per unit/ per hr/per day rate) to Rackspace]]*(1+tb_supplier[[#This Row],[Add contingency]])*tb_supplier[[#This Row],[Qty (In same as cost units)]]/(1-tb_supplier[[#This Row],[Enter required margin or Price]]),tb_supplier[[#This Row],[Enter required margin or Price]]) -> 0
K56: =tb_supplier[[#This Row],[Cost (per unit/ per hr/per day rate) to Rackspace]]*(1+tb_supplier[[#This Row],[Add contingency]])/(1-tb_supplier[[#This Row],[Enter required margin or Price]]) -> 0 | L56: =IF(tb_supplier[[#This Row],[Enter required margin or Price]]<1,tb_supplier[[#This Row],[Cost (per unit/ per hr/per day rate) to Rackspace]]*(1+tb_supplier[[#This Row],[Add contingency]])*tb_supplier[[#This Row],[Qty (In same as cost units)]]/(1-tb_supplier[[#This Row],[Enter required margin or Price]]),tb_supplier[[#This Row],[Enter required margin or Price]]) -> 0
K57: =tb_supplier[[#This Row],[Cost (per unit/ per hr/per day rate) to Rackspace]]*(1+tb_supplier[[#This Row],[Add contingency]])/(1-tb_supplier[[#This Row],[Enter required margin or Price]]) -> 0 | L57: =IF(tb_supplier[[#This Row],[Enter required margin or Price]]<1,tb_supplier[[#This Row],[Cost (per unit/ per hr/per day rate) to Rackspace]]*(1+tb_supplier[[#This Row],[Add contingency]])*tb_supplier[[#This Row],[Qty (In same as cost units)]]/(1-tb_supplier[[#This Row],[Enter required margin or Price]]),tb_supplier[[#This Row],[Enter required margin or Price]]) -> 0
K58: =tb_supplier[[#This Row],[Cost (per unit/ per hr/per day rate) to Rackspace]]*(1+tb_supplier[[#This Row],[Add contingency]])/(1-tb_supplier[[#This Row],[Enter required margin or Price]]) -> 0 | L58: =IF(tb_supplier[[#This Row],[Enter required margin or Price]]<1,tb_supplier[[#This Row],[Cost (per unit/ per hr/per day rate) to Rackspace]]*(1+tb_supplier[[#This Row],[Add contingency]])*tb_supplier[[#This Row],[Qty (In same as cost units)]]/(1-tb_supplier[[#This Row],[Enter required margin or Price]]),tb_supplier[[#This Row],[Enter required margin or Price]]) -> 0
K59: =tb_supplier[[#This Row],[Cost (per unit/ per hr/per day rate) to Rackspace]]*(1+tb_supplier[[#This Row],[Add contingency]])/(1-tb_supplier[[#This Row],[Enter required margin or Price]]) -> 0 | L59: =IF(tb_supplier[[#This Row],[Enter required margin or Price]]<1,tb_supplier[[#This Row],[Cost (per unit/ per hr/per day rate) to Rackspace]]*(1+tb_supplier[[#This Row],[Add contingency]])*tb_supplier[[#This Row],[Qty (In same as cost units)]]/(1-tb_supplier[[#This Row],[Enter required margin or Price]]),tb_supplier[[#This Row],[Enter required margin or Price]]) -> 0
K60: =tb_supplier[[#This Row],[Cost (per unit/ per hr/per day rate) to Rackspace]]*(1+tb_supplier[[#This Row],[Add contingency]])/(1-tb_supplier[[#This Row],[Enter required margin or Price]]) -> 0 | L60: =IF(tb_supplier[[#This Row],[Enter required margin or Price]]<1,tb_supplier[[#This Row],[Cost (per unit/ per hr/per day rate) to Rackspace]]*(1+tb_supplier[[#This Row],[Add contingency]])*tb_supplier[[#This Row],[Qty (In same as cost units)]]/(1-tb_supplier[[#This Row],[Enter required margin or Price]]),tb_supplier[[#This Row],[Enter required margin or Price]]) -> 0
K61: =tb_supplier[[#This Row],[Cost (per unit/ per hr/per day rate) to Rackspace]]*(1+tb_supplier[[#This Row],[Add contingency]])/(1-tb_supplier[[#This Row],[Enter required margin or Price]]) -> 0 | L61: =IF(tb_supplier[[#This Row],[Enter required margin or Price]]<1,tb_supplier[[#This Row],[Cost (per unit/ per hr/per day rate) to Rackspace]]*(1+tb_supplier[[#This Row],[Add contingency]])*tb_supplier[[#This Row],[Qty (In same as cost units)]]/(1-tb_supplier[[#This Row],[Enter required margin or Price]]),tb_supplier[[#This Row],[Enter required margin or Price]]) -> 0
K62: =tb_supplier[[#This Row],[Cost (per unit/ per hr/per day rate) to Rackspace]]*(1+tb_supplier[[#This Row],[Add contingency]])/(1-tb_supplier[[#This Row],[Enter required margin or Price]]) -> 0 | L62: =IF(tb_supplier[[#This Row],[Enter required margin or Price]]<1,tb_supplier[[#This Row],[Cost (per unit/ per hr/per day rate) to Rackspace]]*(1+tb_supplier[[#This Row],[Add contingency]])*tb_supplier[[#This Row],[Qty (In same as cost units)]]/(1-tb_supplier[[#This Row],[Enter required margin or Price]]),tb_supplier[[#This Row],[Enter required margin or Price]]) -> 0
K63: =tb_supplier[[#This Row],[Cost (per unit/ per hr/per day rate) to Rackspace]]*(1+tb_supplier[[#This Row],[Add contingency]])/(1-tb_supplier[[#This Row],[Enter required margin or Price]]) -> 0 | L63: =IF(tb_supplier[[#This Row],[Enter required margin or Price]]<1,tb_supplier[[#This Row],[Cost (per unit/ per hr/per day rate) to Rackspace]]*(1+tb_supplier[[#This Row],[Add contingency]])*tb_supplier[[#This Row],[Qty (In same as cost units)]]/(1-tb_supplier[[#This Row],[Enter required margin or Price]]),tb_supplier[[#This Row],[Enter required margin or Price]]) -> 0
K64: =tb_supplier[[#This Row],[Cost (per unit/ per hr/per day rate) to Rackspace]]*(1+tb_supplier[[#This Row],[Add contingency]])/(1-tb_supplier[[#This Row],[Enter required margin or Price]]) -> 0 | L64: =IF(tb_supplier[[#This Row],[Enter required margin or Price]]<1,tb_supplier[[#This Row],[Cost (per unit/ per hr/per day rate) to Rackspace]]*(1+tb_supplier[[#This Row],[Add contingency]])*tb_supplier[[#This Row],[Qty (In same as cost units)]]/(1-tb_supplier[[#This Row],[Enter required margin or Price]]),tb_supplier[[#This Row],[Enter required margin or Price]]) -> 0
... K72: =tb_supplier[[#This Row],[Cost (per unit/ per hr/per day rate) to Rackspace]]*(1+tb_supplier[[#This Row],[Add contingency]])/(1-tb_supplier[[#This Row],[Enter required margin or Price]]) -> 0 | L72: =IF(tb_supplier[[#This Row],[Enter required margin or Price]]<1,tb_supplier[[#This Row],[Cost (per unit/ per hr/per day rate) to Rackspace]]*(1+tb_supplier[[#This Row],[Add contingency]])*tb_supplier[[#This Row],[Qty (In same as cost units)]]/(1-tb_supplier[[#This Row],[Enter required margin or Price]]),tb_supplier[[#This Row],[Enter required margin or Price]]) -> 0

Sheet LOE
C3: W01 | D3: W02 | E3: W03 | F3: W04 | G3: W05 | H3: W06 | I3: W07 | J3: W08 | K3: W09 | L3: W10 | M3: W11
A4: Project kickoff and planning
A5: Kickoff internal meeting to align on goals and finalize delivery resources
A6: Identify key stakeholders/contributors
A7: Create project plan with activities and milestones
A8: Conduct kickoff meeting with stakeholders and external team
A9: Get access to environments & Documentation
A10: Strategy Assessment
A11: Conduct workshop with stakeholers & document business drivers, plans, roadmaps
A12: Finalise Hyper-scaler selection criteria with project team from DMG Media
A13: Document maturity, team readiness, migration assumptions
A14: Analyse data & report
A15: Automated Infrastructure Discovery
... A37: Conduct project-close out meeting
C38: Kickoff Workshops Tool Deploy | D38: Workshops Tool Deploy | E38: Workshops Tool Deploy | F38: Workshops Tool Deploy | G38: Workshops Tool Deploy | H38: Discovery CSP Selection | I38: Discovery CSP Selection | J38: TCO Review Assess Report | K38: TCO Review Assess Report | L38: Report Present Close | M38: Report Present Close
A39: Role & Hours | B39: # Resrcs | C39: W01 | D39: W02 | E39: W03 | F39: W04 | G39: W05 | H39: W06 | I39: W07 | J39: W08 | K39: W09 | L39: W10 | M39: W11 | N39: Total
A40: Sr. Project Manager (UK) | B40: 1 | C40: 5 | D40: 5 | E40: 5 | F40: 5 | G40: 2.5 | H40: 2.5 | I40: 2.5 | J40: 2.5 | K40: 2.5 | L40: 2.5 | M40: 2.5 | N40: =SUM(C40:M40) -> 37.5
A41: Lead Consulting Architect (NL) | B41: 1 | C41: 5 | D41: 5 | E41: 5 | F41: 5 | G41: 5 | H41: 2.5 | I41: 2.5 | J41: 2.5 | K41: 2.5 | L41: 2.5 | M41: 2.5 | N41: =SUM(C41:M41) -> 40
A42: Platform Architect (AWS) (IN) | B42: 1 | C42: 2 | D42: 2 | E42: 2 | F42: 2 | G42: 2 | H42: 2 | I42: 2 | J42: 2 | K42: 2 | L42: 2 | M42: 2 | N42: =SUM(C42:M42) -> 22
A43: Platform Architect (Azure) (IN) | B43: 1 | C43: 2 | D43: 2 | E43: 2 | F43: 2 | G43: 2 | H43: 2 | I43: 2 | J43: 2 | K43: 2 | L43: 2 | M43: 2 | N43: =SUM(C43:M43) -> 22
A44: Platform Architect (GCP) (NL) | B44: 1 | C44: 2 | D44: 2 | E44: 2 | F44: 2 | G44: 2 | H44: 2 | I44: 2 | J44: 2 | K44: 2 | L44: 2 | M44: 2 | N44: =SUM(C44:M44) -> 22
A45: Sr. Cloud Engineer (IN) | B45: 1 | C45: 5 | D45: 5 | E45: 2.5 | N45: =SUM(C45:M45) -> 12.5
A46: Migration Consultant (UK) | B46: 1 | J46: 1 | K46: 1 | L46: 1 | M46: 1 | N46: =SUM(C46:M46) -> 4
A51: Resource Role Hours & Assumptions

Sheet Milestones
D1: TOTAL | E1: =Calculator!I11 -> 99691.785
B4: Milestone | C4: Descriptions | D4: Deliverable | E4: ="Fee("&Calculator!F6&")" -> Fee(GBP) | G4: Split
B5: MS 1 | C5: Mobilisation | E5: =$E$1*G5 -> 0 | G5: 0
B6: MS 2 | C6: Kick-off | E6: =$E$1*G6 -> 49845.892 | G6: 0.5
B7: MS 3 | C7: Strategy Assessment | E7: =$E$1*G7 -> 0 | G7: 0
B8: MS 4 | C8: Infrastructure Discovery | E8: =$E$1*G8 -> 0 | G8: 0
B9: MS 5 | C9: CSP Selection | E9: =$E$1*G9 -> 0 | G9: 0
B10: MS 6 | C10: TCO Analysis | E10: =$E$1*G10 -> 0 | G10: 0
B11: MS 7 | C11: Cloud Strategy & Presentation | E11: =$E$1*G11 -> 49845.892 | G11: 0.5
B12: Total | E12: =SUM(E5:E11) -> 99691.785 | G12: =SUM(G5:G11) -> 1 | H12: =IF(AND(G12>99.98%,G12<=100.01%),"","There is an error in allocating total price. Please recheck the %s")

Sheet Price Tables 
C1: *US=United States, UK=United Kingdom, NL=Netherlands, AE=UAE, PL=Poland, DE=Germany, VN=Veitnam, AU=Australia, SG=Singapore, EG=Egypt, CAN=Canada, SA = Saudi Arabia, IN = India | AQ1: Check
B3: Currency | C3: USD
B5: Platform and Apps | E5: For All Markets except India, Egypt, Veitnam | Q5: Platform and Apps | U5: At Following Margins
B7: Platform & Apps Price | C7: US | D7: UK | E7: DE | F7: PL | G7: NL | H7: MX | I7: IN | J7: EG | K7: CAN | L7: AU | M7: AE | N7: SG | O7: VN | Q7: Price | R7: US | S7: UK | T7: DE | U7: PL | V7: NL | W7: MX | X7: IN | Y7: EG | Z7: CAN | AA7: AU | AB7: AE | AC7: SG | AD7: VN | AE7: SA
B8: Jr. Eng | C8: 0 | D8: 103.33333 | E8: 106.66667 | F8: 110 | G8: 0 | H8: 0 | I8: 40 | J8: 0 | K8: 0 | L8: 0 | M8: 0 | N8: 0 | O8: 0 | P8: =I8*(1-X8) -> 16 | Q8: Jr. Eng | R8: 0.4 | S8: 0.4 | T8: 0.4 | U8: 0.4 | V8: 0.4 | W8: 0.4 | X8: 0.6 | Y8: 0.6 | Z8: 0.4 | AA8: 0.4 | AB8: 0.4 | AC8: 0.4 | AD8: 0.4 | AE8: 0.6
B9: Eng | C9: 190 | D9: 153.33333 | E9: 150 | F9: 116.66667 | G9: 143.33333 | H9: 73 | I9: 50 | J9: 62.5 | K9: 0 | L9: 0 | M9: 155.59143 | N9: 0 | O9: 0 | P9: =I9*(1-X9) -> 20 | Q9: Eng | R9: 0.4 | S9: 0.4 | T9: 0.4 | U9: 0.4 | V9: 0.4 | W9: 0.4 | X9: 0.6 | Y9: 0.6 | Z9: 0.4 | AA9: 0.4 | AB9: 0.4 | AC9: 0.4 | AD9: 0.4 | AE9: 0.6
B10: Sr. Eng | C10: 220 | D10: 213.33333 | E10: 173.33333 | F10: 146.66667 | G10: 188.33333 | H10: 95 | I10: 80 | J10: 85 | K10: 168.33333 | L10: 0 | M10: 0 | N10: 0 | O10: 0 | P10: =I10*(1-X10) -> 32 | Q10: Sr. Eng | R10: 0.4 | S10: 0.4 | T10: 0.4 | U10: 0.4 | V10: 0.4 | W10: 0.4 | X10: 0.6 | Y10: 0.6 | Z10: 0.4 | AA10: 0.4 | AB10: 0.4 | AC10: 0.4 | AD10: 0.4 | AE10: 0.6
B11: Arch | C11: 290 | D11: 250 | E11: 223 | F11: 173.06667 | G11: 225 | H11: 156.66667 | I11: 100 | J11: 93.515572 | K11: 185 | L11: 0 | N11: 0 | O11: 0 | P11: =I11*(1-X11) -> 40 | Q11: Arch | R11: 0.4 | S11: 0.4 | T11: 0.4 | U11: 0.4 | V11: 0.4 | W11: 0.4 | X11: 0.6 | Y11: 0.6 | Z11: 0.4 | AA11: 0.4 | AB11: 0.4 | AC11: 0.4 | AD11: 0.4 | AE11: 0.6
B12: Sr. Arch | C12: 310 | D12: 260 | E12: 0 | F12: 0 | G12: 256.5 | H12: 167.47126 | I12: 102.5 | J12: 0 | K12: 213.33333 | L12: 0 | M12: 241.42857 | N12: 0 | O12: 0 | P12: =I12*(1-X12) -> 41 | Q12: Sr. Arch | R12: 0.4 | S12: 0.4 | T12: 0.4 | U12: 0.4 | V12: 0.4 | W12: 0.4 | X12: 0.6 | Y12: 0.6 | Z12: 0.4 | AA12: 0.4 | AB12: 0.4 | AC12: 0.4 | AD12: 0.4 | AE12: 0.6
B13: TCT/Lead Arch | D13: 278.33333 | E13: 0 | F13: 0 | G13: 408.33333 | H13: 0 | I13: 0 | J13: 0 | K13: 288.33333 | L13: 0 | M13: 0 | N13: 0 | O13: 0 | P13: =I13*(1-X13) -> 0 | Q13: TCT/Lead Arch | R13: 0.4 | S13: 0.4 | T13: 0.4 | U13: 0.4 | V13: 0.4 | W13: 0.4 | X13: 0.6 | Y13: 0.6 | Z13: 0.4 | AA13: 0.4 | AB13: 0.4 | AC13: 0.4 | AD13: 0.4 | AE13: 0.6
B14: Manager | C14: 300 | D14: 265 | E14: 215.71429 | F14: 0 | G14: 240 | H14: 0 | I14: 105 | J14: 116 | K14: 195 | L14: 0 | M14: 0 | N14: 0 | O14: 0 | P14: =I14*(1-X14) -> 52.5 | Q14: Manager | R14: 0.3 | S14: 0.3 | T14: 0.3 | U14: 0.3 | V14: 0.3 | W14: 0.3 | X14: 0.5 | Y14: 0.5 | Z14: 0.3 | AA14: 0.3 | AB14: 0.3 | AC14: 0.3 | AD14: 0.3 | AE14: 0.5
B15: Sr. Mgr | C15: 350 | D15: 310 | E15: 0 | F15: 0 | G15: 260 | H15: 0 | I15: 110 | J15: 0 | K15: 0 | L15: 0 | M15: 0 | N15: 0 | O15: 0 | P15: =I15*(1-X15) -> 55 | Q15: Sr. Mgr | R15: 0.3 | S15: 0.3 | T15: 0.3 | U15: 0.3 | V15: 0.3 | W15: 0.3 | X15: 0.5 | Y15: 0.5 | Z15: 0.3 | AA15: 0.3 | AB15: 0.3 | AC15: 0.3 | AD15: 0.3 | AE15: 0.5
B16: EM/PJM | D16: 228.69333 | E16: 208 | F16: 0 | G16: 0 | H16: 95.676721 | I16: 88 | J16: 102 | K16: 0 | L16: 0 | M16: 0 | N16: 0 | O16: 0 | P16: =I16*(1-X16) -> 35.2 | Q16: EM/PJM | R16: 0.4 | S16: 0.4 | T16: 0.4 | U16: 0.4 | V16: 0.4 | W16: 0.4 | X16: 0.6 | Y16: 0.6 | Z16: 0.4 | AA16: 0.4 | AB16: 0.4 | AC16: 0.4 | AD16: 0.4 | AE16: 0.6
B17: Sr. EM/Sr. PJM/PGM | C17: 301 | D17: 255 | E17: 221.66667 | F17: 207.68 | G17: 231.66667 | H17: 0 | I17: 101 | J17: 115 | K17: 195 | L17: 0 | N17: 198.33333 | O17: 0 | P17: =I17*(1-X17) -> 40.4 | Q17: Sr. EM/Sr. PJM/PGM | R17: 0.4 | S17: 0.4 | T17: 0.4 | U17: 0.4 | V17: 0.4 | W17: 0.4 | X17: 0.6 | Y17: 0.6 | Z17: 0.4 | AA17: 0.4 | AB17: 0.4 | AC17: 0.4 | AD17: 0.4 | AE17: 0.6
B20: Data
B22: Data Price | C22: US | D22: UK | E22: DE | F22: PL | G22: NL | H22: MX | I22: IN | J22: EG | K22: CA | L22: AU | M22: AE | N22: SG | O22: VN | U22: 90 | X22: =I10*0.4 -> 32
B23: Associate Eng | C23: 147 | D23: 0 | E23: 0 | F23: 0 | G23: 0 | H23: 0 | I23: 31 | J23: 53 | K23: 0 | L23: 0 | M23: 0 | N23: 68 | O23: 29 | T23: 2100000 | U23: =T23/U22 -> 23333.333 | V23: =U23/1480 -> 15.765766 | X23: =X22/0.7 -> 45.714286 | Y23: =J8*(1-Y8) -> 0
B24: Eng | C24: 230 | D24: 0 | E24: 0 | F24: 0 | G24: 172 | H24: 0 | I24: 63 | J24: 75 | K24: 170 | L24: 0 | M24: 0 | N24: 106 | O24: 56 | V24: =V23*1.22 -> 19.234234 | Y24: =J9*(1-Y9) -> 25
B25: Sr. Eng | C25: 277 | D25: 0 | E25: 0 | F25: 0 | G25: 0 | H25: 0 | I25: 90 | J25: 76 | K25: 183 | L25: 0 | M25: 106 | N25: 0 | O25: 97 | V25: =V24/0.4 -> 48.085586 | Y25: =J10*(1-Y10) -> 34
B26: Staff Eng | C26: 354 | D26: 0 | E26: 0 | F26: 0 | G26: 0 | H26: 0 | I26: 99 | J26: 0 | K26: 0 | L26: 0 | M26: 0 | N26: 0 | O26: 0 | Y26: =J11*(1-Y11) -> 37.406229
B27: Lead Eng | C27: 528 | D27: 0 | E27: 0 | F27: 0 | G27: 0 | H27: 0 | I27: 135 | J27: 0 | K27: 0 | L27: 0 | M27: 0 | N27: 0 | O27: 0 | Y27: =J12*(1-Y12) -> 0
B28: Arch | C28: 290 | D28: 0 | E28: 0 | F28: 0 | G28: 0 | H28: 0 | I28: 149 | J28: 110 | K28: 191 | L28: 0 | M28: 0 | N28: 187 | O28: 103 | U28: =50*0.4 -> 20 | Y28: =J13*(1-Y13) -> 0
B29: Sr. Arch | C29: 370 | D29: 0 | E29: 0 | F29: 0 | G29: 0 | H29: 0 | I29: 118 | J29: 0 | K29: 235 | L29: 0 | M29: 0 | N29: 0 | O29: 0 | Y29: =J14*(1-Y14) -> 58
B30: Lead Arch | C30: 361 | D30: 0 | E30: 0 | F30: 0 | G30: 0 | H30: 0 | I30: 0 | J30: 0 | K30: 0 | L30: 0 | M30: 0 | N30: 0 | O30: 0 | Y30: =J15*(1-Y15) -> 0
B31: Manager | C31: 545 | D31: 0 | E31: 0 | F31: 0 | G31: 0 | H31: 0 | I31: 87 | J31: 82 | K31: 0 | L31: 0 | M31: 0 | N31: 0 | O31: 0 | Y31: =J16*(1-Y16) -> 40.8
B32: Sr. Mgr | C32: 0 | D32: 0 | E32: 0 | F32: 0 | G32: 0 | H32: 0 | I32: 0 | J32: 0 | K32: 385 | L32: 0 | M32: 0 | N32: 379 | O32: 127 | Y32: =J17*(1-Y17) -> 46
B33: EM | C33: 0 | D33: 0 | E33: 0 | F33: 0 | G33: 0 | H33: 0 | I33: 82 | J33: 52 | K33: 0 | L33: 0 | M33: 0 | N33: 124 | O33: 36
B34: Sr. EM | C34: 225 | D34: 0 | E34: 0 | F34: 0 | G34: 304 | H34: 0 | I34: 142 | J34: 79 | K34: 0 | L34: 0 | M34: 0 | N34: 0 | O34: 146
B36: Security
B38: Security PS Price | C38: US | D38: UK | E38: DE | F38: PL | G38: NL | H38: MX | I38: IN | J38: EG | K38: CAN | L38: AU | M38: AE | N38: SG | O38: VN
B39: Jr. Eng | C39: =IFERROR(ROUND(Costs!C36/(1-R8),0)*INDEX(fx,MATCH($C$3,currency,0)),"") -> 0 | D39: =IFERROR(ROUND(Costs!D36/(1-S8),0)*INDEX(fx,MATCH($C$3,currency,0)),"") -> 0 | E39: =IFERROR(ROUND(Costs!E36/(1-T8),0)*INDEX(fx,MATCH($C$3,currency,0)),"") -> 0 | F39: =IFERROR(ROUND(Costs!F36/(1-U8),0)*INDEX(fx,MATCH($C$3,currency,0)),"") -> 0 | G39: =IFERROR(ROUND(Costs!G36/(1-V8),0)*INDEX(fx,MATCH($C$3,currency,0)),"") -> 0 | H39: =IFERROR(ROUND(Costs!H36/(1-W8),0)*INDEX(fx,MATCH($C$3,currency,0)),"") -> 0 | I39: =IFERROR(ROUND(Costs!I36/(1-X8),0)*INDEX(fx,MATCH($C$3,currency,0)),"") -> 37 | J39: =IFERROR(ROUND(Costs!J36/(1-Y8),0)*INDEX(fx,MATCH($C$3,currency,0)),"") -> 0 | ... O39: =IFERROR(ROUND(Costs!O36/(1-AD8),0)*INDEX(fx,MATCH($C$3,currency,0)),"") -> 0
B40: Eng | C40: =IFERROR(ROUND(Costs!C37/(1-R9),0)*INDEX(fx,MATCH($C$3,currency,0)),"") -> 0 | D40: =IFERROR(ROUND(Costs!D37/(1-S9),0)*INDEX(fx,MATCH($C$3,currency,0)),"") -> 0 | E40: =IFERROR(ROUND(Costs!E37/(1-T9),0)*INDEX(fx,MATCH($C$3,currency,0)),"") -> 0 | F40: =IFERROR(ROUND(Costs!F37/(1-U9),0)*INDEX(fx,MATCH($C$3,currency,0)),"") -> 0 | G40: =IFERROR(ROUND(Costs!G37/(1-V9),0)*INDEX(fx,MATCH($C$3,currency,0)),"") -> 0 | H40: =IFERROR(ROUND(Costs!H37/(1-W9),0)*INDEX(fx,MATCH($C$3,currency,0)),"") -> 72 | I40: =IFERROR(ROUND(Costs!I37/(1-X9),0)*INDEX(fx,MATCH($C$3,currency,0)),"") -> 51 | J40: =IFERROR(ROUND(Costs!J37/(1-Y9),0)*INDEX(fx,MATCH($C$3,currency,0)),"") -> 0 | ... O40: =IFERROR(ROUND(Costs!O37/(1-AD9),0)*INDEX(fx,MATCH($C$3,currency,0)),"") -> 0
B41: Sr. Eng | C41: =IFERROR(ROUND(Costs!C38/(1-R10),0)*INDEX(fx,MATCH($C$3,currency,0)),"") -> 223 | D41: =IFERROR(ROUND(Costs!D38/(1-S10),0)*INDEX(fx,MATCH($C$3,currency,0)),"") -> 0 | E41: =IFERROR(ROUND(Costs!E38/(1-T10),0)*INDEX(fx,MATCH($C$3,currency,0)),"") -> 0 | F41: =IFERROR(ROUND(Costs!F38/(1-U10),0)*INDEX(fx,MATCH($C$3,currency,0)),"") -> 0 | G41: =IFERROR(ROUND(Costs!G38/(1-V10),0)*INDEX(fx,MATCH($C$3,currency,0)),"") -> 0 | H41: =IFERROR(ROUND(Costs!H38/(1-W10),0)*INDEX(fx,MATCH($C$3,currency,0)),"") -> 84 | I41: =IFERROR(ROUND(Costs!I38/(1-X10),0)*INDEX(fx,MATCH($C$3,currency,0)),"") -> 80 | J41: =IFERROR(ROUND(Costs!J38/(1-Y10),0)*INDEX(fx,MATCH($C$3,currency,0)),"") -> 0 | ... O41: =IFERROR(ROUND(Costs!O38/(1-AD10),0)*INDEX(fx,MATCH($C$3,currency,0)),"") -> 0
B42: Arch | C42: =IFERROR(ROUND(Costs!C39/(1-R11),0)*INDEX(fx,MATCH($C$3,currency,0)),"") -> 280 | D42: =IFERROR(ROUND(Costs!D39/(1-S11),0)*INDEX(fx,MATCH($C$3,currency,0)),"") -> 207 | E42: =IFERROR(ROUND(Costs!E39/(1-T11),0)*INDEX(fx,MATCH($C$3,currency,0)),"") -> 214 | F42: =IFERROR(ROUND(Costs!F39/(1-U11),0)*INDEX(fx,MATCH($C$3,currency,0)),"") -> 0 | G42: =IFERROR(ROUND(Costs!G39/(1-V11),0)*INDEX(fx,MATCH($C$3,currency,0)),"") -> 238 | H42: =IFERROR(ROUND(Costs!H39/(1-W11),0)*INDEX(fx,MATCH($C$3,currency,0)),"") -> 119 | I42: =IFERROR(ROUND(Costs!I39/(1-X11),0)*INDEX(fx,MATCH($C$3,currency,0)),"") -> 0 | J42: =IFERROR(ROUND(Costs!J39/(1-Y11),0)*INDEX(fx,MATCH($C$3,currency,0)),"") -> 0 | ... O42: =IFERROR(ROUND(Costs!O39/(1-AD11),0)*INDEX(fx,MATCH($C$3,currency,0)),"") -> 0
B43: Sr. Arch | C43: =IFERROR(ROUND(Costs!C40/(1-R12),0)*INDEX(fx,MATCH($C$3,currency,0)),"") -> 322 | D43: =IFERROR(ROUND(Costs!D40/(1-S12),0)*INDEX(fx,MATCH($C$3,currency,0)),"") -> 0 | E43: =IFERROR(ROUND(Costs!E40/(1-T12),0)*INDEX(fx,MATCH($C$3,currency,0)),"") -> 0 | F43: =IFERROR(ROUND(Costs!F40/(1-U12),0)*INDEX(fx,MATCH($C$3,currency,0)),"") -> 0 | G43: =IFERROR(ROUND(Costs!G40/(1-V12),0)*INDEX(fx,MATCH($C$3,currency,0)),"") -> 261 | H43: =IFERROR(ROUND(Costs!H40/(1-W12),0)*INDEX(fx,MATCH($C$3,currency,0)),"") -> 0 | I43: =IFERROR(ROUND(Costs!I40/(1-X12),0)*INDEX(fx,MATCH($C$3,currency,0)),"") -> 0 | J43: =IFERROR(ROUND(Costs!J40/(1-Y12),0)*INDEX(fx,MATCH($C$3,currency,0)),"") -> 0 | ... O43: =IFERROR(ROUND(Costs!O40/(1-AD12),0)*INDEX(fx,MATCH($C$3,currency,0)),"") -> 0
B44: TCT/Lead Arch | C44: =IFERROR(ROUND(Costs!C41/(1-R13),0)*INDEX(fx,MATCH($C$3,currency,0)),"") -> 0 | D44: =IFERROR(ROUND(Costs!D41/(1-S13),0)*INDEX(fx,MATCH($C$3,currency,0)),"") -> 0 | E44: =IFERROR(ROUND(Costs!E41/(1-T13),0)*INDEX(fx,MATCH($C$3,currency,0)),"") -> 0 | F44: =IFERROR(ROUND(Costs!F41/(1-U13),0)*INDEX(fx,MATCH($C$3,currency,0)),"") -> 0 | G44: =IFERROR(ROUND(Costs!G41/(1-V13),0)*INDEX(fx,MATCH($C$3,currency,0)),"") -> 0 | H44: =IFERROR(ROUND(Costs!H41/(1-W13),0)*INDEX(fx,MATCH($C$3,currency,0)),"") -> 0 | I44: =IFERROR(ROUND(Costs!I41/(1-X13),0)*INDEX(fx,MATCH($C$3,currency,0)),"") -> 0 | J44: =IFERROR(ROUND(Costs!J41/(1-Y13),0)*INDEX(fx,MATCH($C$3,currency,0)),"") -> 0 | ... O44: =IFERROR(ROUND(Costs!O41/(1-AD13),0)*INDEX(fx,MATCH($C$3,currency,0)),"") -> 0
B45: Manager | C45: =IFERROR(ROUND(Costs!C42/(1-R14),0)*INDEX(fx,MATCH($C$3,currency,0)),"") -> 0 | D45: =IFERROR(ROUND(Costs!D42/(1-S14),0)*INDEX(fx,MATCH($C$3,currency,0)),"") -> 144 | E45: =IFERROR(ROUND(Costs!E42/(1-T14),0)*INDEX(fx,MATCH($C$3,currency,0)),"") -> 0 | F45: =IFERROR(ROUND(Costs!F42/(1-U14),0)*INDEX(fx,MATCH($C$3,currency,0)),"") -> 0 | G45: =IFERROR(ROUND(Costs!G42/(1-V14),0)*INDEX(fx,MATCH($C$3,currency,0)),"") -> 0 | H45: =IFERROR(ROUND(Costs!H42/(1-W14),0)*INDEX(fx,MATCH($C$3,currency,0)),"") -> 0 | I45: =IFERROR(ROUND(Costs!I42/(1-X14),0)*INDEX(fx,MATCH($C$3,currency,0)),"") -> 78 | J45: =IFERROR(ROUND(Costs!J42/(1-Y14),0)*INDEX(fx,MATCH($C$3,currency,0)),"") -> 0 | ... O45: =IFERROR(ROUND(Costs!O42/(1-AD14),0)*INDEX(fx,MATCH($C$3,currency,0)),"") -> 0
B46: Sr. Mgr | C46: =IFERROR(ROUND(Costs!C43/(1-R15),0)*INDEX(fx,MATCH($C$3,currency,0)),"") -> 545 | D46: =IFERROR(ROUND(Costs!D43/(1-S15),0)*INDEX(fx,MATCH($C$3,currency,0)),"") -> 396 | E46: =IFERROR(ROUND(Costs!E43/(1-T15),0)*INDEX(fx,MATCH($C$3,currency,0)),"") -> 0 | F46: =IFERROR(ROUND(Costs!F43/(1-U15),0)*INDEX(fx,MATCH($C$3,currency,0)),"") -> 0 | G46: =IFERROR(ROUND(Costs!G43/(1-V15),0)*INDEX(fx,MATCH($C$3,currency,0)),"") -> 0 | H46: =IFERROR(ROUND(Costs!H43/(1-W15),0)*INDEX(fx,MATCH($C$3,currency,0)),"") -> 0 | I46: =IFERROR(ROUND(Costs!I43/(1-X15),0)*INDEX(fx,MATCH($C$3,currency,0)),"") -> 0 | J46: =IFERROR(ROUND(Costs!J43/(1-Y15),0)*INDEX(fx,MATCH($C$3,currency,0)),"") -> 0 | ... O46: =IFERROR(ROUND(Costs!O43/(1-AD15),0)*INDEX(fx,MATCH($C$3,currency,0)),"") -> 0
B47: EM/PJM | C47: =IFERROR(ROUND(Costs!C44/(1-R16),0)*INDEX(fx,MATCH($C$3,currency,0)),"") -> 0 | D47: =IFERROR(ROUND(Costs!D44/(1-S16),0)*INDEX(fx,MATCH($C$3,currency,0)),"") -> 0 | E47: =IFERROR(ROUND(Costs!E44/(1-T16),0)*INDEX(fx,MATCH($C$3,currency,0)),"") -> 0 | F47: =IFERROR(ROUND(Costs!F44/(1-U16),0)*INDEX(fx,MATCH($C$3,currency,0)),"") -> 0 | G47: =IFERROR(ROUND(Costs!G44/(1-V16),0)*INDEX(fx,MATCH($C$3,currency,0)),"") -> 0 | H47: =IFERROR(ROUND(Costs!H44/(1-W16),0)*INDEX(fx,MATCH($C$3,currency,0)),"") -> 0 | I47: =IFERROR(ROUND(Costs!I44/(1-X16),0)*INDEX(fx,MATCH($C$3,currency,0)),"") -> 0 | J47: =IFERROR(ROUND(Costs!J44/(1-Y16),0)*INDEX(fx,MATCH($C$3,currency,0)),"") -> 0 | ... O47: =IFERROR(ROUND(Costs!O44/(1-AD16),0)*INDEX(fx,MATCH($C$3,currency,0)),"") -> 0
B48: Sr. EM/Sr. PJM/PGM | C48: =IFERROR(ROUND(Costs!C45/(1-R17),0)*INDEX(fx,MATCH($C$3,currency,0)),"") -> 0 | D48: =IFERROR(ROUND(Costs!D45/(1-S17),0)*INDEX(fx,MATCH($C$3,currency,0)),"") -> 0 | E48: =IFERROR(ROUND(Costs!E45/(1-T17),0)*INDEX(fx,MATCH($C$3,currency,0)),"") -> 0 | F48: =IFERROR(ROUND(Costs!F45/(1-U17),0)*INDEX(fx,MATCH($C$3,currency,0)),"") -> 0 | G48: =IFERROR(ROUND(Costs!G45/(1-V17),0)*INDEX(fx,MATCH($C$3,currency,0)),"") -> 0 | H48: =IFERROR(ROUND(Costs!H45/(1-W17),0)*INDEX(fx,MATCH($C$3,currency,0)),"") -> 0 | I48: =IFERROR(ROUND(Costs!I45/(1-X17),0)*INDEX(fx,MATCH($C$3,currency,0)),"") -> 0 | J48: =IFERROR(ROUND(Costs!J45/(1-Y17),0)*INDEX(fx,MATCH($C$3,currency,0)),"") -> 0 | ... O48: =IFERROR(ROUND(Costs!O45/(1-AD17),0)*INDEX(fx,MATCH($C$3,currency,0)),"") -> 0
B51: PS Private Cloud | C51: US | D51: UK | E51: DE | F51: PL | G51: NL | H51: MX | I51: IN | J51: EG | K51: CAN | L51: AU | M51: AE | N51: SG | O51: VN | P51: SA
B52: Jr. Engineer | C52: =IFERROR(ROUND(Costs!C80/(1-40%),0)*INDEX(fx,MATCH($C$3,currency,0)),"") -> 0 | D52: =IFERROR(ROUND(Costs!D80/(1-40%),0)*INDEX(fx,MATCH($C$3,currency,0)),"") -> 0 | E52: =IFERROR(ROUND(Costs!E80/(1-40%),0)*INDEX(fx,MATCH($C$3,currency,0)),"") -> 0 | F52: =IFERROR(ROUND(Costs!F80/(1-40%),0)*INDEX(fx,MATCH($C$3,currency,0)),"") -> 0 | G52: =IFERROR(ROUND(Costs!G80/(1-40%),0)*INDEX(fx,MATCH($C$3,currency,0)),"") -> 0 | H52: =IFERROR(ROUND(Costs!H80/(1-40%),0)*INDEX(fx,MATCH($C$3,currency,0)),"") -> 0 | I52: =IFERROR(ROUND(Costs!I80/(1-40%),0)*INDEX(fx,MATCH($C$3,currency,0)),"") -> 0 | J52: =IFERROR(ROUND(Costs!J80/(1-40%),0)*INDEX(fx,MATCH($C$3,currency,0)),"") -> 0 | ... P52: =IFERROR(ROUND(Costs!P80/(1-40%),0)*INDEX(fx,MATCH($C$3,currency,0)),"") -> 0
B53: Engineer | C53: =IFERROR(ROUND(Costs!C81/(1-40%),0)*INDEX(fx,MATCH($C$3,currency,0)),"") -> 187 | D53: =IFERROR(ROUND(Costs!D81/(1-40%),0)*INDEX(fx,MATCH($C$3,currency,0)),"") -> 0 | E53: =IFERROR(ROUND(Costs!E81/(1-40%),0)*INDEX(fx,MATCH($C$3,currency,0)),"") -> 0 | F53: =IFERROR(ROUND(Costs!F81/(1-40%),0)*INDEX(fx,MATCH($C$3,currency,0)),"") -> 0 | G53: =IFERROR(ROUND(Costs!G81/(1-40%),0)*INDEX(fx,MATCH($C$3,currency,0)),"") -> 0 | H53: =IFERROR(ROUND(Costs!H81/(1-40%),0)*INDEX(fx,MATCH($C$3,currency,0)),"") -> 0 | I53: =IFERROR(ROUND(Costs!I81/(1-40%),0)*INDEX(fx,MATCH($C$3,currency,0)),"") -> 40 | J53: =IFERROR(ROUND(Costs!J81/(1-40%),0)*INDEX(fx,MATCH($C$3,currency,0)),"") -> 0 | ... P53: =IFERROR(ROUND(Costs!P81/(1-40%),0)*INDEX(fx,MATCH($C$3,currency,0)),"") -> 0
B54: Sr. Engineer | C54: =IFERROR(ROUND(Costs!C82/(1-40%),0)*INDEX(fx,MATCH($C$3,currency,0)),"") -> 225 | D54: =IFERROR(ROUND(Costs!D82/(1-40%),0)*INDEX(fx,MATCH($C$3,currency,0)),"") -> 148 | E54: =IFERROR(ROUND(Costs!E82/(1-40%),0)*INDEX(fx,MATCH($C$3,currency,0)),"") -> 0 | F54: =IFERROR(ROUND(Costs!F82/(1-40%),0)*INDEX(fx,MATCH($C$3,currency,0)),"") -> 0 | G54: =IFERROR(ROUND(Costs!G82/(1-40%),0)*INDEX(fx,MATCH($C$3,currency,0)),"") -> 0 | H54: =IFERROR(ROUND(Costs!H82/(1-40%),0)*INDEX(fx,MATCH($C$3,currency,0)),"") -> 0 | I54: =IFERROR(ROUND(Costs!I82/(1-40%),0)*INDEX(fx,MATCH($C$3,currency,0)),"") -> 48 | J54: =IFERROR(ROUND(Costs!J82/(1-40%),0)*INDEX(fx,MATCH($C$3,currency,0)),"") -> 0 | ... P54: =IFERROR(ROUND(Costs!P82/(1-40%),0)*INDEX(fx,MATCH($C$3,currency,0)),"") -> 0
B55: Architect | C55: =IFERROR(ROUND(Costs!C83/(1-40%),0)*INDEX(fx,MATCH($C$3,currency,0)),"") -> 250 | D55: =IFERROR(ROUND(Costs!D83/(1-40%),0)*INDEX(fx,MATCH($C$3,currency,0)),"") -> 195 | E55: =IFERROR(ROUND(Costs!E83/(1-40%),0)*INDEX(fx,MATCH($C$3,currency,0)),"") -> 178 | F55: =IFERROR(ROUND(Costs!F83/(1-40%),0)*INDEX(fx,MATCH($C$3,currency,0)),"") -> 0 | G55: =IFERROR(ROUND(Costs!G83/(1-40%),0)*INDEX(fx,MATCH($C$3,currency,0)),"") -> 0 | H55: =IFERROR(ROUND(Costs!H83/(1-40%),0)*INDEX(fx,MATCH($C$3,currency,0)),"") -> 0 | I55: =IFERROR(ROUND(Costs!I83/(1-40%),0)*INDEX(fx,MATCH($C$3,currency,0)),"") -> 0 | J55: =IFERROR(ROUND(Costs!J83/(1-40%),0)*INDEX(fx,MATCH($C$3,currency,0)),"") -> 0 | ... P55: =IFERROR(ROUND(Costs!P83/(1-40%),0)*INDEX(fx,MATCH($C$3,currency,0)),"") -> 0
B56: Sr. Architect | C56: =IFERROR(ROUND(Costs!C84/(1-40%),0)*INDEX(fx,MATCH($C$3,currency,0)),"") -> 0 | D56: =IFERROR(ROUND(Costs!D84/(1-40%),0)*INDEX(fx,MATCH($C$3,currency,0)),"") -> 287 | E56: =IFERROR(ROUND(Costs!E84/(1-40%),0)*INDEX(fx,MATCH($C$3,currency,0)),"") -> 0 | F56: =IFERROR(ROUND(Costs!F84/(1-40%),0)*INDEX(fx,MATCH($C$3,currency,0)),"") -> 0 | G56: =IFERROR(ROUND(Costs!G84/(1-40%),0)*INDEX(fx,MATCH($C$3,currency,0)),"") -> 0 | H56: =IFERROR(ROUND(Costs!H84/(1-40%),0)*INDEX(fx,MATCH($C$3,currency,0)),"") -> 0 | I56: =IFERROR(ROUND(Costs!I84/(1-40%),0)*INDEX(fx,MATCH($C$3,currency,0)),"") -> 0 | J56: =IFERROR(ROUND(Costs!J84/(1-40%),0)*INDEX(fx,MATCH($C$3,currency,0)),"") -> 0 | ... P56: =IFERROR(ROUND(Costs!P84/(1-40%),0)*INDEX(fx,MATCH($C$3,currency,0)),"") -> 0
B57: Consultant | C57: =IFERROR(ROUND(Costs!C85/(1-40%),0)*INDEX(fx,MATCH($C$3,currency,0)),"") -> 0 | D57: =IFERROR(ROUND(Costs!D85/(1-40%),0)*INDEX(fx,MATCH($C$3,currency,0)),"") -> 148 | E57: =IFERROR(ROUND(Costs!E85/(1-40%),0)*INDEX(fx,MATCH($C$3,currency,0)),"") -> 0 | F57: =IFERROR(ROUND(Costs!F85/(1-40%),0)*INDEX(fx,MATCH($C$3,currency,0)),"") -> 0 | G57: =IFERROR(ROUND(Costs!G85/(1-40%),0)*INDEX(fx,MATCH($C$3,currency,0)),"") -> 0 | H57: =IFERROR(ROUND(Costs!H85/(1-40%),0)*INDEX(fx,MATCH($C$3,currency,0)),"") -> 0 | I57: =IFERROR(ROUND(Costs!I85/(1-40%),0)*INDEX(fx,MATCH($C$3,currency,0)),"") -> 0 | J57: =IFERROR(ROUND(Costs!J85/(1-40%),0)*INDEX(fx,MATCH($C$3,currency,0)),"") -> 0 | ... P57: =IFERROR(ROUND(Costs!P85/(1-40%),0)*INDEX(fx,MATCH($C$3,currency,0)),"") -> 0
B58: Sr. Consultant | C58: =IFERROR(ROUND(Costs!C86/(1-40%),0)*INDEX(fx,MATCH($C$3,currency,0)),"") -> 0 | D58: =IFERROR(ROUND(Costs!D86/(1-40%),0)*INDEX(fx,MATCH($C$3,currency,0)),"") -> 215 | E58: =IFERROR(ROUND(Costs!E86/(1-40%),0)*INDEX(fx,MATCH($C$3,currency,0)),"") -> 0 | F58: =IFERROR(ROUND(Costs!F86/(1-40%),0)*INDEX(fx,MATCH($C$3,currency,0)),"") -> 0 | G58: =IFERROR(ROUND(Costs!G86/(1-40%),0)*INDEX(fx,MATCH($C$3,currency,0)),"") -> 0 | H58: =IFERROR(ROUND(Costs!H86/(1-40%),0)*INDEX(fx,MATCH($C$3,currency,0)),"") -> 0 | I58: =IFERROR(ROUND(Costs!I86/(1-40%),0)*INDEX(fx,MATCH($C$3,currency,0)),"") -> 0 | J58: =IFERROR(ROUND(Costs!J86/(1-40%),0)*INDEX(fx,MATCH($C$3,currency,0)),"") -> 0 | ... P58: =IFERROR(ROUND(Costs!P86/(1-40%),0)*INDEX(fx,MATCH($C$3,currency,0)),"") -> 0
B59: Developer | C59: =IFERROR(ROUND(Costs!C87/(1-40%),0)*INDEX(fx,MATCH($C$3,currency,0)),"") -> 0 | D59: =IFERROR(ROUND(Costs!D87/(1-40%),0)*INDEX(fx,MATCH($C$3,currency,0)),"") -> 0 | E59: =IFERROR(ROUND(Costs!E87/(1-40%),0)*INDEX(fx,MATCH($C$3,currency,0)),"") -> 0 | F59: =IFERROR(ROUND(Costs!F87/(1-40%),0)*INDEX(fx,MATCH($C$3,currency,0)),"") -> 0 | G59: =IFERROR(ROUND(Costs!G87/(1-40%),0)*INDEX(fx,MATCH($C$3,currency,0)),"") -> 0 | H59: =IFERROR(ROUND(Costs!H87/(1-40%),0)*INDEX(fx,MATCH($C$3,currency,0)),"") -> 0 | I59: =IFERROR(ROUND(Costs!I87/(1-40%),0)*INDEX(fx,MATCH($C$3,currency,0)),"") -> 0 | J59: =IFERROR(ROUND(Costs!J87/(1-40%),0)*INDEX(fx,MATCH($C$3,currency,0)),"") -> 0 | ... P59: =IFERROR(ROUND(Costs!P87/(1-40%),0)*INDEX(fx,MATCH($C$3,currency,0)),"") -> 0
B60: Project Coordinator | C60: =IFERROR(ROUND(Costs!C88/(1-40%),0)*INDEX(fx,MATCH($C$3,currency,0)),"") -> 0 | D60: =IFERROR(ROUND(Costs!D88/(1-40%),0)*INDEX(fx,MATCH($C$3,currency,0)),"") -> 63 | E60: =IFERROR(ROUND(Costs!E88/(1-40%),0)*INDEX(fx,MATCH($C$3,currency,0)),"") -> 0 | F60: =IFERROR(ROUND(Costs!F88/(1-40%),0)*INDEX(fx,MATCH($C$3,currency,0)),"") -> 0 | G60: =IFERROR(ROUND(Costs!G88/(1-40%),0)*INDEX(fx,MATCH($C$3,currency,0)),"") -> 0 | H60: =IFERROR(ROUND(Costs!H88/(1-40%),0)*INDEX(fx,MATCH($C$3,currency,0)),"") -> 0 | I60: =IFERROR(ROUND(Costs!I88/(1-40%),0)*INDEX(fx,MATCH($C$3,currency,0)),"") -> 17 | J60: =IFERROR(ROUND(Costs!J88/(1-40%),0)*INDEX(fx,MATCH($C$3,currency,0)),"") -> 0 | ... P60: =IFERROR(ROUND(Costs!P88/(1-40%),0)*INDEX(fx,MATCH($C$3,currency,0)),"") -> 0
B61: Project Mgr | C61: =IFERROR(ROUND(Costs!C89/(1-40%),0)*INDEX(fx,MATCH($C$3,currency,0)),"") -> 0 | D61: =IFERROR(ROUND(Costs!D89/(1-40%),0)*INDEX(fx,MATCH($C$3,currency,0)),"") -> 133 | E61: =IFERROR(ROUND(Costs!E89/(1-40%),0)*INDEX(fx,MATCH($C$3,currency,0)),"") -> 0 | F61: =IFERROR(ROUND(Costs!F89/(1-40%),0)*INDEX(fx,MATCH($C$3,currency,0)),"") -> 0 | G61: =IFERROR(ROUND(Costs!G89/(1-40%),0)*INDEX(fx,MATCH($C$3,currency,0)),"") -> 0 | H61: =IFERROR(ROUND(Costs!H89/(1-40%),0)*INDEX(fx,MATCH($C$3,currency,0)),"") -> 0 | I61: =IFERROR(ROUND(Costs!I89/(1-40%),0)*INDEX(fx,MATCH($C$3,currency,0)),"") -> 40 | J61: =IFERROR(ROUND(Costs!J89/(1-40%),0)*INDEX(fx,MATCH($C$3,currency,0)),"") -> 0 | ... P61: =IFERROR(ROUND(Costs!P89/(1-40%),0)*INDEX(fx,MATCH($C$3,currency,0)),"") -> 0
B62: Sr. Proj Mgr | C62: =IFERROR(ROUND(Costs!C90/(1-40%),0)*INDEX(fx,MATCH($C$3,currency,0)),"") -> 0 | D62: =IFERROR(ROUND(Costs!D90/(1-40%),0)*INDEX(fx,MATCH($C$3,currency,0)),"") -> 160 | E62: =IFERROR(ROUND(Costs!E90/(1-40%),0)*INDEX(fx,MATCH($C$3,currency,0)),"") -> 0 | F62: =IFERROR(ROUND(Costs!F90/(1-40%),0)*INDEX(fx,MATCH($C$3,currency,0)),"") -> 0 | G62: =IFERROR(ROUND(Costs!G90/(1-40%),0)*INDEX(fx,MATCH($C$3,currency,0)),"") -> 0 | H62: =IFERROR(ROUND(Costs!H90/(1-40%),0)*INDEX(fx,MATCH($C$3,currency,0)),"") -> 0 | I62: =IFERROR(ROUND(Costs!I90/(1-40%),0)*INDEX(fx,MATCH($C$3,currency,0)),"") -> 0 | J62: =IFERROR(ROUND(Costs!J90/(1-40%),0)*INDEX(fx,MATCH($C$3,currency,0)),"") -> 0 | ... P62: =IFERROR(ROUND(Costs!P90/(1-40%),0)*INDEX(fx,MATCH($C$3,currency,0)),"") -> 0
B63: Prog Mgr | C63: =IFERROR(ROUND(Costs!C91/(1-40%),0)*INDEX(fx,MATCH($C$3,currency,0)),"") -> 0 | D63: =IFERROR(ROUND(Costs!D91/(1-40%),0)*INDEX(fx,MATCH($C$3,currency,0)),"") -> 202 | E63: =IFERROR(ROUND(Costs!E91/(1-40%),0)*INDEX(fx,MATCH($C$3,currency,0)),"") -> 0 | F63: =IFERROR(ROUND(Costs!F91/(1-40%),0)*INDEX(fx,MATCH($C$3,currency,0)),"") -> 0 | G63: =IFERROR(ROUND(Costs!G91/(1-40%),0)*INDEX(fx,MATCH($C$3,currency,0)),"") -> 0 | H63: =IFERROR(ROUND(Costs!H91/(1-40%),0)*INDEX(fx,MATCH($C$3,currency,0)),"") -> 0 | I63: =IFERROR(ROUND(Costs!I91/(1-40%),0)*INDEX(fx,MATCH($C$3,currency,0)),"") -> 0 | J63: =IFERROR(ROUND(Costs!J91/(1-40%),0)*INDEX(fx,MATCH($C$3,currency,0)),"") -> 0 | ... P63: =IFERROR(ROUND(Costs!P91/(1-40%),0)*INDEX(fx,MATCH($C$3,currency,0)),"") -> 0
B68: SDAIA Price | C68: US | D68: UK | E68: DE | F68: PL | G68: NL | H68: MX | I68: IN | J68: EG | K68: CAN | L68: AU | M68: AE | N68: SG | O68: VN | P68: SA
B69: Jr. Engineer | C69: =IFERROR(ROUND(Costs!C97/(1-40%),0)*INDEX(fx,MATCH($C$3,currency,0)),"") -> 0 | D69: =IFERROR(ROUND(Costs!D97/(1-40%),0)*INDEX(fx,MATCH($C$3,currency,0)),"") -> 0 | E69: =IFERROR(ROUND(Costs!E97/(1-40%),0)*INDEX(fx,MATCH($C$3,currency,0)),"") -> 0 | F69: =IFERROR(ROUND(Costs!F97/(1-40%),0)*INDEX(fx,MATCH($C$3,currency,0)),"") -> 0 | G69: =IFERROR(ROUND(Costs!G97/(1-40%),0)*INDEX(fx,MATCH($C$3,currency,0)),"") -> 0 | H69: =IFERROR(ROUND(Costs!H97/(1-40%),0)*INDEX(fx,MATCH($C$3,currency,0)),"") -> 0 | I69: =IFERROR(ROUND(Costs!I97/(1-40%),0)*INDEX(fx,MATCH($C$3,currency,0)),"") -> 0 | J69: =IFERROR(ROUND(Costs!J97/(1-40%),0)*INDEX(fx,MATCH($C$3,currency,0)),"") -> 0 | ... P69: =IFERROR(ROUND(Costs!P97/(1-40%),0)*INDEX(fx,MATCH($C$3,currency,0)),"") -> 0
B70: Engineer | C70: =IFERROR(ROUND(Costs!C98/(1-40%),0)*INDEX(fx,MATCH($C$3,currency,0)),"") -> 0 | D70: =IFERROR(ROUND(Costs!D98/(1-40%),0)*INDEX(fx,MATCH($C$3,currency,0)),"") -> 0 | E70: =IFERROR(ROUND(Costs!E98/(1-40%),0)*INDEX(fx,MATCH($C$3,currency,0)),"") -> 0 | F70: =IFERROR(ROUND(Costs!F98/(1-40%),0)*INDEX(fx,MATCH($C$3,currency,0)),"") -> 0 | G70: =IFERROR(ROUND(Costs!G98/(1-40%),0)*INDEX(fx,MATCH($C$3,currency,0)),"") -> 0 | H70: =IFERROR(ROUND(Costs!H98/(1-40%),0)*INDEX(fx,MATCH($C$3,currency,0)),"") -> 0 | I70: =IFERROR(ROUND(Costs!I98/(1-40%),0)*INDEX(fx,MATCH($C$3,currency,0)),"") -> 42 | J70: =IFERROR(ROUND(Costs!J98/(1-40%),0)*INDEX(fx,MATCH($C$3,currency,0)),"") -> 0 | ... P70: =IFERROR(ROUND(Costs!P98/(1-40%),0)*INDEX(fx,MATCH($C$3,currency,0)),"") -> 0
B71: Sr. Engineer | C71: =IFERROR(ROUND(Costs!C99/(1-40%),0)*INDEX(fx,MATCH($C$3,currency,0)),"") -> 148 | D71: =IFERROR(ROUND(Costs!D99/(1-40%),0)*INDEX(fx,MATCH($C$3,currency,0)),"") -> 0 | E71: =IFERROR(ROUND(Costs!E99/(1-40%),0)*INDEX(fx,MATCH($C$3,currency,0)),"") -> 0 | F71: =IFERROR(ROUND(Costs!F99/(1-40%),0)*INDEX(fx,MATCH($C$3,currency,0)),"") -> 0 | G71: =IFERROR(ROUND(Costs!G99/(1-40%),0)*INDEX(fx,MATCH($C$3,currency,0)),"") -> 0 | H71: =IFERROR(ROUND(Costs!H99/(1-40%),0)*INDEX(fx,MATCH($C$3,currency,0)),"") -> 0 | I71: =IFERROR(ROUND(Costs!I99/(1-40%),0)*INDEX(fx,MATCH($C$3,currency,0)),"") -> 72 | J71: =IFERROR(ROUND(Costs!J99/(1-40%),0)*INDEX(fx,MATCH($C$3,currency,0)),"") -> 0 | ... P71: =IFERROR(ROUND(Costs!P99/(1-40%),0)*INDEX(fx,MATCH($C$3,currency,0)),"") -> 0
B72: Architect | C72: =IFERROR(ROUND(Costs!C100/(1-40%),0)*INDEX(fx,MATCH($C$3,currency,0)),"") -> 0 | D72: =IFERROR(ROUND(Costs!D100/(1-40%),0)*INDEX(fx,MATCH($C$3,currency,0)),"") -> 0 | E72: =IFERROR(ROUND(Costs!E100/(1-40%),0)*INDEX(fx,MATCH($C$3,currency,0)),"") -> 0 | F72: =IFERROR(ROUND(Costs!F100/(1-40%),0)*INDEX(fx,MATCH($C$3,currency,0)),"") -> 0 | G72: =IFERROR(ROUND(Costs!G100/(1-40%),0)*INDEX(fx,MATCH($C$3,currency,0)),"") -> 0 | H72: =IFERROR(ROUND(Costs!H100/(1-40%),0)*INDEX(fx,MATCH($C$3,currency,0)),"") -> 0 | I72: =IFERROR(ROUND(Costs!I100/(1-40%),0)*INDEX(fx,MATCH($C$3,currency,0)),"") -> 0 | J72: =IFERROR(ROUND(Costs!J100/(1-40%),0)*INDEX(fx,MATCH($C$3,currency,0)),"") -> 0 | ... P72: =IFERROR(ROUND(Costs!P100/(1-40%),0)*INDEX(fx,MATCH($C$3,currency,0)),"") -> 0
B73: Sr. Architect | C73: =IFERROR(ROUND(Costs!C101/(1-40%),0)*INDEX(fx,MATCH($C$3,currency,0)),"") -> 0 | D73: =IFERROR(ROUND(Costs!D101/(1-40%),0)*INDEX(fx,MATCH($C$3,currency,0)),"") -> 0 | E73: =IFERROR(ROUND(Costs!E101/(1-40%),0)*INDEX(fx,MATCH($C$3,currency,0)),"") -> 0 | F73: =IFERROR(ROUND(Costs!F101/(1-40%),0)*INDEX(fx,MATCH($C$3,currency,0)),"") -> 0 | G73: =IFERROR(ROUND(Costs!G101/(1-40%),0)*INDEX(fx,MATCH($C$3,currency,0)),"") -> 0 | H73: =IFERROR(ROUND(Costs!H101/(1-40%),0)*INDEX(fx,MATCH($C$3,currency,0)),"") -> 0 | I73: =IFERROR(ROUND(Costs!I101/(1-40%),0)*INDEX(fx,MATCH($C$3,currency,0)),"") -> 78 | J73: =IFERROR(ROUND(Costs!J101/(1-40%),0)*INDEX(fx,MATCH($C$3,currency,0)),"") -> 0 | ... P73: =IFERROR(ROUND(Costs!P101/(1-40%),0)*INDEX(fx,MATCH($C$3,currency,0)),"") -> 0
B74: Consultant | C74: =IFERROR(ROUND(Costs!C102/(1-40%),0)*INDEX(fx,MATCH($C$3,currency,0)),"") -> 0 | D74: =IFERROR(ROUND(Costs!D102/(1-40%),0)*INDEX(fx,MATCH($C$3,currency,0)),"") -> 0 | E74: =IFERROR(ROUND(Costs!E102/(1-40%),0)*INDEX(fx,MATCH($C$3,currency,0)),"") -> 0 | F74: =IFERROR(ROUND(Costs!F102/(1-40%),0)*INDEX(fx,MATCH($C$3,currency,0)),"") -> 0 | G74: =IFERROR(ROUND(Costs!G102/(1-40%),0)*INDEX(fx,MATCH($C$3,currency,0)),"") -> 0 | H74: =IFERROR(ROUND(Costs!H102/(1-40%),0)*INDEX(fx,MATCH($C$3,currency,0)),"") -> 0 | I74: =IFERROR(ROUND(Costs!I102/(1-40%),0)*INDEX(fx,MATCH($C$3,currency,0)),"") -> 0 | J74: =IFERROR(ROUND(Costs!J102/(1-40%),0)*INDEX(fx,MATCH($C$3,currency,0)),"") -> 0 | ... P74: =IFERROR(ROUND(Costs!P102/(1-40%),0)*INDEX(fx,MATCH($C$3,currency,0)),"") -> 0
B75: Sr. Consultant | C75: =IFERROR(ROUND(Costs!C103/(1-40%),0)*INDEX(fx,MATCH($C$3,currency,0)),"") -> 0 | D75: =IFERROR(ROUND(Costs!D103/(1-40%),0)*INDEX(fx,MATCH($C$3,currency,0)),"") -> 0 | E75: =IFERROR(ROUND(Costs!E103/(1-40%),0)*INDEX(fx,MATCH($C$3,currency,0)),"") -> 0 | F75: =IFERROR(ROUND(Costs!F103/(1-40%),0)*INDEX(fx,MATCH($C$3,currency,0)),"") -> 0 | G75: =IFERROR(ROUND(Costs!G103/(1-40%),0)*INDEX(fx,MATCH($C$3,currency,0)),"") -> 0 | H75: =IFERROR(ROUND(Costs!H103/(1-40%),0)*INDEX(fx,MATCH($C$3,currency,0)),"") -> 0 | I75: =IFERROR(ROUND(Costs!I103/(1-40%),0)*INDEX(fx,MATCH($C$3,currency,0)),"") -> 0 | J75: =IFERROR(ROUND(Costs!J103/(1-40%),0)*INDEX(fx,MATCH($C$3,currency,0)),"") -> 0 | ... P75: =IFERROR(ROUND(Costs!P103/(1-40%),0)*INDEX(fx,MATCH($C$3,currency,0)),"") -> 0
B76: Developer | C76: =IFERROR(ROUND(Costs!C104/(1-40%),0)*INDEX(fx,MATCH($C$3,currency,0)),"") -> 0 | D76: =IFERROR(ROUND(Costs!D104/(1-40%),0)*INDEX(fx,MATCH($C$3,currency,0)),"") -> 0 | E76: =IFERROR(ROUND(Costs!E104/(1-40%),0)*INDEX(fx,MATCH($C$3,currency,0)),"") -> 0 | F76: =IFERROR(ROUND(Costs!F104/(1-40%),0)*INDEX(fx,MATCH($C$3,currency,0)),"") -> 0 | G76: =IFERROR(ROUND(Costs!G104/(1-40%),0)*INDEX(fx,MATCH($C$3,currency,0)),"") -> 0 | H76: =IFERROR(ROUND(Costs!H104/(1-40%),0)*INDEX(fx,MATCH($C$3,currency,0)),"") -> 0 | I76: =IFERROR(ROUND(Costs!I104/(1-40%),0)*INDEX(fx,MATCH($C$3,currency,0)),"") -> 0 | J76: =IFERROR(ROUND(Costs!J104/(1-40%),0)*INDEX(fx,MATCH($C$3,currency,0)),"") -> 0 | ... P76: =IFERROR(ROUND(Costs!P104/(1-40%),0)*INDEX(fx,MATCH($C$3,currency,0)),"") -> 0
B77: Project Coordinator | C77: =IFERROR(ROUND(Costs!C105/(1-40%),0)*INDEX(fx,MATCH($C$3,currency,0)),"") -> 0 | D77: =IFERROR(ROUND(Costs!D105/(1-40%),0)*INDEX(fx,MATCH($C$3,currency,0)),"") -> 0 | E77: =IFERROR(ROUND(Costs!E105/(1-40%),0)*INDEX(fx,MATCH($C$3,currency,0)),"") -> 0 | F77: =IFERROR(ROUND(Costs!F105/(1-40%),0)*INDEX(fx,MATCH($C$3,currency,0)),"") -> 0 | G77: =IFERROR(ROUND(Costs!G105/(1-40%),0)*INDEX(fx,MATCH($C$3,currency,0)),"") -> 0 | H77: =IFERROR(ROUND(Costs!H105/(1-40%),0)*INDEX(fx,MATCH($C$3,currency,0)),"") -> 0 | I77: =IFERROR(ROUND(Costs!I105/(1-40%),0)*INDEX(fx,MATCH($C$3,currency,0)),"") -> 0 | J77: =IFERROR(ROUND(Costs!J105/(1-40%),0)*INDEX(fx,MATCH($C$3,currency,0)),"") -> 0 | ... P77: =IFERROR(ROUND(Costs!P105/(1-40%),0)*INDEX(fx,MATCH($C$3,currency,0)),"") -> 85
B78: Project Mgr | C78: =IFERROR(ROUND(Costs!C106/(1-40%),0)*INDEX(fx,MATCH($C$3,currency,0)),"") -> 0 | D78: =IFERROR(ROUND(Costs!D106/(1-40%),0)*INDEX(fx,MATCH($C$3,currency,0)),"") -> 0 | E78: =IFERROR(ROUND(Costs!E106/(1-40%),0)*INDEX(fx,MATCH($C$3,currency,0)),"") -> 0 | F78: =IFERROR(ROUND(Costs!F106/(1-40%),0)*INDEX(fx,MATCH($C$3,currency,0)),"") -> 0 | G78: =IFERROR(ROUND(Costs!G106/(1-40%),0)*INDEX(fx,MATCH($C$3,currency,0)),"") -> 0 | H78: =IFERROR(ROUND(Costs!H106/(1-40%),0)*INDEX(fx,MATCH($C$3,currency,0)),"") -> 0 | I78: =IFERROR(ROUND(Costs!I106/(1-40%),0)*INDEX(fx,MATCH($C$3,currency,0)),"") -> 0 | J78: =IFERROR(ROUND(Costs!J106/(1-40%),0)*INDEX(fx,MATCH($C$3,currency,0)),"") -> 0 | ... P78: =IFERROR(ROUND(Costs!P106/(1-40%),0)*INDEX(fx,MATCH($C$3,currency,0)),"") -> 0
B79: Sr. Proj Mgr | C79: =IFERROR(ROUND(Costs!C107/(1-40%),0)*INDEX(fx,MATCH($C$3,currency,0)),"") -> 0 | D79: =IFERROR(ROUND(Costs!D107/(1-40%),0)*INDEX(fx,MATCH($C$3,currency,0)),"") -> 0 | E79: =IFERROR(ROUND(Costs!E107/(1-40%),0)*INDEX(fx,MATCH($C$3,currency,0)),"") -> 0 | F79: =IFERROR(ROUND(Costs!F107/(1-40%),0)*INDEX(fx,MATCH($C$3,currency,0)),"") -> 0 | G79: =IFERROR(ROUND(Costs!G107/(1-40%),0)*INDEX(fx,MATCH($C$3,currency,0)),"") -> 0 | H79: =IFERROR(ROUND(Costs!H107/(1-40%),0)*INDEX(fx,MATCH($C$3,currency,0)),"") -> 0 | I79: =IFERROR(ROUND(Costs!I107/(1-40%),0)*INDEX(fx,MATCH($C$3,currency,0)),"") -> 0 | J79: =IFERROR(ROUND(Costs!J107/(1-40%),0)*INDEX(fx,MATCH($C$3,currency,0)),"") -> 0 | ... P79: =IFERROR(ROUND(Costs!P107/(1-40%),0)*INDEX(fx,MATCH($C$3,currency,0)),"") -> 162
B80: Prog Mgr | C80: =IFERROR(ROUND(Costs!C108/(1-40%),0)*INDEX(fx,MATCH($C$3,currency,0)),"") -> 0 | D80: =IFERROR(ROUND(Costs!D108/(1-40%),0)*INDEX(fx,MATCH($C$3,currency,0)),"") -> 0 | E80: =IFERROR(ROUND(Costs!E108/(1-40%),0)*INDEX(fx,MATCH($C$3,currency,0)),"") -> 0 | F80: =IFERROR(ROUND(Costs!F108/(1-40%),0)*INDEX(fx,MATCH($C$3,currency,0)),"") -> 0 | G80: =IFERROR(ROUND(Costs!G108/(1-40%),0)*INDEX(fx,MATCH($C$3,currency,0)),"") -> 0 | H80: =IFERROR(ROUND(Costs!H108/(1-40%),0)*INDEX(fx,MATCH($C$3,currency,0)),"") -> 0 | I80: =IFERROR(ROUND(Costs!I108/(1-40%),0)*INDEX(fx,MATCH($C$3,currency,0)),"") -> 0 | J80: =IFERROR(ROUND(Costs!J108/(1-40%),0)*INDEX(fx,MATCH($C$3,currency,0)),"") -> 0 | ... P80: =IFERROR(ROUND(Costs!P108/(1-40%),0)*INDEX(fx,MATCH($C$3,currency,0)),"") -> 320
B85: ERP Price | C85: US | D85: UK | E85: DE | F85: PL | G85: NL | H85: MX | I85: IN | J85: EG | K85: CAN | L85: AU | M85: AE | N85: SG | O85: VN | P85: SA
B86: Jr. Engineer | C86: =IFERROR(ROUND(Costs!C114/(1-40%),0)*INDEX(fx,MATCH($C$3,currency,0)),"") -> 0 | D86: =IFERROR(ROUND(Costs!D114/(1-40%),0)*INDEX(fx,MATCH($C$3,currency,0)),"") -> 0 | E86: =IFERROR(ROUND(Costs!E114/(1-40%),0)*INDEX(fx,MATCH($C$3,currency,0)),"") -> 0 | F86: =IFERROR(ROUND(Costs!F114/(1-40%),0)*INDEX(fx,MATCH($C$3,currency,0)),"") -> 0 | G86: =IFERROR(ROUND(Costs!G114/(1-40%),0)*INDEX(fx,MATCH($C$3,currency,0)),"") -> 0 | H86: =IFERROR(ROUND(Costs!H114/(1-40%),0)*INDEX(fx,MATCH($C$3,currency,0)),"") -> 0 | I86: =IFERROR(ROUND(Costs!I114/(1-40%),0)*INDEX(fx,MATCH($C$3,currency,0)),"") -> 0 | J86: =IFERROR(ROUND(Costs!J114/(1-40%),0)*INDEX(fx,MATCH($C$3,currency,0)),"") -> 0 | ... P86: =IFERROR(ROUND(Costs!P114/(1-40%),0)*INDEX(fx,MATCH($C$3,currency,0)),"") -> 0
B87: Engineer | C87: =IFERROR(ROUND(Costs!C115/(1-40%),0)*INDEX(fx,MATCH($C$3,currency,0)),"") -> 0 | D87: =IFERROR(ROUND(Costs!D115/(1-40%),0)*INDEX(fx,MATCH($C$3,currency,0)),"") -> 0 | E87: =IFERROR(ROUND(Costs!E115/(1-40%),0)*INDEX(fx,MATCH($C$3,currency,0)),"") -> 0 | F87: =IFERROR(ROUND(Costs!F115/(1-40%),0)*INDEX(fx,MATCH($C$3,currency,0)),"") -> 0 | G87: =IFERROR(ROUND(Costs!G115/(1-40%),0)*INDEX(fx,MATCH($C$3,currency,0)),"") -> 0 | H87: =IFERROR(ROUND(Costs!H115/(1-40%),0)*INDEX(fx,MATCH($C$3,currency,0)),"") -> 0 | I87: =IFERROR(ROUND(Costs!I115/(1-40%),0)*INDEX(fx,MATCH($C$3,currency,0)),"") -> 0 | J87: =IFERROR(ROUND(Costs!J115/(1-40%),0)*INDEX(fx,MATCH($C$3,currency,0)),"") -> 0 | ... P87: =IFERROR(ROUND(Costs!P115/(1-40%),0)*INDEX(fx,MATCH($C$3,currency,0)),"") -> 0
B88: Sr. Engineer | C88: =IFERROR(ROUND(Costs!C116/(1-40%),0)*INDEX(fx,MATCH($C$3,currency,0)),"") -> 0 | D88: =IFERROR(ROUND(Costs!D116/(1-40%),0)*INDEX(fx,MATCH($C$3,currency,0)),"") -> 0 | E88: =IFERROR(ROUND(Costs!E116/(1-40%),0)*INDEX(fx,MATCH($C$3,currency,0)),"") -> 0 | F88: =IFERROR(ROUND(Costs!F116/(1-40%),0)*INDEX(fx,MATCH($C$3,currency,0)),"") -> 0 | G88: =IFERROR(ROUND(Costs!G116/(1-40%),0)*INDEX(fx,MATCH($C$3,currency,0)),"") -> 0 | H88: =IFERROR(ROUND(Costs!H116/(1-40%),0)*INDEX(fx,MATCH($C$3,currency,0)),"") -> 0 | I88: =IFERROR(ROUND(Costs!I116/(1-40%),0)*INDEX(fx,MATCH($C$3,currency,0)),"") -> 0 | J88: =IFERROR(ROUND(Costs!J116/(1-40%),0)*INDEX(fx,MATCH($C$3,currency,0)),"") -> 0 | ... P88: =IFERROR(ROUND(Costs!P116/(1-40%),0)*INDEX(fx,MATCH($C$3,currency,0)),"") -> 0
B89: Architect | C89: =IFERROR(ROUND(Costs!C117/(1-40%),0)*INDEX(fx,MATCH($C$3,currency,0)),"") -> 0 | D89: =IFERROR(ROUND(Costs!D117/(1-40%),0)*INDEX(fx,MATCH($C$3,currency,0)),"") -> 0 | E89: =IFERROR(ROUND(Costs!E117/(1-40%),0)*INDEX(fx,MATCH($C$3,currency,0)),"") -> 0 | F89: =IFERROR(ROUND(Costs!F117/(1-40%),0)*INDEX(fx,MATCH($C$3,currency,0)),"") -> 0 | G89: =IFERROR(ROUND(Costs!G117/(1-40%),0)*INDEX(fx,MATCH($C$3,currency,0)),"") -> 0 | H89: =IFERROR(ROUND(Costs!H117/(1-40%),0)*INDEX(fx,MATCH($C$3,currency,0)),"") -> 0 | I89: =IFERROR(ROUND(Costs!I117/(1-40%),0)*INDEX(fx,MATCH($C$3,currency,0)),"") -> 0 | J89: =IFERROR(ROUND(Costs!J117/(1-40%),0)*INDEX(fx,MATCH($C$3,currency,0)),"") -> 0 | ... P89: =IFERROR(ROUND(Costs!P117/(1-40%),0)*INDEX(fx,MATCH($C$3,currency,0)),"") -> 0
B90: Sr. Architect | C90: =IFERROR(ROUND(Costs!C118/(1-40%),0)*INDEX(fx,MATCH($C$3,currency,0)),"") -> 0 | D90: =IFERROR(ROUND(Costs!D118/(1-40%),0)*INDEX(fx,MATCH($C$3,currency,0)),"") -> 0 | E90: =IFERROR(ROUND(Costs!E118/(1-40%),0)*INDEX(fx,MATCH($C$3,currency,0)),"") -> 0 | F90: =IFERROR(ROUND(Costs!F118/(1-40%),0)*INDEX(fx,MATCH($C$3,currency,0)),"") -> 0 | G90: =IFERROR(ROUND(Costs!G118/(1-40%),0)*INDEX(fx,MATCH($C$3,currency,0)),"") -> 0 | H90: =IFERROR(ROUND(Costs!H118/(1-40%),0)*INDEX(fx,MATCH($C$3,currency,0)),"") -> 158 | I90: =IFERROR(ROUND(Costs!I118/(1-40%),0)*INDEX(fx,MATCH($C$3,currency,0)),"") -> 0 | J90: =IFERROR(ROUND(Costs!J118/(1-40%),0)*INDEX(fx,MATCH($C$3,currency,0)),"") -> 0 | ... P90: =IFERROR(ROUND(Costs!P118/(1-40%),0)*INDEX(fx,MATCH($C$3,currency,0)),"") -> 0
B91: Consultant | C91: =IFERROR(ROUND(Costs!C119/(1-40%),0)*INDEX(fx,MATCH($C$3,currency,0)),"") -> 147 | D91: =IFERROR(ROUND(Costs!D119/(1-40%),0)*INDEX(fx,MATCH($C$3,currency,0)),"") -> 0 | E91: =IFERROR(ROUND(Costs!E119/(1-40%),0)*INDEX(fx,MATCH($C$3,currency,0)),"") -> 0 | F91: =IFERROR(ROUND(Costs!F119/(1-40%),0)*INDEX(fx,MATCH($C$3,currency,0)),"") -> 0 | G91: =IFERROR(ROUND(Costs!G119/(1-40%),0)*INDEX(fx,MATCH($C$3,currency,0)),"") -> 0 | H91: =IFERROR(ROUND(Costs!H119/(1-40%),0)*INDEX(fx,MATCH($C$3,currency,0)),"") -> 0 | I91: =IFERROR(ROUND(Costs!I119/(1-40%),0)*INDEX(fx,MATCH($C$3,currency,0)),"") -> 30 | J91: =IFERROR(ROUND(Costs!J119/(1-40%),0)*INDEX(fx,MATCH($C$3,currency,0)),"") -> 0 | ... P91: =IFERROR(ROUND(Costs!P119/(1-40%),0)*INDEX(fx,MATCH($C$3,currency,0)),"") -> 0
B92: Sr. Consultant | C92: =IFERROR(ROUND(Costs!C120/(1-40%),0)*INDEX(fx,MATCH($C$3,currency,0)),"") -> 227 | D92: =IFERROR(ROUND(Costs!D120/(1-40%),0)*INDEX(fx,MATCH($C$3,currency,0)),"") -> 0 | E92: =IFERROR(ROUND(Costs!E120/(1-40%),0)*INDEX(fx,MATCH($C$3,currency,0)),"") -> 0 | F92: =IFERROR(ROUND(Costs!F120/(1-40%),0)*INDEX(fx,MATCH($C$3,currency,0)),"") -> 0 | G92: =IFERROR(ROUND(Costs!G120/(1-40%),0)*INDEX(fx,MATCH($C$3,currency,0)),"") -> 0 | H92: =IFERROR(ROUND(Costs!H120/(1-40%),0)*INDEX(fx,MATCH($C$3,currency,0)),"") -> 0 | I92: =IFERROR(ROUND(Costs!I120/(1-40%),0)*INDEX(fx,MATCH($C$3,currency,0)),"") -> 57 | J92: =IFERROR(ROUND(Costs!J120/(1-40%),0)*INDEX(fx,MATCH($C$3,currency,0)),"") -> 0 | ... P92: =IFERROR(ROUND(Costs!P120/(1-40%),0)*INDEX(fx,MATCH($C$3,currency,0)),"") -> 0
B93: Developer | C93: =IFERROR(ROUND(Costs!C121/(1-40%),0)*INDEX(fx,MATCH($C$3,currency,0)),"") -> 135 | D93: =IFERROR(ROUND(Costs!D121/(1-40%),0)*INDEX(fx,MATCH($C$3,currency,0)),"") -> 0 | E93: =IFERROR(ROUND(Costs!E121/(1-40%),0)*INDEX(fx,MATCH($C$3,currency,0)),"") -> 0 | F93: =IFERROR(ROUND(Costs!F121/(1-40%),0)*INDEX(fx,MATCH($C$3,currency,0)),"") -> 0 | G93: =IFERROR(ROUND(Costs!G121/(1-40%),0)*INDEX(fx,MATCH($C$3,currency,0)),"") -> 0 | H93: =IFERROR(ROUND(Costs!H121/(1-40%),0)*INDEX(fx,MATCH($C$3,currency,0)),"") -> 0 | I93: =IFERROR(ROUND(Costs!I121/(1-40%),0)*INDEX(fx,MATCH($C$3,currency,0)),"") -> 0 | J93: =IFERROR(ROUND(Costs!J121/(1-40%),0)*INDEX(fx,MATCH($C$3,currency,0)),"") -> 0 | ... P93: =IFERROR(ROUND(Costs!P121/(1-40%),0)*INDEX(fx,MATCH($C$3,currency,0)),"") -> 0
B94: Project Coordinator | C94: =IFERROR(ROUND(Costs!C122/(1-40%),0)*INDEX(fx,MATCH($C$3,currency,0)),"") -> 0 | D94: =IFERROR(ROUND(Costs!D122/(1-40%),0)*INDEX(fx,MATCH($C$3,currency,0)),"") -> 0 | E94: =IFERROR(ROUND(Costs!E122/(1-40%),0)*INDEX(fx,MATCH($C$3,currency,0)),"") -> 0 | F94: =IFERROR(ROUND(Costs!F122/(1-40%),0)*INDEX(fx,MATCH($C$3,currency,0)),"") -> 0 | G94: =IFERROR(ROUND(Costs!G122/(1-40%),0)*INDEX(fx,MATCH($C$3,currency,0)),"") -> 0 | H94: =IFERROR(ROUND(Costs!H122/(1-40%),0)*INDEX(fx,MATCH($C$3,currency,0)),"") -> 0 | I94: =IFERROR(ROUND(Costs!I122/(1-40%),0)*INDEX(fx,MATCH($C$3,currency,0)),"") -> 0 | J94: =IFERROR(ROUND(Costs!J122/(1-40%),0)*INDEX(fx,MATCH($C$3,currency,0)),"") -> 0 | ... P94: =IFERROR(ROUND(Costs!P122/(1-40%),0)*INDEX(fx,MATCH($C$3,currency,0)),"") -> 0
B95: Project Mgr | C95: =IFERROR(ROUND(Costs!C123/(1-40%),0)*INDEX(fx,MATCH($C$3,currency,0)),"") -> 0 | D95: =IFERROR(ROUND(Costs!D123/(1-40%),0)*INDEX(fx,MATCH($C$3,currency,0)),"") -> 0 | E95: =IFERROR(ROUND(Costs!E123/(1-40%),0)*INDEX(fx,MATCH($C$3,currency,0)),"") -> 0 | F95: =IFERROR(ROUND(Costs!F123/(1-40%),0)*INDEX(fx,MATCH($C$3,currency,0)),"") -> 0 | G95: =IFERROR(ROUND(Costs!G123/(1-40%),0)*INDEX(fx,MATCH($C$3,currency,0)),"") -> 0 | H95: =IFERROR(ROUND(Costs!H123/(1-40%),0)*INDEX(fx,MATCH($C$3,currency,0)),"") -> 0 | I95: =IFERROR(ROUND(Costs!I123/(1-40%),0)*INDEX(fx,MATCH($C$3,currency,0)),"") -> 0 | J95: =IFERROR(ROUND(Costs!J123/(1-40%),0)*INDEX(fx,MATCH($C$3,currency,0)),"") -> 0 | ... P95: =IFERROR(ROUND(Costs!P123/(1-40%),0)*INDEX(fx,MATCH($C$3,currency,0)),"") -> 0
B96: Sr. Proj Mgr | C96: =IFERROR(ROUND(Costs!C124/(1-40%),0)*INDEX(fx,MATCH($C$3,currency,0)),"") -> 0 | D96: =IFERROR(ROUND(Costs!D124/(1-40%),0)*INDEX(fx,MATCH($C$3,currency,0)),"") -> 0 | E96: =IFERROR(ROUND(Costs!E124/(1-40%),0)*INDEX(fx,MATCH($C$3,currency,0)),"") -> 0 | F96: =IFERROR(ROUND(Costs!F124/(1-40%),0)*INDEX(fx,MATCH($C$3,currency,0)),"") -> 0 | G96: =IFERROR(ROUND(Costs!G124/(1-40%),0)*INDEX(fx,MATCH($C$3,currency,0)),"") -> 0 | H96: =IFERROR(ROUND(Costs!H124/(1-40%),0)*INDEX(fx,MATCH($C$3,currency,0)),"") -> 0 | I96: =IFERROR(ROUND(Costs!I124/(1-40%),0)*INDEX(fx,MATCH($C$3,currency,0)),"") -> 0 | J96: =IFERROR(ROUND(Costs!J124/(1-40%),0)*INDEX(fx,MATCH($C$3,currency,0)),"") -> 0 | ... P96: =IFERROR(ROUND(Costs!P124/(1-40%),0)*INDEX(fx,MATCH($C$3,currency,0)),"") -> 0
B97: Prog Mgr | C97: =IFERROR(ROUND(Costs!C125/(1-40%),0)*INDEX(fx,MATCH($C$3,currency,0)),"") -> 235 | D97: =IFERROR(ROUND(Costs!D125/(1-40%),0)*INDEX(fx,MATCH($C$3,currency,0)),"") -> 0 | E97: =IFERROR(ROUND(Costs!E125/(1-40%),0)*INDEX(fx,MATCH($C$3,currency,0)),"") -> 0 | F97: =IFERROR(ROUND(Costs!F125/(1-40%),0)*INDEX(fx,MATCH($C$3,currency,0)),"") -> 0 | G97: =IFERROR(ROUND(Costs!G125/(1-40%),0)*INDEX(fx,MATCH($C$3,currency,0)),"") -> 0 | H97: =IFERROR(ROUND(Costs!H125/(1-40%),0)*INDEX(fx,MATCH($C$3,currency,0)),"") -> 0 | I97: =IFERROR(ROUND(Costs!I125/(1-40%),0)*INDEX(fx,MATCH($C$3,currency,0)),"") -> 0 | J97: =IFERROR(ROUND(Costs!J125/(1-40%),0)*INDEX(fx,MATCH($C$3,currency,0)),"") -> 0 | ... P97: =IFERROR(ROUND(Costs!P125/(1-40%),0)*INDEX(fx,MATCH($C$3,currency,0)),"") -> 0
B101: HealthCare PS Price | C101: US | D101: UK | E101: DE | F101: PL | G101: NL | H101: MX | I101: IN | J101: EG | K101: CAN | L101: AU | M101: AE | N101: SG | O101: VN | P101: SA
B102: WSS Eng | C102: =IFERROR(ROUND(Costs!C129/(1-40%),0)*INDEX(fx,MATCH($C$3,currency,0)),"") -> 197 | D102: =IFERROR(ROUND(Costs!D129/(1-40%),0)*INDEX(fx,MATCH($C$3,currency,0)),"") -> 0 | E102: =IFERROR(ROUND(Costs!E129/(1-40%),0)*INDEX(fx,MATCH($C$3,currency,0)),"") -> 0 | F102: =IFERROR(ROUND(Costs!F129/(1-40%),0)*INDEX(fx,MATCH($C$3,currency,0)),"") -> 0 | G102: =IFERROR(ROUND(Costs!G129/(1-40%),0)*INDEX(fx,MATCH($C$3,currency,0)),"") -> 0 | H102: =IFERROR(ROUND(Costs!H129/(1-40%),0)*INDEX(fx,MATCH($C$3,currency,0)),"") -> 0 | I102: =IFERROR(ROUND(Costs!I129/(1-40%),0)*INDEX(fx,MATCH($C$3,currency,0)),"") -> 0 | J102: =IFERROR(ROUND(Costs!J129/(1-40%),0)*INDEX(fx,MATCH($C$3,currency,0)),"") -> 0 | ... P102: =IFERROR(ROUND(Costs!P129/(1-40%),0)*INDEX(fx,MATCH($C$3,currency,0)),"") -> 0
B103: WSS Sr. Eng | C103: =IFERROR(ROUND(Costs!C130/(1-40%),0)*INDEX(fx,MATCH($C$3,currency,0)),"") -> 225 | D103: =IFERROR(ROUND(Costs!D130/(1-40%),0)*INDEX(fx,MATCH($C$3,currency,0)),"") -> 0 | E103: =IFERROR(ROUND(Costs!E130/(1-40%),0)*INDEX(fx,MATCH($C$3,currency,0)),"") -> 0 | F103: =IFERROR(ROUND(Costs!F130/(1-40%),0)*INDEX(fx,MATCH($C$3,currency,0)),"") -> 0 | G103: =IFERROR(ROUND(Costs!G130/(1-40%),0)*INDEX(fx,MATCH($C$3,currency,0)),"") -> 0 | H103: =IFERROR(ROUND(Costs!H130/(1-40%),0)*INDEX(fx,MATCH($C$3,currency,0)),"") -> 0 | I103: =IFERROR(ROUND(Costs!I130/(1-40%),0)*INDEX(fx,MATCH($C$3,currency,0)),"") -> 0 | J103: =IFERROR(ROUND(Costs!J130/(1-40%),0)*INDEX(fx,MATCH($C$3,currency,0)),"") -> 0 | ... P103: =IFERROR(ROUND(Costs!P130/(1-40%),0)*INDEX(fx,MATCH($C$3,currency,0)),"") -> 0
B104: Cogito Eng | C104: =IFERROR(ROUND(Costs!C131/(1-40%),0)*INDEX(fx,MATCH($C$3,currency,0)),"") -> 198 | D104: =IFERROR(ROUND(Costs!D131/(1-40%),0)*INDEX(fx,MATCH($C$3,currency,0)),"") -> 0 | E104: =IFERROR(ROUND(Costs!E131/(1-40%),0)*INDEX(fx,MATCH($C$3,currency,0)),"") -> 0 | F104: =IFERROR(ROUND(Costs!F131/(1-40%),0)*INDEX(fx,MATCH($C$3,currency,0)),"") -> 0 | G104: =IFERROR(ROUND(Costs!G131/(1-40%),0)*INDEX(fx,MATCH($C$3,currency,0)),"") -> 0 | H104: =IFERROR(ROUND(Costs!H131/(1-40%),0)*INDEX(fx,MATCH($C$3,currency,0)),"") -> 0 | I104: =IFERROR(ROUND(Costs!I131/(1-40%),0)*INDEX(fx,MATCH($C$3,currency,0)),"") -> 0 | J104: =IFERROR(ROUND(Costs!J131/(1-40%),0)*INDEX(fx,MATCH($C$3,currency,0)),"") -> 0 | ... P104: =IFERROR(ROUND(Costs!P131/(1-40%),0)*INDEX(fx,MATCH($C$3,currency,0)),"") -> 0
B105: Cogito Sr. Eng | C105: =IFERROR(ROUND(Costs!C132/(1-40%),0)*INDEX(fx,MATCH($C$3,currency,0)),"") -> 252 | D105: =IFERROR(ROUND(Costs!D132/(1-40%),0)*INDEX(fx,MATCH($C$3,currency,0)),"") -> 0 | E105: =IFERROR(ROUND(Costs!E132/(1-40%),0)*INDEX(fx,MATCH($C$3,currency,0)),"") -> 0 | F105: =IFERROR(ROUND(Costs!F132/(1-40%),0)*INDEX(fx,MATCH($C$3,currency,0)),"") -> 0 | G105: =IFERROR(ROUND(Costs!G132/(1-40%),0)*INDEX(fx,MATCH($C$3,currency,0)),"") -> 0 | H105: =IFERROR(ROUND(Costs!H132/(1-40%),0)*INDEX(fx,MATCH($C$3,currency,0)),"") -> 0 | I105: =IFERROR(ROUND(Costs!I132/(1-40%),0)*INDEX(fx,MATCH($C$3,currency,0)),"") -> 0 | J105: =IFERROR(ROUND(Costs!J132/(1-40%),0)*INDEX(fx,MATCH($C$3,currency,0)),"") -> 0 | ... P105: =IFERROR(ROUND(Costs!P132/(1-40%),0)*INDEX(fx,MATCH($C$3,currency,0)),"") -> 0
B106: ODB Eng | C106: =IFERROR(ROUND(Costs!C133/(1-40%),0)*INDEX(fx,MATCH($C$3,currency,0)),"") -> 218 | D106: =IFERROR(ROUND(Costs!D133/(1-40%),0)*INDEX(fx,MATCH($C$3,currency,0)),"") -> 0 | E106: =IFERROR(ROUND(Costs!E133/(1-40%),0)*INDEX(fx,MATCH($C$3,currency,0)),"") -> 0 | F106: =IFERROR(ROUND(Costs!F133/(1-40%),0)*INDEX(fx,MATCH($C$3,currency,0)),"") -> 0 | G106: =IFERROR(ROUND(Costs!G133/(1-40%),0)*INDEX(fx,MATCH($C$3,currency,0)),"") -> 0 | H106: =IFERROR(ROUND(Costs!H133/(1-40%),0)*INDEX(fx,MATCH($C$3,currency,0)),"") -> 0 | I106: =IFERROR(ROUND(Costs!I133/(1-40%),0)*INDEX(fx,MATCH($C$3,currency,0)),"") -> 0 | J106: =IFERROR(ROUND(Costs!J133/(1-40%),0)*INDEX(fx,MATCH($C$3,currency,0)),"") -> 0 | ... P106: =IFERROR(ROUND(Costs!P133/(1-40%),0)*INDEX(fx,MATCH($C$3,currency,0)),"") -> 0
B107: ODB Sr. Eng | C107: =IFERROR(ROUND(Costs!C134/(1-40%),0)*INDEX(fx,MATCH($C$3,currency,0)),"") -> 282 | D107: =IFERROR(ROUND(Costs!D134/(1-40%),0)*INDEX(fx,MATCH($C$3,currency,0)),"") -> 0 | E107: =IFERROR(ROUND(Costs!E134/(1-40%),0)*INDEX(fx,MATCH($C$3,currency,0)),"") -> 0 | F107: =IFERROR(ROUND(Costs!F134/(1-40%),0)*INDEX(fx,MATCH($C$3,currency,0)),"") -> 0 | G107: =IFERROR(ROUND(Costs!G134/(1-40%),0)*INDEX(fx,MATCH($C$3,currency,0)),"") -> 0 | H107: =IFERROR(ROUND(Costs!H134/(1-40%),0)*INDEX(fx,MATCH($C$3,currency,0)),"") -> 0 | I107: =IFERROR(ROUND(Costs!I134/(1-40%),0)*INDEX(fx,MATCH($C$3,currency,0)),"") -> 0 | J107: =IFERROR(ROUND(Costs!J134/(1-40%),0)*INDEX(fx,MATCH($C$3,currency,0)),"") -> 0 | ... P107: =IFERROR(ROUND(Costs!P134/(1-40%),0)*INDEX(fx,MATCH($C$3,currency,0)),"") -> 0
B108: Sppt Jr. Eng | C108: =IFERROR(ROUND(Costs!C135/(1-40%),0)*INDEX(fx,MATCH($C$3,currency,0)),"") -> 200 | D108: =IFERROR(ROUND(Costs!D135/(1-40%),0)*INDEX(fx,MATCH($C$3,currency,0)),"") -> 0 | E108: =IFERROR(ROUND(Costs!E135/(1-40%),0)*INDEX(fx,MATCH($C$3,currency,0)),"") -> 0 | F108: =IFERROR(ROUND(Costs!F135/(1-40%),0)*INDEX(fx,MATCH($C$3,currency,0)),"") -> 0 | G108: =IFERROR(ROUND(Costs!G135/(1-40%),0)*INDEX(fx,MATCH($C$3,currency,0)),"") -> 0 | H108: =IFERROR(ROUND(Costs!H135/(1-40%),0)*INDEX(fx,MATCH($C$3,currency,0)),"") -> 0 | I108: =IFERROR(ROUND(Costs!I135/(1-40%),0)*INDEX(fx,MATCH($C$3,currency,0)),"") -> 0 | J108: =IFERROR(ROUND(Costs!J135/(1-40%),0)*INDEX(fx,MATCH($C$3,currency,0)),"") -> 0 | ... P108: =IFERROR(ROUND(Costs!P135/(1-40%),0)*INDEX(fx,MATCH($C$3,currency,0)),"") -> 0
B109: Sppt Eng | C109: =IFERROR(ROUND(Costs!C136/(1-40%),0)*INDEX(fx,MATCH($C$3,currency,0)),"") -> 230 | D109: =IFERROR(ROUND(Costs!D136/(1-40%),0)*INDEX(fx,MATCH($C$3,currency,0)),"") -> 0 | E109: =IFERROR(ROUND(Costs!E136/(1-40%),0)*INDEX(fx,MATCH($C$3,currency,0)),"") -> 0 | F109: =IFERROR(ROUND(Costs!F136/(1-40%),0)*INDEX(fx,MATCH($C$3,currency,0)),"") -> 0 | G109: =IFERROR(ROUND(Costs!G136/(1-40%),0)*INDEX(fx,MATCH($C$3,currency,0)),"") -> 0 | H109: =IFERROR(ROUND(Costs!H136/(1-40%),0)*INDEX(fx,MATCH($C$3,currency,0)),"") -> 0 | I109: =IFERROR(ROUND(Costs!I136/(1-40%),0)*INDEX(fx,MATCH($C$3,currency,0)),"") -> 0 | J109: =IFERROR(ROUND(Costs!J136/(1-40%),0)*INDEX(fx,MATCH($C$3,currency,0)),"") -> 0 | ... P109: =IFERROR(ROUND(Costs!P136/(1-40%),0)*INDEX(fx,MATCH($C$3,currency,0)),"") -> 0
B110: Sppt Sr. Eng | C110: =IFERROR(ROUND(Costs!C137/(1-40%),0)*INDEX(fx,MATCH($C$3,currency,0)),"") -> 253 | D110: =IFERROR(ROUND(Costs!D137/(1-40%),0)*INDEX(fx,MATCH($C$3,currency,0)),"") -> 0 | E110: =IFERROR(ROUND(Costs!E137/(1-40%),0)*INDEX(fx,MATCH($C$3,currency,0)),"") -> 0 | F110: =IFERROR(ROUND(Costs!F137/(1-40%),0)*INDEX(fx,MATCH($C$3,currency,0)),"") -> 0 | G110: =IFERROR(ROUND(Costs!G137/(1-40%),0)*INDEX(fx,MATCH($C$3,currency,0)),"") -> 0 | H110: =IFERROR(ROUND(Costs!H137/(1-40%),0)*INDEX(fx,MATCH($C$3,currency,0)),"") -> 0 | I110: =IFERROR(ROUND(Costs!I137/(1-40%),0)*INDEX(fx,MATCH($C$3,currency,0)),"") -> 0 | J110: =IFERROR(ROUND(Costs!J137/(1-40%),0)*INDEX(fx,MATCH($C$3,currency,0)),"") -> 0 | ... P110: =IFERROR(ROUND(Costs!P137/(1-40%),0)*INDEX(fx,MATCH($C$3,currency,0)),"") -> 0
B111: Tech Coordinator | C111: =IFERROR(ROUND(Costs!C138/(1-40%),0)*INDEX(fx,MATCH($C$3,currency,0)),"") -> 235 | D111: =IFERROR(ROUND(Costs!D138/(1-40%),0)*INDEX(fx,MATCH($C$3,currency,0)),"") -> 0 | E111: =IFERROR(ROUND(Costs!E138/(1-40%),0)*INDEX(fx,MATCH($C$3,currency,0)),"") -> 0 | F111: =IFERROR(ROUND(Costs!F138/(1-40%),0)*INDEX(fx,MATCH($C$3,currency,0)),"") -> 0 | G111: =IFERROR(ROUND(Costs!G138/(1-40%),0)*INDEX(fx,MATCH($C$3,currency,0)),"") -> 0 | H111: =IFERROR(ROUND(Costs!H138/(1-40%),0)*INDEX(fx,MATCH($C$3,currency,0)),"") -> 0 | I111: =IFERROR(ROUND(Costs!I138/(1-40%),0)*INDEX(fx,MATCH($C$3,currency,0)),"") -> 0 | J111: =IFERROR(ROUND(Costs!J138/(1-40%),0)*INDEX(fx,MATCH($C$3,currency,0)),"") -> 0 | ... P111: =IFERROR(ROUND(Costs!P138/(1-40%),0)*INDEX(fx,MATCH($C$3,currency,0)),"") -> 0
B112: CSM | C112: =IFERROR(ROUND(Costs!C139/(1-40%),0)*INDEX(fx,MATCH($C$3,currency,0)),"") -> 292 | D112: =IFERROR(ROUND(Costs!D139/(1-40%),0)*INDEX(fx,MATCH($C$3,currency,0)),"") -> 0 | E112: =IFERROR(ROUND(Costs!E139/(1-40%),0)*INDEX(fx,MATCH($C$3,currency,0)),"") -> 0 | F112: =IFERROR(ROUND(Costs!F139/(1-40%),0)*INDEX(fx,MATCH($C$3,currency,0)),"") -> 0 | G112: =IFERROR(ROUND(Costs!G139/(1-40%),0)*INDEX(fx,MATCH($C$3,currency,0)),"") -> 0 | H112: =IFERROR(ROUND(Costs!H139/(1-40%),0)*INDEX(fx,MATCH($C$3,currency,0)),"") -> 0 | I112: =IFERROR(ROUND(Costs!I139/(1-40%),0)*INDEX(fx,MATCH($C$3,currency,0)),"") -> 0 | J112: =IFERROR(ROUND(Costs!J139/(1-40%),0)*INDEX(fx,MATCH($C$3,currency,0)),"") -> 0 | ... P112: =IFERROR(ROUND(Costs!P139/(1-40%),0)*INDEX(fx,MATCH($C$3,currency,0)),"") -> 0
B113: Sr. Arch | C113: =IFERROR(ROUND(Costs!C140/(1-40%),0)*INDEX(fx,MATCH($C$3,currency,0)),"") -> 303 | D113: =IFERROR(ROUND(Costs!D140/(1-40%),0)*INDEX(fx,MATCH($C$3,currency,0)),"") -> 0 | E113: =IFERROR(ROUND(Costs!E140/(1-40%),0)*INDEX(fx,MATCH($C$3,currency,0)),"") -> 0 | F113: =IFERROR(ROUND(Costs!F140/(1-40%),0)*INDEX(fx,MATCH($C$3,currency,0)),"") -> 0 | G113: =IFERROR(ROUND(Costs!G140/(1-40%),0)*INDEX(fx,MATCH($C$3,currency,0)),"") -> 0 | H113: =IFERROR(ROUND(Costs!H140/(1-40%),0)*INDEX(fx,MATCH($C$3,currency,0)),"") -> 0 | I113: =IFERROR(ROUND(Costs!I140/(1-40%),0)*INDEX(fx,MATCH($C$3,currency,0)),"") -> 0 | J113: =IFERROR(ROUND(Costs!J140/(1-40%),0)*INDEX(fx,MATCH($C$3,currency,0)),"") -> 0 | ... P113: =IFERROR(ROUND(Costs!P140/(1-40%),0)*INDEX(fx,MATCH($C$3,currency,0)),"") -> 0
... B115: Sr. Proj Mgr | C115: =IFERROR(ROUND(Costs!C142/(1-40%),0)*INDEX(fx,MATCH($C$3,currency,0)),"") -> 288 | D115: =IFERROR(ROUND(Costs!D142/(1-40%),0)*INDEX(fx,MATCH($C$3,currency,0)),"") -> 0 | E115: =IFERROR(ROUND(Costs!E142/(1-40%),0)*INDEX(fx,MATCH($C$3,currency,0)),"") -> 0 | F115: =IFERROR(ROUND(Costs!F142/(1-40%),0)*INDEX(fx,MATCH($C$3,currency,0)),"") -> 0 | G115: =IFERROR(ROUND(Costs!G142/(1-40%),0)*INDEX(fx,MATCH($C$3,currency,0)),"") -> 0 | H115: =IFERROR(ROUND(Costs!H142/(1-40%),0)*INDEX(fx,MATCH($C$3,currency,0)),"") -> 0 | I115: =IFERROR(ROUND(Costs!I142/(1-40%),0)*INDEX(fx,MATCH($C$3,currency,0)),"") -> 0 | J115: =IFERROR(ROUND(Costs!J142/(1-40%),0)*INDEX(fx,MATCH($C$3,currency,0)),"") -> 0 | ... P115: =IFERROR(ROUND(Costs!P142/(1-40%),0)*INDEX(fx,MATCH($C$3,currency,0)),"") -> 0

Sheet PriceTbls
B1: Prices | AI1: Alternative Costs
B3: PnA Price | C3: US | D3: UK | E3: DE | F3: PL | G3: NL | H3: MX | I3: IN | J3: EG | K3: CAN | L3: AU | M3: AE | N3: SG | O3: VN | R3: PnA Count | S3: US | T3: UK | U3: DE | V3: PL | W3: NL | X3: MX | Y3: IN | Z3: EG | AA3: CAN | AB3: AU | AC3: AE | AD3: SG | AE3: VN | AI3: PnA Alt Cost | AJ3: US | AK3: UK | AL3: DE | AM3: PL | AN3: NL | AO3: MX | AP3: IN | AQ3: EG | AR3: CAN | AS3: AU | AT3: AE | AU3: SG | AV3: VN | AX3: costAps | AY3: altcostAps
B4: Jr. Eng | C4: 0 | D4: 103.33333 | E4: 106.66667 | F4: 110 | G4: 0 | H4: 0 | I4: 40 | J4: 0 | K4: 0 | L4: 0 | M4: 0 | N4: 0 | O4: 0 | R4: Jr. Eng | S4: 0 | T4: 9 | U4: 2 | V4: 1 | W4: 0 | X4: 0 | Y4: 11 | Z4: 0 | AA4: 0 | AB4: 0 | AC4: 0 | AD4: 0 | AE4: 0 | AI4: Jr. Eng | AJ4: 82.39 | AK4: 55.540351 | AL4: 57.346708 | AM4: 48.07399 | AN4: 59.160347 | AO4: 35.851942 | AP4: 13.041247 | AQ4: 9.2123963 | AR4: 0 | AS4: 64.321796 | AT4: 0 | AU4: 96.257145 | AV4: 17.34645 | AX4: costData | AY4: altcostData
B5: Eng | C5: 190 | D5: 153.33333 | E5: 150 | F5: 116.66667 | G5: 143.33333 | H5: 73 | I5: 50 | J5: 62.5 | K5: 0 | L5: 0 | M5: 155.59143 | N5: 0 | O5: 0 | R5: Eng | S5: 4 | T5: 9 | U5: 4 | V5: 2 | W5: 1 | X5: 0 | Y5: 48 | Z5: 12 | AA5: 0 | AB5: 0 | AC5: 1 | AD5: 0 | AE5: 0 | AI5: Eng | AJ5: 102.98983 | AK5: 84.124343 | AL5: 79.075836 | AM5: 63.217425 | AN5: 78.802166 | AO5: 46.617347 | AP5: 17.106016 | AQ5: 10.172819 | AR5: 74.126274 | AS5: 75.780805 | AT5: 104.46341 | AU5: 122.95082 | AV5: 24.0405 | AX5: costSec | AY5: altcostSec
B6: Sr. Eng | C6: 220 | D6: 213.33333 | E6: 173.33333 | F6: 146.66667 | G6: 188.33333 | H6: 95 | I6: 80 | J6: 85 | K6: 168.33333 | L6: 0 | M6: 0 | N6: 0 | O6: 0 | R6: Sr. Eng | S6: 19 | T6: 20 | U6: 11 | V6: 5 | W6: 10 | X6: 0 | Y6: 31 | Z6: 9 | AA6: 4 | AB6: 0 | AC6: 0 | AD6: 0 | AE6: 0 | AI6: Sr. Eng | AJ6: 121.76082 | AK6: 116.1602 | AL6: 93.295127 | AM6: 74.679927 | AN6: 100.8746 | AO6: 63.59054 | AP6: 27.48632 | AQ6: 14.285154 | AR6: 90.087979 | AS6: 104.91479 | AT6: 115 | AU6: 144.724 | AV6: 33.9306 | AX6: costAdv | AY6: altcostAdv
B7: Arch | C7: 290 | D7: 250 | E7: 223 | F7: 173.06667 | G7: 225 | H7: 156.66667 | I7: 100 | J7: 93.515572 | K7: 185 | L7: 0 | N7: 0 | O7: 0 | R7: Arch | S7: 11 | T7: 6 | U7: 10 | V7: 1 | W7: 10 | X7: 1 | Y7: 6 | Z7: 0 | AA7: 2 | AB7: 0 | AC7: 2 | AD7: 0 | AE7: 0 | AI7: Arch | AJ7: 139.47395 | AK7: 133.05859 | AL7: 123.46714 | AM7: 91.34847 | AN7: 120.96608 | AO7: 89.711708 | AP7: 36.686571 | AQ7: 18.52942 | AR7: 99.457642 | AS7: 137.12974 | AT7: 120.12672 | AU7: 201.51469 | AV7: 40.656 | AX7: costProd | AY7: altcostProd
B8: Sr. Arch | C8: 310 | D8: 260 | E8: 0 | F8: 0 | G8: 256.5 | H8: 167.47126 | I8: 102.5 | J8: 0 | K8: 213.33333 | L8: 0 | M8: 241.42857 | N8: 0 | O8: 0 | R8: Sr. Arch | S8: 15 | T8: 1 | V8: 0 | W8: 1 | X8: 0 | Y8: 4 | Z8: 0 | AA8: 5 | AB8: 0 | AC8: 0 | AD8: 0 | AE8: 0 | AI8: Sr. Arch | AJ8: 158.0263 | AK8: 136.56195 | AL8: 0 | AM8: 111.11045 | AN8: 137.05657 | AO8: 103.82002 | AP8: 38.890318 | AQ8: 20.994139 | AR8: 116.7559 | AS8: 155.37027 | AT8: 0 | AU8: 0 | AV8: 0 | AX8: costPvtCld | AY8: altcostPvtCld
B9: TCT/Lead Arch | D9: 278.33333 | E9: 0 | F9: 0 | G9: 408.33333 | H9: 0 | I9: 0 | J9: 0 | K9: 288.33333 | L9: 0 | M9: 0 | N9: 0 | O9: 0 | R9: TCT/Lead Arch | S9: 0 | T9: 1 | V9: 0 | W9: 1 | X9: 0 | Y9: 0 | Z9: 0 | AA9: 2 | AB9: 0 | AC9: 0 | AD9: 0 | AE9: 0 | AI9: TCT/Lead Arch | AJ9: 333.34875 | AK9: 334.55294 | AL9: 0 | AM9: 0 | AN9: 384.46934 | AO9: 149.5468 | AP9: 0 | AQ9: 0 | AR9: 272.2884 | AS9: 270.59747 | AT9: 0 | AU9: 0 | AV9: 0 | AX9: costSadia | AY9: altcostSadia
B10: Manager | C10: 300 | D10: 265 | E10: 215.71429 | F10: 0 | G10: 240 | H10: 0 | I10: 105 | J10: 116 | K10: 195 | L10: 0 | M10: 0 | N10: 0 | O10: 0 | R10: Manager | S10: 3 | T10: 6 | U10: 4 | V10: 0 | W10: 1 | X10: 0 | Y10: 5 | Z10: 3 | AA10: 3 | AB10: 0 | AC10: 0 | AD10: 0 | AE10: 0 | AI10: Manager | AJ10: 120.29802 | AK10: 77.211211 | AL10: 84.23606 | AM10: 0 | AN10: 89.052606 | AO10: 66.354946 | AP10: 20.928856 | AQ10: 15.147542 | AR10: 92.832985 | AS10: 108.23899 | AT10: 161.71115 | AU10: 100.05515 | AV10: 21.7239 | AX10: costErp | AY10: altcostErp
B11: Sr. Mgr | C11: 350 | D11: 310 | E11: 0 | F11: 0 | G11: 260 | H11: 0 | I11: 110 | J11: 0 | K11: 0 | L11: 0 | M11: 0 | N11: 0 | O11: 0 | R11: Sr. Mgr | S11: 1 | T11: 2 | V11: 0 | W11: 1 | X11: 0 | Y11: 2 | Z11: 0 | AA11: 0 | AB11: 0 | AC11: 0 | AD11: 0 | AE11: 0 | AI11: Sr. Mgr | AJ11: 409.81573 | AK11: 287.14644 | AL11: 277.81841 | AM11: 62.699734 | AN11: 279.97709 | AO11: 203.68937 | AP11: 97.256885 | AQ11: 51.602686 | AR11: 239.48314 | AS11: 271.76297 | AT11: 405.7097 | AU11: 264.55338 | AV11: 140.03859
B12: EM/PJM | D12: 228.69333 | E12: 208 | F12: 0 | G12: 0 | H12: 95.676721 | I12: 88 | J12: 102 | K12: 0 | L12: 0 | M12: 0 | N12: 0 | O12: 0 | R12: EM/PJM | S12: 3 | T12: 3 | U12: 2 | V12: 0 | W12: 0 | X12: 0 | Y12: 10 | Z12: 2 | AA12: 0 | AB12: 0 | AC12: 0 | AD12: 0 | AE12: 0 | AI12: EM/PJM | AJ12: 120.92323 | AK12: 75.451419 | AL12: 106.01025 | AM12: 55.368232 | AN12: 94.635869 | AO12: 68.96299 | AP12: 21.92616 | AQ12: 8.3590742 | AR12: 73.104865 | AS12: 114.34064 | AT12: 0 | AU12: 0 | AV12: 21.004183
B13: Sr. EM/Sr. PJM/PGM | C13: 301 | D13: 255 | E13: 221.66667 | F13: 207.68 | G13: 231.66667 | H13: 0 | I13: 101 | J13: 115 | K13: 195 | L13: 0 | N13: 198.33333 | O13: 0 | R13: Sr. EM/Sr. PJM/PGM | S13: 2 | T13: 11 | U13: 5 | V13: 1 | W13: 3 | X13: 0 | Y13: 2 | Z13: 1 | AA13: 2 | AB13: 0 | AC13: 1 | AD13: 1 | AE13: 0 | AI13: Sr. EM/Sr. PJM/PGM | AJ13: 144.00912 | AK13: 121.70636 | AL13: 133.36389 | AM13: 65.938781 | AN13: 145.97743 | AO13: 75.557306 | AP13: 31.222678 | AQ13: 19.524194 | AR13: 98.56639 | AS13: 120.04797 | AT13: 149.79014 | AU13: 114.86888 | AV13: 30.097904
S14: =SUBTOTAL(109,TbCountAps22[US]) -> 58 | T14: =SUBTOTAL(109,TbCountAps22[UK]) -> 68 | U14: =SUBTOTAL(109,TbCountAps22[DE]) -> 38 | V14: =SUBTOTAL(109,TbCountAps22[PL]) -> 10 | W14: =SUBTOTAL(109,TbCountAps22[NL]) -> 28 | X14: =SUBTOTAL(109,TbCountAps22[MX]) -> 1 | Y14: =SUBTOTAL(109,TbCountAps22[IN]) -> 119 | Z14: =SUBTOTAL(109,TbCountAps22[EG]) -> 27 | AA14: =SUBTOTAL(109,TbCountAps22[CAN]) -> 18 | AB14: =SUBTOTAL(109,TbCountAps22[AU]) -> 0 | AC14: =SUBTOTAL(109,TbCountAps22[AE]) -> 4 | AD14: =SUBTOTAL(109,TbCountAps22[SG]) -> 1 | AE14: =SUBTOTAL(109,TbCountAps22[VN]) -> 0 | AG14: =SUM(TbCountAps22[[#Totals],[US]:[VN]]) -> 372
B17: Data Price | C17: US | D17: UK | E17: DE | F17: PL | G17: NL | H17: MX | I17: IN | J17: EG | K17: CAN | L17: AU | M17: AE | N17: SG | O17: VN | P17: Column1 | R17: Data Count | S17: US | T17: UK | U17: DE | V17: PL | W17: NL | X17: MX | Y17: IN | Z17: EG | AA17: CAN | AB17: AU | AC17: AE | AD17: SG | AE17: VN | AI17: Data Alt Cost | AJ17: US | AK17: UK | AL17: DE | AM17: PL | AN17: NL | AO17: MX | AP17: IN | AQ17: EG | AR17: CAN | AS17: AU | AT17: AE | AU17: SG | AV17: VN
B18: Jr. Eng | C18: 147 | D18: 0 | E18: 0 | F18: 0 | G18: 0 | H18: 0 | I18: 31 | J18: 53 | K18: 0 | L18: 0 | M18: 0 | N18: 68 | O18: 29 | R18: Jr. Eng | S18: 3 | T18: 0 | U18: 0 | V18: 0 | W18: 0 | X18: 0 | Y18: 2 | Z18: 8 | AA18: 0 | AB18: 0 | AC18: 0 | AD18: 4 | AE18: 17 | AI18: Jr. Eng | AJ18: 76.116067 | AK18: 69.419036 | AL18: 72.33697 | AM18: 50.016882 | AN18: 59.160347 | AO18: 35.851942 | AP18: 9.8456418 | AQ18: 10.326672 | AR18: 0 | AS18: 64.321796 | AT18: 0 | AU18: 38.735203 | AV18: 9.5456396
B19: Eng | C19: 230 | D19: 0 | E19: 0 | F19: 0 | G19: 172 | H19: 0 | I19: 63 | J19: 75 | K19: 170 | L19: 0 | M19: 0 | N19: 106 | O19: 56 | R19: Eng | S19: 1 | T19: 0 | U19: 0 | V19: 0 | W19: 1 | X19: 0 | Y19: 16 | Z19: 15 | AA19: 2 | AB19: 0 | AC19: 0 | AD19: 3 | AE19: 30 | AI19: Eng | AJ19: 121.66 | AK19: 86.36329 | AL19: 85.155045 | AM19: 63.889345 | AN19: 88.925525 | AO19: 46.617347 | AP19: 18.713146 | AQ19: 14.81178 | AR19: 89.495633 | AS19: 75.780805 | AT19: 104.75289 | AU19: 53.602147 | AV19: 16.915688
B20: Sr. Eng | C20: 277 | D20: 0 | E20: 0 | F20: 0 | G20: 0 | H20: 0 | I20: 90 | J20: 76 | K20: 183 | L20: 0 | M20: 106 | N20: 0 | O20: 97 | R20: Sr. Eng | S20: 4 | T20: 0 | U20: 0 | V20: 0 | W20: 0 | X20: 0 | Y20: 18 | Z20: 2 | AA20: 1 | AB20: 0 | AC20: 1 | AD20: 0 | AE20: 9 | AI20: Sr. Eng | AJ20: 134.11442 | AK20: 118.35447 | AL20: 104.91998 | AM20: 77.723802 | AN20: 99.7061 | AO20: 63.59054 | AP20: 24.322377 | AQ20: 15.5 | AR20: 95 | AS20: 104.91479 | AT20: 115 | AU20: 80.547625 | AV20: 32.28122
B21: Arch | C21: 354 | D21: 0 | E21: 0 | F21: 0 | G21: 0 | H21: 0 | I21: 99 | J21: 0 | K21: 0 | L21: 0 | M21: 0 | N21: 0 | O21: 0 | R21: Arch | S21: 8 | T21: 0 | U21: 0 | V21: 0 | W21: 0 | X21: 0 | Y21: 3 | Z21: 3 | AA21: 2 | AB21: 0 | AC21: 0 | AD21: 3 | AE21: 4 | AI21: Arch | AJ21: 166.59168 | AK21: 172.03632 | AL21: 133.55896 | AM21: 91.824306 | AN21: 115.8625 | AO21: 88.272719 | AP21: 41.761753 | AQ21: 15.685678 | AR21: 100.53167 | AS21: 137.12974 | AT21: 189.56141 | AU21: 100.05311 | AV21: 40.098469
B22: Sr. Arch | C22: 528 | D22: 0 | E22: 0 | F22: 0 | G22: 0 | H22: 0 | I22: 135 | J22: 0 | K22: 0 | L22: 0 | M22: 0 | N22: 0 | O22: 0 | R22: Sr. Arch | S22: 4 | T22: 0 | U22: 0 | V22: 0 | W22: 0 | X22: 0 | Y22: 2 | Z22: 0 | AA22: 2 | AB22: 0 | AC22: 0 | AD22: 0 | AE22: 0 | AI22: Sr. Arch | AJ22: 191.86575 | AK22: 198.1364 | AL22: 0 | AM22: 111.11045 | AN22: 133.4403 | AO22: 103.82002 | AP22: 48.097539 | AQ22: 25.485364 | AR22: 123.56407 | AS22: 191.28978 | AT22: 0 | AU22: 0 | AV22: 0
B23: TCT/Lead Arch | C23: 290 | D23: 0 | E23: 0 | F23: 0 | G23: 0 | H23: 0 | I23: 149 | J23: 110 | K23: 191 | L23: 0 | M23: 0 | N23: 187 | O23: 103 | R23: TCT/Lead Arch | S23: 0 | T23: 0 | U23: 0 | V23: 0 | W23: 0 | X23: 0 | Y23: 0 | Z23: 0 | AA23: 0 | AB23: 0 | AC23: 0 | AD23: 0 | AE23: 0 | AI23: TCT/Lead Arch | AJ23: 456.98555 | AK23: 334.55294 | AL23: 0 | AM23: 0 | AN23: 302.02029 | AO23: 149.5468 | AP23: 0 | AQ23: 0 | AR23: 259.1869 | AS23: 270.59747 | AT23: 0 | AU23: 0 | AV23: 0
B24: Manager | C24: 370 | D24: 0 | E24: 0 | F24: 0 | G24: 0 | H24: 0 | I24: 118 | J24: 0 | K24: 235 | L24: 0 | M24: 0 | N24: 0 | O24: 0 | R24: Manager | S24: 1 | T24: 0 | U24: 0 | V24: 0 | W24: 0 | X24: 0 | Y24: 4 | Z24: 1 | AA24: 0 | AB24: 0 | AC24: 0 | AD24: 0 | AE24: 1 | AI24: Manager | AJ24: 136.275 | AK24: 92.841343 | AL24: 82.111872 | AM24: 0 | AN24: 112.47189 | AO24: 66.354946 | AP24: 25.139985 | AQ24: 15.120975 | AR24: 91.146537 | AS24: 108.23899 | AT24: 161.71115 | AU24: 100.05515 | AV24: 31.914
B25: Sr. Mgr | C25: 361 | D25: 0 | E25: 0 | F25: 0 | G25: 0 | H25: 0 | I25: 0 | J25: 0 | K25: 0 | L25: 0 | M25: 0 | N25: 0 | O25: 0 | R25: Sr. Mgr | S25: 0 | T25: 0 | U25: 0 | V25: 0 | W25: 0 | X25: 0 | Y25: 0 | Z25: 0 | AA25: 1 | AB25: 0 | AC25: 0 | AD25: 1 | AE25: 0 | AI25: Sr. Mgr | AJ25: 507.8125 | AK25: 226.58572 | AL25: 248.04423 | AM25: 62.699734 | AN25: 343.28127 | AO25: 203.68937 | AP25: 104.72285 | AQ25: 56.346506 | AR25: 316.10102 | AS25: 271.76297 | AT25: 405.7097 | AU25: 299.71663 | AV25: 140.03859
B26: EM/PJM | C26: 545 | D26: 0 | E26: 0 | F26: 0 | G26: 0 | H26: 0 | I26: 87 | J26: 82 | K26: 0 | L26: 0 | M26: 0 | N26: 0 | O26: 0 | R26: EM/PJM | S26: 1 | T26: 0 | U26: 0 | V26: 0 | W26: 0 | X26: 0 | Y26: 1 | Z26: 1 | AA26: 0 | AB26: 0 | AC26: 0 | AD26: 1 | AE26: 1 | AI26: EM/PJM | AJ26: 133.75089 | AK26: 89.168968 | AL26: 90.602209 | AM26: 55.368232 | AN26: 94.635869 | AO26: 39.066905 | AP26: 26.48081 | AQ26: 16.985683 | AR26: 85.319477 | AS26: 74.217457 | AT26: 0 | AU26: 72.529942 | AV26: 21.004183
B27: Sr. EM/Sr. PJM/PGM | C27: 0 | D27: 0 | E27: 0 | F27: 0 | G27: 0 | H27: 0 | I27: 0 | J27: 0 | K27: 385 | L27: 0 | M27: 0 | N27: 379 | O27: 127 | R27: Sr. EM/Sr. PJM/PGM | S27: 1 | T27: 0 | U27: 0 | V27: 0 | W27: 0 | X27: 0 | Y27: 0 | Z27: 3 | AA27: 0 | AB27: 0 | AC27: 0 | AD27: 0 | AE27: 2 | AI27: Sr. EM/Sr. PJM/PGM | AJ27: 202.37885 | AK27: 125.48154 | AL27: 166.48328 | AM27: 0 | AN27: 165.13873 | AO27: 75.557306 | AP27: 40.226735 | AQ27: 20.228481 | AR27: 141.54319 | AS27: 145.06706 | AT27: 241.01182 | AU27: 120.6467 | AV27: 30.097904
C28: 0 | D28: 0 | E28: 0 | F28: 0 | G28: 0 | H28: 0 | I28: 82 | J28: 52 | K28: 0 | L28: 0 | M28: 0 | N28: 124 | O28: 36 | S28: =SUBTOTAL(109,TbCountData24[US]) -> 23 | T28: =SUBTOTAL(109,TbCountData24[UK]) -> 0 | U28: =SUBTOTAL(109,TbCountData24[DE]) -> 0 | V28: =SUBTOTAL(109,TbCountData24[PL]) -> 0 | W28: =SUBTOTAL(109,TbCountData24[NL]) -> 1 | X28: =SUBTOTAL(109,TbCountData24[MX]) -> 0 | Y28: =SUBTOTAL(109,TbCountData24[IN]) -> 46 | Z28: =SUBTOTAL(109,TbCountData24[EG]) -> 33 | AA28: =SUBTOTAL(109,TbCountData24[CAN]) -> 8 | AB28: =SUBTOTAL(109,TbCountData24[AU]) -> 0 | AC28: =SUBTOTAL(109,TbCountData24[AE]) -> 1 | AD28: =SUBTOTAL(109,TbCountData24[SG]) -> 12 | AE28: =SUBTOTAL(109,TbCountData24[VN]) -> 64 | AG28: =SUM(TbCountData24[[#Totals],[US]:[VN]]) -> 188
C29: 225 | D29: 0 | E29: 0 | F29: 0 | G29: 304 | H29: 0 | I29: 142 | J29: 79 | K29: 0 | L29: 0 | M29: 0 | N29: 0 | O29: 146
R32: Security Count | S32: US | T32: UK | U32: DE | V32: PL | W32: NL | X32: MX | Y32: IN | Z32: EG | AA32: CAN | AB32: AU | AC32: AE | AD32: SG | AE32: VN | AI32: Sec Alt Cost | AJ32: US | AK32: UK | AL32: DE | AM32: PL | AN32: NL | AO32: MX | AP32: IN | AQ32: EG | AR32: CAN | AS32: AU | AT32: AE | AU32: SG | AV32: VN
R33: Jr. Eng | S33: 0 | T33: 0 | U33: 0 | V33: 0 | W33: 0 | X33: 0 | Y33: 9 | Z33: 0 | AA33: 0 | AB33: 0 | AC33: 0 | AD33: 0 | AE33: 0 | AI33: Jr. Eng | AJ33: 82.39 | AK33: 69.419036 | AL33: 72.33697 | AM33: 50.016882 | AN33: 59.160347 | AO33: 35.851942 | AP33: 13.532455 | AQ33: 9.2123963 | AR33: 0 | AS33: 64.321796 | AT33: 0 | AU33: 96.257145 | AV33: 17.34645
B34: Security Price | C34: US | D34: UK | E34: DE | F34: PL | G34: NL | H34: MX | I34: IN | J34: EG | K34: CAN | L34: AU | M34: AE | N34: SG | O34: VN | P34: Column1 | R34: Eng | S34: 0 | T34: 0 | U34: 0 | V34: 0 | W34: 0 | X34: 2 | Y34: 11 | Z34: 0 | AA34: 0 | AB34: 0 | AC34: 0 | AD34: 0 | AE34: 0 | AI34: Eng | AJ34: 121.66 | AK34: 86.36329 | AL34: 85.155045 | AM34: 63.889345 | AN34: 75.877627 | AO34: 39.094338 | AP34: 18.388129 | AQ34: 9.903326 | AR34: 74.126274 | AS34: 75.780805 | AT34: 104.75289 | AU34: 122.95082 | AV34: 24.0405
B35: Jr. Eng | C35: 0 | D35: 0 | E35: 0 | F35: 0 | G35: 0 | H35: 0 | I35: 37 | J35: 0 | K35: 0 | L35: 0 | M35: 0 | N35: 0 | O35: 0 | R35: Sr. Eng | S35: 2 | T35: 0 | U35: 0 | V35: 0 | W35: 0 | X35: 1 | Y35: 9 | Z35: 0 | AA35: 0 | AB35: 1 | AC35: 0 | AD35: 0 | AE35: 0 | AI35: Sr. Eng | AJ35: 121.59333 | AK35: 118.35447 | AL35: 104.91998 | AM35: 77.723802 | AN35: 99.7061 | AO35: 46.060367 | AP35: 29.112436 | AQ35: 16.360794 | AR35: 95 | AS35: 94.951242 | AT35: 115 | AU35: 144.724 | AV35: 33.9306
B36: Eng | C36: 0 | D36: 0 | E36: 0 | F36: 0 | G36: 0 | H36: 72 | I36: 51 | J36: 0 | K36: 0 | L36: 0 | M36: 0 | N36: 0 | O36: 0 | R36: Arch | S36: 1 | T36: 7 | U36: 1 | V36: 0 | W36: 1 | X36: 1 | Y36: 0 | Z36: 0 | AA36: 0 | AB36: 0 | AC36: 1 | AD36: 0 | AE36: 0 | AI36: Arch | AJ36: 152.67515 | AK36: 112.66605 | AL36: 116.98068 | AM36: 91.824306 | AN36: 129.84007 | AO36: 65.125425 | AP36: 43.436965 | AQ36: 18.52942 | AR36: 115.54441 | AS36: 137.12974 | AT36: 147.01011 | AU36: 201.51469 | AV36: 40.656
B37: Sr. Eng | C37: 223 | D37: 0 | E37: 0 | F37: 0 | G37: 0 | H37: 84 | I37: 80 | J37: 0 | K37: 174 | L37: 174 | M37: 211 | N37: 0 | O37: 0 | R37: Sr. Arch | S37: 2 | T37: 0 | U37: 0 | V37: 0 | W37: 0 | X37: 0 | Y37: 0 | Z37: 0 | AA37: 0 | AB37: 0 | AC37: 0 | AD37: 0 | AE37: 0 | AI37: Sr. Arch | AJ37: 175.8379 | AK37: 129.75891 | AL37: 0 | AM37: 111.11045 | AN37: 149.53844 | AO37: 103.82002 | AP37: 53.372914 | AQ37: 25.485364 | AR37: 124.71121 | AS37: 191.28978 | AT37: 0 | AU37: 0 | AV37: 0
B38: Arch | C38: 280 | D38: 207 | E38: 214 | F38: 0 | G38: 238 | H38: 119 | I38: 0 | J38: 0 | K38: 0 | L38: 0 | M38: 270 | N38: 0 | O38: 0 | R38: TCT/Lead Arch | S38: 0 | T38: 0 | U38: 0 | V38: 0 | W38: 0 | X38: 0 | Y38: 0 | Z38: 0 | AA38: 0 | AB38: 0 | AC38: 0 | AD38: 0 | AE38: 0 | AI38: TCT/Lead Arch | AJ38: 456.98555 | AK38: 334.55294 | AL38: 0 | AM38: 0 | AN38: 302.02029 | AO38: 149.5468 | AP38: 0 | AQ38: 0 | AR38: 259.1869 | AS38: 270.59747 | AT38: 0 | AU38: 0 | AV38: 0
B39: Sr. Arch | C39: 322 | D39: 0 | E39: 0 | F39: 0 | G39: 261 | H39: 0 | I39: 0 | J39: 0 | K39: 0 | L39: 0 | M39: 0 | N39: 0 | O39: 0 | R39: Manager | S39: 0 | T39: 1 | U39: 0 | V39: 0 | W39: 0 | X39: 0 | Y39: 1 | Z39: 0 | AA39: 0 | AB39: 0 | AC39: 0 | AD39: 0 | AE39: 0 | AI39: Manager | AJ39: 111.12386 | AK39: 91.807844 | AL39: 82.111872 | AM39: 0 | AN39: 112.47189 | AO39: 66.354946 | AP39: 35.65255 | AQ39: 16.006639 | AR39: 91.146537 | AS39: 108.23899 | AT39: 161.71115 | AU39: 100.05515 | AV39: 21.7239
B40: TCT/Lead Arch | C40: 0 | D40: 0 | E40: 0 | F40: 0 | G40: 0 | H40: 0 | I40: 0 | J40: 0 | K40: 0 | L40: 0 | M40: 0 | N40: 0 | O40: 0 | R40: Sr. Mgr | S40: 1 | T40: 3 | U40: 0 | V40: 0 | W40: 0 | X40: 0 | Y40: 0 | Z40: 0 | AA40: 0 | AB40: 0 | AC40: 0 | AD40: 0 | AE40: 0 | AI40: Sr. Mgr | AJ40: 346.875 | AK40: 252.09932 | AL40: 248.04423 | AM40: 62.699734 | AN40: 343.28127 | AO40: 203.68937 | AP40: 52.489443 | AQ40: 49.964993 | AR40: 259.68655 | AS40: 271.76297 | AT40: 405.7097 | AU40: 264.55338 | AV40: 140.03859
B41: Manager | C41: 0 | D41: 144 | E41: 0 | F41: 0 | G41: 0 | H41: 0 | I41: 78 | J41: 0 | K41: 0 | L41: 0 | M41: 0 | N41: 0 | O41: 0 | R41: EM/PJM | S41: 0 | T41: 0 | U41: 0 | V41: 0 | W41: 0 | X41: 0 | Y41: 0 | Z41: 0 | AA41: 0 | AB41: 0 | AC41: 0 | AD41: 0 | AE41: 0 | AI41: EM/PJM | AJ41: 127.81947 | AK41: 89.168968 | AL41: 90.602209 | AM41: 55.368232 | AN41: 94.635869 | AO41: 39.066905 | AP41: 26.48081 | AQ41: 8.3590742 | AR41: 85.319477 | AS41: 74.217457 | AT41: 0 | AU41: 0 | AV41: 21.004183
B42: Sr. Mgr | C42: 545 | D42: 396 | E42: 0 | F42: 0 | G42: 0 | H42: 0 | I42: 0 | J42: 0 | K42: 0 | L42: 0 | M42: 0 | N42: 0 | O42: 0 | R42: Sr. EM/Sr. PJM/PGM | S42: 0 | T42: 0 | U42: 0 | V42: 0 | W42: 0 | X42: 0 | Y42: 0 | Z42: 0 | AA42: 0 | AB42: 0 | AC42: 0 | AD42: 0 | AE42: 0 | AI42: Sr. EM/Sr. PJM/PGM | AJ42: 202.37885 | AK42: 125.48154 | AL42: 166.48328 | AM42: 0 | AN42: 165.13873 | AO42: 75.557306 | AP42: 40.226735 | AQ42: 19.524194 | AR42: 141.54319 | AS42: 145.06706 | AT42: 241.01182 | AU42: 120.6467 | AV42: 30.097904
B43: EM/PJM | C43: 0 | D43: 0 | E43: 0 | F43: 0 | G43: 0 | H43: 0 | I43: 0 | J43: 0 | K43: 0 | L43: 0 | M43: 0 | N43: 0 | O43: 0 | S43: =SUBTOTAL(109,TbCountSec26[US]) -> 6 | T43: =SUBTOTAL(109,TbCountSec26[UK]) -> 11 | U43: =SUBTOTAL(109,TbCountSec26[DE]) -> 1 | V43: =SUBTOTAL(109,TbCountSec26[PL]) -> 0 | W43: =SUBTOTAL(109,TbCountSec26[NL]) -> 1 | X43: =SUBTOTAL(109,TbCountSec26[MX]) -> 4 | Y43: =SUBTOTAL(109,TbCountSec26[IN]) -> 30 | Z43: =SUBTOTAL(109,TbCountSec26[EG]) -> 0 | AA43: =SUBTOTAL(109,TbCountSec26[CAN]) -> 0 | AB43: =SUBTOTAL(109,TbCountSec26[AU]) -> 1 | AC43: =SUBTOTAL(109,TbCountSec26[AE]) -> 1 | AD43: =SUBTOTAL(109,TbCountSec26[SG]) -> 0 | AE43: =SUBTOTAL(109,TbCountSec26[VN]) -> 0 | AG43: =SUM(TbCountSec26[[#Totals],[US]:[VN]]) -> 55
B44: Sr. EM/Sr. PJM/PGM | C44: 0 | D44: 0 | E44: 0 | F44: 0 | G44: 0 | H44: 0 | I44: 0 | J44: 0 | K44: 0 | L44: 0 | M44: 0 | N44: 0 | O44: 0
R47: Advisory Count | S47: US | T47: UK | U47: DE | V47: PL | W47: NL | X47: MX | Y47: IN | Z47: EG | AA47: CAN | AB47: AU | AC47: AE | AD47: SG | AE47: VN | AI47: Advisory Cost | AJ47: US | AK47: UK | AL47: DE | AM47: PL | AN47: NL | AO47: MX | AP47: IN | AQ47: EG | AR47: CAN | AS47: AU | AT47: AE | AU47: SG | AV47: VN
R48: Advisory Consultant | S48: 4 | AI48: Advisory Consultant | AK48: 119.12969 | AL48: 114.05187 | AM48: 70.238766 | AN48: 118.48153 | AO48: 75.141087 | AP48: 30.279239 | AQ48: 20.531458 | AR48: 97.980958 | AS48: 119.66981 | AT48: 132.51316 | AU48: 182.55944 | AV48: 42.886076
B49: Advisory Price | C49: US | D49: UK | E49: DE | F49: PL | G49: NL | H49: MX | I49: IN | J49: EG | K49: CAN | L49: AU | M49: AE | N49: SG | O49: VN | P49: SA | R49: Sr. Advisory Consultant | S49: 2 | AI49: Sr. Advisory Consultant | AK49: 132.60299 | AL49: 126.79758 | AM49: 121.2057 | AN49: 125.59145 | AO49: 92.716374 | AP49: 36.017783 | AQ49: 22.628558 | AR49: 114.8673 | AS49: 130 | AT49: 172 | AU49: 210 | AV49: 0
B50: Advisory Consultant | C50: 227.87072
B51: Sr. Advisory Consultant | C51: 256.40925
S58: =SUBTOTAL(109,TbCountAdv27[US]) -> 6 | T58: =SUBTOTAL(109,TbCountAdv27[UK]) -> 0 | U58: =SUBTOTAL(109,TbCountAdv27[DE]) -> 0 | V58: =SUBTOTAL(109,TbCountAdv27[PL]) -> 0 | W58: =SUBTOTAL(109,TbCountAdv27[NL]) -> 0 | X58: =SUBTOTAL(109,TbCountAdv27[MX]) -> 0 | Y58: =SUBTOTAL(109,TbCountAdv27[IN]) -> 0 | Z58: =SUBTOTAL(109,TbCountAdv27[EG]) -> 0 | AA58: =SUBTOTAL(109,TbCountAdv27[CAN]) -> 0 | AB58: =SUBTOTAL(109,TbCountAdv27[AU]) -> 0 | AC58: =SUBTOTAL(109,TbCountAdv27[AE]) -> 0 | AD58: =SUBTOTAL(109,TbCountAdv27[SG]) -> 0 | AE58: =SUBTOTAL(109,TbCountAdv27[VN]) -> 0 | AG58: =SUM(TbCountAdv27[[#Totals],[US]:[VN]]) -> 6
R62: Productivity Count | S62: US | T62: UK | U62: DE | V62: PL | W62: NL | X62: MX | Y62: IN | Z62: EG | AA62: CAN | AB62: AU | AC62: AE | AD62: SG | AE62: VN | AI62: Productivity Alt Cost | AJ62: US | AK62: UK | AL62: DE | AM62: PL | AN62: NL | AO62: MX | AP62: IN | AQ62: EG | AR62: CAN | AS62: AU | AT62: AE | AU62: SG | AV62: VN
R63: Specialty Architect | S63: 1 | AI63: Specialty Architect
B64: Productivity Price | C64: US | D64: UK | E64: DE | F64: PL | G64: NL | H64: MX | I64: IN | J64: EG | K64: CAN | L64: AU | M64: AE | N64: SG | O64: VN | P64: SA | R64: Sr. Specialty Engineer | S64: 1 | AI64: Sr. Specialty Engineer
B65: Specialty Architect | C65: 250 | R65: Specialty Engineer | S65: 1 | AI65: Specialty Engineer
B66: Sr. Specialty Engineer | C66: 220 | R66: Program Manager | S66: 1 | AI66: Program Manager
B67: Specialty Engineer | C67: 165 | R67: Engagement Manager (EM) | S67: 1 | AI67: Engagement Manager (EM)
B68: Program Manager | C68: 250
B69: Engagement Manager (EM) | C69: 220
S73: =SUBTOTAL(109,TbCountProd28[US]) -> 5 | T73: =SUBTOTAL(109,TbCountProd28[UK]) -> 0 | U73: =SUBTOTAL(109,TbCountProd28[DE]) -> 0 | V73: =SUBTOTAL(109,TbCountProd28[PL]) -> 0 | W73: =SUBTOTAL(109,TbCountProd28[NL]) -> 0 | X73: =SUBTOTAL(109,TbCountProd28[MX]) -> 0 | Y73: =SUBTOTAL(109,TbCountProd28[IN]) -> 0 | Z73: =SUBTOTAL(109,TbCountProd28[EG]) -> 0 | AA73: =SUBTOTAL(109,TbCountProd28[CAN]) -> 0 | AB73: =SUBTOTAL(109,TbCountProd28[AU]) -> 0 | AC73: =SUBTOTAL(109,TbCountProd28[AE]) -> 0 | AD73: =SUBTOTAL(109,TbCountProd28[SG]) -> 0 | AE73: =SUBTOTAL(109,TbCountProd28[VN]) -> 0 | AG73: =SUM(TbCountProd28[[#Totals],[US]:[VN]]) -> 5
R76: PS Pvt Cld Count | S76: US | T76: UK | U76: DE | V76: PL | W76: NL | X76: MX | Y76: IN | Z76: EG | AA76: CAN | AB76: AU | AC76: AE | AD76: SG | AE76: VN | AI76: PS Private Cloud Alt Cost | AJ76: US | AK76: UK | AL76: DE | AM76: PL | AN76: NL | AO76: MX | AP76: IN | AQ76: EG | AR76: CAN | AS76: AU | AT76: AE | AU76: SG | AV76: VN
R77: Jr. Engineer | S77: 0 | T77: 0 | U77: 0 | V77: 0 | W77: 0 | X77: 0 | Y77: 0 | Z77: 0 | AA77: 0 | AB77: 0 | AC77: 0 | AD77: 0 | AE77: 0 | AI77: Jr. Engineer | AJ77: 69 | AK77: 58 | AL77: 61 | AM77: 44 | AN77: 50 | AO77: 30 | AP77: 15 | AQ77: 0 | AR77: 0 | AS77: 54 | AT77: 0 | AU77: 81 | AV77: 15
B78: PS Private Cloud | C78: US | D78: UK | E78: DE | F78: PL | G78: NL | H78: MX | I78: IN | J78: EG | K78: CAN | L78: AU | M78: AE | N78: SG | O78: VN | P78: SA | R78: Engineer | S78: 2 | T78: 0 | U78: 0 | V78: 0 | W78: 0 | X78: 0 | Y78: 1 | Z78: 0 | AA78: 0 | AB78: 0 | AC78: 0 | AD78: 0 | AE78: 0 | AI78: Engineer | AJ78: 124 | AK78: 72 | AL78: 71 | AM78: 56 | AN78: 64 | AO78: 39 | AP78: 27 | AQ78: 9 | AR78: 62 | AS78: 64 | AT78: 88 | AU78: 103 | AV78: 21
B79: Jr. Engineer | C79: 0 | D79: 0 | E79: 0 | F79: 0 | G79: 0 | H79: 0 | I79: 0 | J79: 0 | K79: 0 | L79: 0 | M79: 0 | N79: 0 | O79: 0 | P79: 0 | R79: Sr. Engineer | S79: 3 | T79: 7 | U79: 0 | V79: 0 | W79: 0 | X79: 0 | Y79: 11 | Z79: 0 | AA79: 0 | AB79: 0 | AC79: 0 | AD79: 0 | AE79: 0 | AI79: Sr. Engineer | AJ79: 149 | AK79: 98 | AL79: 88 | AM79: 68 | AN79: 84 | AO79: 53 | AP79: 32 | AQ79: 15 | AR79: 76 | AS79: 88 | AT79: 107 | AU79: 116 | AV79: 29
B80: Engineer | C80: 187 | D80: 0 | E80: 0 | F80: 0 | G80: 0 | H80: 0 | I80: 40 | J80: 0 | K80: 0 | L80: 0 | M80: 0 | N80: 0 | O80: 0 | P80: 0 | R80: Architect | S80: 2 | T80: 2 | U80: 1 | V80: 0 | W80: 0 | X80: 0 | Y80: 0 | Z80: 0 | AA80: 0 | AB80: 0 | AC80: 0 | AD80: 0 | AE80: 0 | AI80: Architect | AJ80: 169 | AK80: 128 | AL80: 118 | AM80: 86 | AN80: 121 | AO80: 82 | AP80: 40 | AQ80: 19 | AR80: 96 | AS80: 132 | AT80: 160 | AU80: 135 | AV80: 34
B81: Sr. Engineer | C81: 225 | D81: 148 | E81: 0 | F81: 0 | G81: 0 | H81: 0 | I81: 48 | J81: 0 | K81: 0 | L81: 0 | M81: 0 | N81: 0 | O81: 0 | P81: 0 | R81: Sr. Architect | S81: 0 | T81: 1 | U81: 0 | V81: 0 | W81: 0 | X81: 0 | Y81: 0 | Z81: 0 | AA81: 0 | AB81: 0 | AC81: 0 | AD81: 0 | AE81: 0 | AI81: Sr. Architect | AJ81: 210 | AK81: 189 | AL81: 147 | AM81: 107 | AN81: 150 | AO81: 102 | AP81: 0 | AQ81: 0 | AR81: 154 | AS81: 0 | AT81: 199 | AU81: 235 | AV81: 0
B82: Architect | C82: 250 | D82: 195 | E82: 178 | F82: 0 | G82: 0 | H82: 0 | I82: 0 | J82: 0 | K82: 0 | L82: 0 | M82: 0 | N82: 0 | O82: 0 | P82: 0 | R82: Consultant | S82: 0 | T82: 3 | U82: 0 | V82: 0 | W82: 0 | X82: 0 | Y82: 0 | Z82: 0 | AA82: 0 | AB82: 0 | AC82: 0 | AD82: 0 | AE82: 0 | AI82: Consultant | AJ82: 0 | AK82: 98 | AL82: 0 | AM82: 0 | AN82: 56 | AO82: 0 | AP82: 25 | AQ82: 0 | AR82: 0 | AS82: 0 | AT82: 0 | AU82: 0 | AV82: 0
B83: Sr. Architect | C83: 0 | D83: 287 | E83: 0 | F83: 0 | G83: 0 | H83: 0 | I83: 0 | J83: 0 | K83: 0 | L83: 0 | M83: 0 | N83: 0 | O83: 0 | P83: 0 | R83: Sr. Consultant | S83: 0 | T83: 2 | U83: 0 | V83: 0 | W83: 0 | X83: 0 | Y83: 0 | Z83: 0 | AA83: 0 | AB83: 0 | AC83: 0 | AD83: 0 | AE83: 0 | AI83: Sr. Consultant | AJ83: 143 | AK83: 142 | AL83: 0 | AM83: 0 | AN83: 103 | AO83: 0 | AP83: 32 | AQ83: 0 | AR83: 0 | AS83: 142 | AT83: 0 | AU83: 0 | AV83: 0
B84: Consultant | C84: 0 | D84: 148 | E84: 0 | F84: 0 | G84: 0 | H84: 0 | I84: 0 | J84: 0 | K84: 0 | L84: 0 | M84: 0 | N84: 0 | O84: 0 | P84: 0 | R84: Developer | S84: 0 | T84: 0 | U84: 0 | V84: 0 | W84: 0 | X84: 0 | Y84: 0 | Z84: 0 | AA84: 0 | AB84: 0 | AC84: 0 | AD84: 0 | AE84: 0 | AI84: Developer | AJ84: 103 | AK84: 78 | AL84: 78 | AM84: 0 | AN84: 0 | AO84: 0 | AP84: 17 | AQ84: 0 | AR84: 0 | AS84: 0 | AT84: 0 | AU84: 0 | AV84: 0
B85: Sr. Consultant | C85: 0 | D85: 215 | E85: 0 | F85: 0 | G85: 0 | H85: 0 | I85: 0 | J85: 0 | K85: 0 | L85: 0 | M85: 0 | N85: 0 | O85: 0 | P85: 0 | R85: Project Coordinator | S85: 0 | T85: 1 | U85: 0 | V85: 0 | W85: 0 | X85: 0 | Y85: 3 | Z85: 0 | AA85: 0 | AB85: 0 | AC85: 0 | AD85: 0 | AE85: 0 | AI85: Project Coordinator | AJ85: 0 | AK85: 42 | AL85: 0 | AM85: 0 | AN85: 0 | AO85: 0 | AP85: 11 | AQ85: 0 | AR85: 0 | AS85: 0 | AT85: 0 | AU85: 0 | AV85: 0
B86: Developer | C86: 0 | D86: 0 | E86: 0 | F86: 0 | G86: 0 | H86: 0 | I86: 0 | J86: 0 | K86: 0 | L86: 0 | M86: 0 | N86: 0 | O86: 0 | P86: 0 | R86: Project Mgr | S86: 0 | T86: 2 | U86: 0 | V86: 0 | W86: 0 | X86: 0 | Y86: 3 | Z86: 0 | AA86: 0 | AB86: 0 | AC86: 0 | AD86: 0 | AE86: 0 | AI86: Project Mgr | AJ86: 99 | AK86: 89 | AL86: 66 | AM86: 40 | AN86: 69 | AO86: 0 | AP86: 27 | AQ86: 0 | AR86: 0 | AS86: 0 | AT86: 0 | AU86: 0 | AV86: 16
B87: Project Coordinator | C87: 0 | D87: 63 | E87: 0 | F87: 0 | G87: 0 | H87: 0 | I87: 17 | J87: 0 | K87: 0 | L87: 0 | M87: 0 | N87: 0 | O87: 0 | P87: 0 | R87: Sr. Proj Mgr | S87: 0 | T87: 1 | U87: 0 | V87: 0 | W87: 0 | X87: 0 | Y87: 0 | Z87: 0 | AA87: 0 | AB87: 0 | AC87: 0 | AD87: 0 | AE87: 0 | AI87: Sr. Proj Mgr | AJ87: 0 | AK87: 106 | AL87: 91 | AM87: 0 | AN87: 88 | AO87: 0 | AP87: 28 | AQ87: 0 | AR87: 0 | AS87: 98 | AT87: 0 | AU87: 88 | AV87: 22
B88: Project Mgr | C88: 0 | D88: 133 | E88: 0 | F88: 0 | G88: 0 | H88: 0 | I88: 40 | J88: 0 | K88: 0 | L88: 0 | M88: 0 | N88: 0 | O88: 0 | P88: 0 | R88: Prog Mgr | S88: 0 | T88: 2 | U88: 0 | V88: 0 | W88: 0 | X88: 0 | Y88: 0 | Z88: 0 | AA88: 0 | AB88: 0 | AC88: 0 | AD88: 0 | AE88: 0 | AI88: Prog Mgr | AJ88: 116 | AK88: 133 | AL88: 129 | AM88: 0 | AN88: 135 | AO88: 27 | AP88: 0 | AQ88: 17 | AR88: 0 | AS88: 121 | AT88: 139 | AU88: 0 | AV88: 0
B89: Sr. Proj Mgr | C89: 0 | D89: 160 | E89: 0 | F89: 0 | G89: 0 | H89: 0 | I89: 0 | J89: 0 | K89: 0 | L89: 0 | M89: 0 | N89: 0 | O89: 0 | P89: 0 | S89: =SUBTOTAL(109,TbCountPvtCld30[US]) -> 7 | T89: =SUBTOTAL(109,TbCountPvtCld30[UK]) -> 21 | U89: =SUBTOTAL(109,TbCountPvtCld30[DE]) -> 1 | V89: =SUBTOTAL(109,TbCountPvtCld30[PL]) -> 0 | W89: =SUBTOTAL(109,TbCountPvtCld30[NL]) -> 0 | X89: =SUBTOTAL(109,TbCountPvtCld30[MX]) -> 0 | Y89: =SUBTOTAL(109,TbCountPvtCld30[IN]) -> 18 | Z89: =SUBTOTAL(109,TbCountPvtCld30[EG]) -> 0 | AA89: =SUBTOTAL(109,TbCountPvtCld30[CAN]) -> 0 | AB89: =SUBTOTAL(109,TbCountPvtCld30[AU]) -> 0 | AC89: =SUBTOTAL(109,TbCountPvtCld30[AE]) -> 0 | AD89: =SUBTOTAL(109,TbCountPvtCld30[SG]) -> 0 | AE89: =SUBTOTAL(109,TbCountPvtCld30[VN]) -> 0 | AG89: =SUM(TbCountPvtCld30[[#Totals],[US]:[VN]]) -> 47
B90: Prog Mgr | C90: 0 | D90: 202 | E90: 0 | F90: 0 | G90: 0 | H90: 0 | I90: 0 | J90: 0 | K90: 0 | L90: 0 | M90: 0 | N90: 0 | O90: 0 | P90: 0
R93: SDAIA Count | S93: US | T93: UK | U93: DE | V93: PL | W93: NL | X93: MX | Y93: IN | Z93: EG | AA93: CAN | AB93: AU | AC93: AE | AD93: SG | AE93: VN | AF93: SA | AI93: SDAIA Alt cost | AJ93: US | AK93: UK | AL93: DE | AM93: PL | AN93: NL | AO93: MX | AP93: IN | AQ93: EG | AR93: CAN | AS93: AU | AT93: AE | AU93: SG | AV93: VN | AW93: SA
R94: Jr. Engineer | S94: 0 | T94: 0 | U94: 0 | V94: 0 | W94: 0 | X94: 0 | Y94: 0 | Z94: 0 | AA94: 0 | AB94: 0 | AC94: 0 | AD94: 0 | AE94: 0 | AF94: 0 | AI94: Jr. Engineer | AJ94: 69 | AK94: 58 | AL94: 61 | AM94: 44 | AN94: 50 | AO94: 30 | AP94: 15 | AQ94: 0 | AR94: 0 | AS94: 54 | AT94: 0 | AU94: 81 | AV94: 0 | AW94: 0
B95: SDAIA Price | C95: US | D95: UK | E95: DE | F95: PL | G95: NL | H95: MX | I95: IN | J95: EG | K95: CAN | L95: AU | M95: AE | N95: SG | O95: VN | P95: SA | R95: Engineer | S95: 0 | T95: 0 | U95: 0 | V95: 0 | W95: 0 | X95: 0 | Y95: 1 | Z95: 0 | AA95: 0 | AB95: 0 | AC95: 1 | AD95: 0 | AE95: 0 | AF95: 0 | AI95: Engineer | AJ95: 96 | AK95: 72 | AL95: 71 | AM95: 56 | AN95: 64 | AO95: 39 | AP95: 25 | AQ95: 9 | AR95: 62 | AS95: 64 | AT95: 75 | AU95: 103 | AV95: 0 | AW95: 0
B96: Jr. Engineer | C96: 0 | D96: 0 | E96: 0 | F96: 0 | G96: 0 | H96: 0 | I96: 0 | J96: 0 | K96: 0 | L96: 0 | M96: 0 | N96: 0 | O96: 0 | P96: 0 | R96: Sr. Engineer | S96: 1 | T96: 0 | U96: 0 | V96: 0 | W96: 0 | X96: 0 | Y96: 1 | Z96: 0 | AA96: 0 | AB96: 0 | AC96: 0 | AD96: 0 | AE96: 0 | AF96: 0 | AI96: Sr. Engineer | AJ96: 89 | AK96: 99 | AL96: 88 | AM96: 68 | AN96: 84 | AO96: 53 | AP96: 43 | AQ96: 15 | AR96: 76 | AS96: 88 | AT96: 107 | AU96: 116 | AV96: 0 | AW96: 0
B97: Engineer | C97: 0 | D97: 0 | E97: 0 | F97: 0 | G97: 0 | H97: 0 | I97: 42 | J97: 0 | K97: 0 | L97: 0 | M97: 125 | N97: 0 | O97: 0 | P97: 0 | R97: Architect | S97: 0 | T97: 0 | U97: 0 | V97: 0 | W97: 0 | X97: 0 | Y97: 0 | Z97: 0 | AA97: 0 | AB97: 0 | AC97: 4 | AD97: 0 | AE97: 0 | AF97: 0 | AI97: Architect | AJ97: 159 | AK97: 122 | AL97: 131 | AM97: 86 | AN97: 121 | AO97: 82 | AP97: 40 | AQ97: 19 | AR97: 96 | AS97: 132 | AT97: 113 | AU97: 135 | AV97: 0 | AW97: 0
B98: Sr. Engineer | C98: 148 | D98: 0 | E98: 0 | F98: 0 | G98: 0 | H98: 0 | I98: 72 | J98: 0 | K98: 0 | L98: 0 | M98: 0 | N98: 0 | O98: 0 | P98: 0 | R98: Sr. Architect | S98: 0 | T98: 0 | U98: 0 | V98: 0 | W98: 0 | X98: 0 | Y98: 1 | Z98: 0 | AA98: 0 | AB98: 0 | AC98: 2 | AD98: 0 | AE98: 0 | AF98: 0 | AI98: Sr. Architect | AJ98: 210 | AK98: 161 | AL98: 173 | AM98: 113 | AN98: 159 | AO98: 108 | AP98: 47 | AQ98: 0 | AR98: 154 | AS98: 0 | AT98: 210 | AU98: 235 | AV98: 0 | AW98: 0
B99: Architect | C99: 0 | D99: 0 | E99: 0 | F99: 0 | G99: 0 | H99: 0 | I99: 0 | J99: 0 | K99: 0 | L99: 0 | M99: 188 | N99: 0 | O99: 0 | P99: 0 | R99: Consultant | S99: 0 | T99: 0 | U99: 0 | V99: 0 | W99: 0 | X99: 0 | Y99: 0 | Z99: 0 | AA99: 0 | AB99: 0 | AC99: 0 | AD99: 0 | AE99: 0 | AF99: 0 | AI99: Consultant | AJ99: 0 | AK99: 84 | AL99: 0 | AM99: 0 | AN99: 72 | AO99: 0 | AP99: 25 | AQ99: 0 | AR99: 0 | AS99: 0 | AT99: 0 | AU99: 0 | AV99: 0 | AW99: 0
B100: Sr. Architect | C100: 0 | D100: 0 | E100: 0 | F100: 0 | G100: 0 | H100: 0 | I100: 78 | J100: 0 | K100: 0 | L100: 0 | M100: 350 | N100: 0 | O100: 0 | P100: 0 | R100: Sr. Consultant | S100: 0 | T100: 0 | U100: 0 | V100: 0 | W100: 0 | X100: 0 | Y100: 0 | Z100: 0 | AA100: 0 | AB100: 0 | AC100: 0 | AD100: 0 | AE100: 0 | AF100: 0 | AI100: Sr. Consultant | AJ100: 143 | AK100: 190 | AL100: 0 | AM100: 0 | AN100: 103 | AO100: 0 | AP100: 32 | AQ100: 0 | AR100: 0 | AS100: 142 | AT100: 0 | AU100: 0 | AV100: 0 | AW100: 0
B101: Consultant | C101: 0 | D101: 0 | E101: 0 | F101: 0 | G101: 0 | H101: 0 | I101: 0 | J101: 0 | K101: 0 | L101: 0 | M101: 0 | N101: 0 | O101: 0 | P101: 0 | R101: Developer | S101: 0 | T101: 0 | U101: 0 | V101: 0 | W101: 0 | X101: 0 | Y101: 0 | Z101: 0 | AA101: 0 | AB101: 0 | AC101: 0 | AD101: 0 | AE101: 0 | AF101: 0 | AI101: Developer | AJ101: 103 | AK101: 78 | AL101: 78 | AM101: 0 | AN101: 0 | AO101: 0 | AP101: 17 | AQ101: 0 | AR101: 0 | AS101: 0 | AT101: 0 | AU101: 0 | AV101: 0 | AW101: 0
B102: Sr. Consultant | C102: 0 | D102: 0 | E102: 0 | F102: 0 | G102: 0 | H102: 0 | I102: 0 | J102: 0 | K102: 0 | L102: 0 | M102: 0 | N102: 0 | O102: 0 | P102: 0 | R102: Project Coordinator | S102: 0 | T102: 0 | U102: 0 | V102: 0 | W102: 0 | X102: 0 | Y102: 0 | Z102: 0 | AA102: 0 | AB102: 0 | AC102: 0 | AD102: 0 | AE102: 0 | AF102: 1 | AI102: Project Coordinator | AJ102: 0 | AK102: 49 | AL102: 0 | AM102: 0 | AN102: 0 | AO102: 0 | AP102: 13 | AQ102: 0 | AR102: 0 | AS102: 0 | AT102: 0 | AU102: 0 | AV102: 0 | AW102: 51
B103: Developer | C103: 0 | D103: 0 | E103: 0 | F103: 0 | G103: 0 | H103: 0 | I103: 0 | J103: 0 | K103: 0 | L103: 0 | M103: 0 | N103: 0 | O103: 0 | P103: 0 | R103: Project Mgr | S103: 0 | T103: 0 | U103: 0 | V103: 0 | W103: 0 | X103: 0 | Y103: 0 | Z103: 0 | AA103: 0 | AB103: 0 | AC103: 0 | AD103: 0 | AE103: 0 | AF103: 0 | AI103: Project Mgr | AJ103: 99 | AK103: 72 | AL103: 66 | AM103: 40 | AN103: 69 | AO103: 0 | AP103: 22 | AQ103: 0 | AR103: 0 | AS103: 0 | AT103: 0 | AU103: 0 | AV103: 0 | AW103: 0
B104: Project Coordinator | C104: 0 | D104: 0 | E104: 0 | F104: 0 | G104: 0 | H104: 0 | I104: 0 | J104: 0 | K104: 0 | L104: 0 | M104: 0 | N104: 0 | O104: 0 | P104: 85 | R104: Sr. Proj Mgr | S104: 0 | T104: 0 | U104: 0 | V104: 0 | W104: 0 | X104: 0 | Y104: 0 | Z104: 0 | AA104: 0 | AB104: 0 | AC104: 1 | AD104: 0 | AE104: 0 | AF104: 1 | AI104: Sr. Proj Mgr | AJ104: 0 | AK104: 94 | AL104: 91 | AM104: 0 | AN104: 88 | AO104: 0 | AP104: 28 | AQ104: 0 | AR104: 0 | AS104: 98 | AT104: 108 | AU104: 88 | AV104: 0 | AW104: 97
B105: Project Mgr | C105: 0 | D105: 0 | E105: 0 | F105: 0 | G105: 0 | H105: 0 | I105: 0 | J105: 0 | K105: 0 | L105: 0 | M105: 0 | N105: 0 | O105: 0 | P105: 0 | R105: Prog Mgr | S105: 0 | T105: 0 | U105: 0 | V105: 0 | W105: 0 | X105: 0 | Y105: 0 | Z105: 0 | AA105: 0 | AB105: 0 | AC105: 0 | AD105: 0 | AE105: 0 | AF105: 1 | AI105: Prog Mgr | AJ105: 116 | AK105: 97 | AL105: 129 | AM105: 0 | AN105: 135 | AO105: 27 | AP105: 0 | AQ105: 17 | AR105: 0 | AS105: 121 | AT105: 139 | AU105: 0 | AV105: 0 | AW105: 192
B106: Sr. Proj Mgr | C106: 0 | D106: 0 | E106: 0 | F106: 0 | G106: 0 | H106: 0 | I106: 0 | J106: 0 | K106: 0 | L106: 0 | M106: 180 | N106: 0 | O106: 0 | P106: 162 | S106: =SUBTOTAL(109,TbCountSdaia31[US]) -> 1 | T106: =SUBTOTAL(109,TbCountSdaia31[UK]) -> 0 | U106: =SUBTOTAL(109,TbCountSdaia31[DE]) -> 0 | V106: =SUBTOTAL(109,TbCountSdaia31[PL]) -> 0 | W106: =SUBTOTAL(109,TbCountSdaia31[NL]) -> 0 | X106: =SUBTOTAL(109,TbCountSdaia31[MX]) -> 0 | Y106: =SUBTOTAL(109,TbCountSdaia31[IN]) -> 3 | Z106: =SUBTOTAL(109,TbCountSdaia31[EG]) -> 0 | AA106: =SUBTOTAL(109,TbCountSdaia31[CAN]) -> 0 | AB106: =SUBTOTAL(109,TbCountSdaia31[AU]) -> 0 | AC106: =SUBTOTAL(109,TbCountSdaia31[AE]) -> 8 | AD106: =SUBTOTAL(109,TbCountSdaia31[SG]) -> 0 | AE106: =SUBTOTAL(109,TbCountSdaia31[VN]) -> 0 | AF106: =SUBTOTAL(109,TbCountSdaia31[SA]) -> 3 | AG106: =SUM(TbCountSdaia31[[#Totals],[US]:[SA]]) -> 15
B107: Prog Mgr | C107: 0 | D107: 0 | E107: 0 | F107: 0 | G107: 0 | H107: 0 | I107: 0 | J107: 0 | K107: 0 | L107: 0 | M107: 0 | N107: 0 | O107: 0 | P107: 320
R110: ERP Count | S110: US | T110: UK | U110: DE | V110: PL | W110: NL | X110: MX | Y110: IN | Z110: EG | AA110: CAN | AB110: AU | AC110: AE | AD110: SG | AE110: VN | AI110: ERP Alt Cost | AJ110: US | AK110: UK | AL110: DE | AM110: PL | AN110: NL | AO110: MX | AP110: IN | AQ110: EG | AR110: CAN | AS110: AU | AT110: AE | AU110: SG | AV110: VN
R111: Jr. Engineer | S111: 0 | T111: 0 | U111: 0 | V111: 0 | W111: 0 | X111: 0 | Y111: 0 | Z111: 0 | AA111: 0 | AB111: 0 | AC111: 0 | AD111: 0 | AE111: 0 | AI111: Jr. Engineer | AJ111: 69 | AK111: 58 | AL111: 61 | AM111: 44 | AN111: 50 | AO111: 30 | AP111: 15 | AQ111: 0 | AR111: 0 | AS111: 54 | AT111: 0 | AU111: 81 | AV111: 15
B112: ERP Price | C112: US | D112: UK | E112: DE | F112: PL | G112: NL | H112: MX | I112: IN | J112: EG | K112: CAN | L112: AU | M112: AE | N112: SG | O112: VN | P112: SA | R112: Engineer | S112: 0 | T112: 0 | U112: 0 | V112: 0 | W112: 0 | X112: 0 | Y112: 0 | Z112: 0 | AA112: 0 | AB112: 0 | AC112: 0 | AD112: 0 | AE112: 0 | AI112: Engineer | AJ112: 96 | AK112: 72 | AL112: 71 | AM112: 56 | AN112: 64 | AO112: 39 | AP112: 20 | AQ112: 9 | AR112: 62 | AS112: 64 | AT112: 88 | AU112: 103 | AV112: 21
B113: Jr. Engineer | C113: 0 | D113: 0 | E113: 0 | F113: 0 | G113: 0 | H113: 0 | I113: 0 | J113: 0 | K113: 0 | L113: 0 | M113: 0 | N113: 0 | O113: 0 | P113: 0 | R113: Sr. Engineer | S113: 0 | T113: 0 | U113: 0 | V113: 0 | W113: 0 | X113: 0 | Y113: 0 | Z113: 0 | AA113: 0 | AB113: 0 | AC113: 0 | AD113: 0 | AE113: 0 | AI113: Sr. Engineer | AJ113: 125 | AK113: 99 | AL113: 88 | AM113: 68 | AN113: 84 | AO113: 53 | AP113: 32 | AQ113: 15 | AR113: 76 | AS113: 88 | AT113: 107 | AU113: 116 | AV113: 29
B114: Engineer | C114: 0 | D114: 0 | E114: 0 | F114: 0 | G114: 0 | H114: 0 | I114: 0 | J114: 0 | K114: 0 | L114: 0 | M114: 0 | N114: 0 | O114: 0 | P114: 0 | R114: Architect | S114: 0 | T114: 0 | U114: 0 | V114: 0 | W114: 0 | X114: 0 | Y114: 0 | Z114: 0 | AA114: 0 | AB114: 0 | AC114: 0 | AD114: 0 | AE114: 0 | AI114: Architect | AJ114: 159 | AK114: 122 | AL114: 131 | AM114: 86 | AN114: 121 | AO114: 82 | AP114: 40 | AQ114: 19 | AR114: 96 | AS114: 132 | AT114: 160 | AU114: 135 | AV114: 34
B115: Sr. Engineer | C115: 0 | D115: 0 | E115: 0 | F115: 0 | G115: 0 | H115: 0 | I115: 0 | J115: 0 | K115: 0 | L115: 0 | M115: 0 | N115: 0 | O115: 0 | P115: 0 | R115: Sr. Architect | S115: 0 | T115: 0 | U115: 0 | V115: 0 | W115: 0 | X115: 1 | Y115: 0 | Z115: 0 | AA115: 0 | AB115: 0 | AC115: 0 | AD115: 0 | AE115: 0 | AI115: Sr. Architect | AJ115: 210 | AK115: 161 | AL115: 173 | AM115: 113 | AN115: 159 | AO115: 108 | AP115: 0 | AQ115: 0 | AR115: 154 | AS115: 0 | AT115: 212 | AU115: 235 | AV115: 0
B116: Architect | C116: 0 | D116: 0 | E116: 0 | F116: 0 | G116: 0 | H116: 0 | I116: 0 | J116: 0 | K116: 0 | L116: 0 | M116: 0 | N116: 0 | O116: 0 | P116: 0 | R116: Consultant | S116: 1 | T116: 0 | U116: 0 | V116: 0 | W116: 0 | X116: 0 | Y116: 5 | Z116: 0 | AA116: 0 | AB116: 0 | AC116: 0 | AD116: 0 | AE116: 0 | AI116: Consultant | AJ116: 88 | AK116: 84 | AL116: 0 | AM116: 0 | AN116: 72 | AO116: 0 | AP116: 18 | AQ116: 0 | AR116: 0 | AS116: 0 | AT116: 0 | AU116: 0 | AV116: 0
B117: Sr. Architect | C117: 0 | D117: 0 | E117: 0 | F117: 0 | G117: 0 | H117: 158 | I117: 0 | J117: 0 | K117: 0 | L117: 0 | M117: 0 | N117: 0 | O117: 0 | P117: 0 | R117: Sr. Consultant | S117: 9 | T117: 0 | U117: 0 | V117: 0 | W117: 0 | X117: 0 | Y117: 15 | Z117: 0 | AA117: 0 | AB117: 0 | AC117: 0 | AD117: 0 | AE117: 0 | AI117: Sr. Consultant | AJ117: 136 | AK117: 190 | AL117: 0 | AM117: 0 | AN117: 103 | AO117: 0 | AP117: 34 | AQ117: 0 | AR117: 0 | AS117: 142 | AT117: 0 | AU117: 0 | AV117: 0
B118: Consultant | C118: 147 | D118: 0 | E118: 0 | F118: 0 | G118: 0 | H118: 0 | I118: 30 | J118: 0 | K118: 0 | L118: 0 | M118: 0 | N118: 0 | O118: 0 | P118: 0 | R118: Developer | S118: 1 | T118: 0 | U118: 0 | V118: 0 | W118: 0 | X118: 0 | Y118: 0 | Z118: 0 | AA118: 0 | AB118: 0 | AC118: 0 | AD118: 0 | AE118: 0 | AI118: Developer | AJ118: 81 | AK118: 78 | AL118: 78 | AM118: 0 | AN118: 0 | AO118: 0 | AP118: 17 | AQ118: 0 | AR118: 0 | AS118: 0 | AT118: 0 | AU118: 0 | AV118: 0
B119: Sr. Consultant | C119: 227 | D119: 0 | E119: 0 | F119: 0 | G119: 0 | H119: 0 | I119: 57 | J119: 0 | K119: 0 | L119: 0 | M119: 0 | N119: 0 | O119: 0 | P119: 0 | R119: Project Coordinator | S119: 0 | T119: 0 | U119: 0 | V119: 0 | W119: 0 | X119: 0 | Y119: 0 | Z119: 0 | AA119: 0 | AB119: 0 | AC119: 0 | AD119: 0 | AE119: 0 | AI119: Project Coordinator | AJ119: 0 | AK119: 49 | AL119: 0 | AM119: 0 | AN119: 0 | AO119: 0 | AP119: 13 | AQ119: 0 | AR119: 0 | AS119: 0 | AT119: 0 | AU119: 0 | AV119: 0
B120: Developer | C120: 135 | D120: 0 | E120: 0 | F120: 0 | G120: 0 | H120: 0 | I120: 0 | J120: 0 | K120: 0 | L120: 0 | M120: 0 | N120: 0 | O120: 0 | P120: 0 | R120: Project Mgr | S120: 0 | T120: 0 | U120: 0 | V120: 0 | W120: 0 | X120: 0 | Y120: 0 | Z120: 0 | AA120: 0 | AB120: 0 | AC120: 0 | AD120: 0 | AE120: 0 | AI120: Project Mgr | AJ120: 99 | AK120: 72 | AL120: 66 | AM120: 40 | AN120: 69 | AO120: 0 | AP120: 22 | AQ120: 0 | AR120: 0 | AS120: 0 | AT120: 0 | AU120: 0 | AV120: 16
B121: Project Coordinator | C121: 0 | D121: 0 | E121: 0 | F121: 0 | G121: 0 | H121: 0 | I121: 0 | J121: 0 | K121: 0 | L121: 0 | M121: 0 | N121: 0 | O121: 0 | P121: 0 | R121: Sr. Proj Mgr | S121: 0 | T121: 0 | U121: 0 | V121: 0 | W121: 0 | X121: 0 | Y121: 0 | Z121: 0 | AA121: 0 | AB121: 0 | AC121: 0 | AD121: 0 | AE121: 0 | AI121: Sr. Proj Mgr | AJ121: 0 | AK121: 94 | AL121: 91 | AM121: 0 | AN121: 88 | AO121: 0 | AP121: 28 | AQ121: 0 | AR121: 0 | AS121: 98 | AT121: 0 | AU121: 88 | AV121: 22
B122: Project Mgr | C122: 0 | D122: 0 | E122: 0 | F122: 0 | G122: 0 | H122: 0 | I122: 0 | J122: 0 | K122: 0 | L122: 0 | M122: 0 | N122: 0 | O122: 0 | P122: 0 | R122: Prog Mgr | S122: 1 | T122: 0 | U122: 0 | V122: 0 | W122: 0 | X122: 0 | Y122: 0 | Z122: 0 | AA122: 0 | AB122: 0 | AC122: 0 | AD122: 0 | AE122: 0 | AI122: Prog Mgr | AJ122: 141 | AK122: 97 | AL122: 129 | AM122: 0 | AN122: 135 | AO122: 27 | AP122: 0 | AQ122: 17 | AR122: 0 | AS122: 121 | AT122: 139 | AU122: 0 | AV122: 0
